Workbook
Name w: #REF!

Sheet Master
A1: Database
A2: Harga Bahan, Alat & Perlengkapan
A3: The Soko Coffee Tea Chocolate
B5: 1 | C5: 2 | D5: 3 | E5: 4 | F5: 5 | G5: 6 | H5: 7 | I5: 8 | J5: 9 | K5: 10 | L5: 11 | M5: 12 | N5: 13
A6: No | B6: Remark | C6: Kode | D6: Divisi | E6: Sub Divisi | F6: Jenis | G6: Price (Rp) | H6: Unit Pack | I6: Qty | J6: Unit | K6: Price/Unit | L6: Toko Belanja | M6: Jenis Belanja | N6: Keterangan | P6: Divisi | R6: Kategori | T6: Kategori Menu | V6: Menu | W6: SKU | Y6: Jenis Bahan | AA6: Unit Pack | AC6: Toko Belanja | AD6: Sales PIC | AE6: Alamat | AF6: No Hp / WA | AG6: Jenis Belanja | AH6: Ket. Barang Masuk
A7: 1 | B7: Ktc Pro Acar | C7: P01 | D7: Kitchen | E7: KTC Kitchen | G7: =VLOOKUP(B7,'Production Kitchen'!$B$5:$L$1029,10,FALSE) -> 321.82692 | I7: 1 | J7: ml | K7: =G7/I7 -> 321.82692 | P7: Office | R7: Bahan Kopi | T7: Coffee | V7: Cappucino Hot | W7: M0001 | Y7: Bar Coffee | AA7: Kilogram | AC7: PT Sukanda Djaya | AD7: Kang Ahmat | AF7: 085157020709 | AG7: Supplier | AH7: H+1
A8: =A7+1 -> 2 | B8: Ktc Pro Bawang Goreng | C8: P02 | D8: Kitchen | E8: KTC Kitchen | G8: =VLOOKUP(B8,'Production Kitchen'!$B$5:$L$1029,10,FALSE) -> 450.70667 | I8: 1 | J8: gr/por | K8: =G8/I8 -> 450.70667 | P8: Marketing | R8: Bahan Non-Kopi | T8: Manual Brewing | V8: Cappucino Ice | W8: M0002 | Y8: Bar Powder | AA8: Can | AC8: Danone | AG8: Supplier | AH8: Setiap Jumat, Tagihan Akhir Bulan
A9: =A8+1 -> 3 | B9: Ktc Pro Cream Soup | C9: P03 | D9: Kitchen | E9: KTC Kitchen | G9: =VLOOKUP(B9,'Production Kitchen'!$B$5:$L$1029,10,FALSE) -> 5583.677 | I9: 1 | J9: gr/ml | K9: =G9/I9 -> 5583.677 | P9: Floor | R9: Bahan Kitchen | T9: Chocolate & Tea | V9: Iced Cafe Latte | W9: M0003 | Y9: Bar Syrup Puree Concentrate | AA9: Pack | AC9: PT Fatarindo Cemerlang | AD9: Dedi | AF9: 081222294407 | AG9: Supplier | AH9: Setiap Rabu, Langsung Bayar
A10: =A9+1 -> 4 | B10: Ktc Pro Sauce Blackpepper | C10: P04 | D10: Kitchen | E10: KTC Kitchen | G10: =VLOOKUP(B10,'Production Kitchen'!$B$5:$L$1029,10,FALSE) -> 1363.1871 | I10: 1 | J10: gr/por | K10: =G10/I10 -> 1363.1871 | P10: Gudang Pusat | R10: Bahan Dessert & Bakery | T10: Milk Base | V10: Hot Cafe Latte | W10: M0004 | Y10: Bar Milk | AA10: Bag | AC10: LMK | AF10: 081322588522 | AG10: Supplier
A11: =A10+1 -> 5 | B11: Ktc Pro Pancake | C11: P05 | D11: Kitchen | E11: KTC Kitchen | G11: =VLOOKUP(B11,'Production Kitchen'!$B$5:$L$1029,10,FALSE) -> 5764.8067 | I11: 1 | J11: gr/slice | K11: =G11/I11 -> 5764.8067 | P11: Bar | R11: Bahan Bar | T11: Mocktail & Squash | V11: Hot Americano | W11: M0005 | Y11: Bar Tea | AA11: Pail | AC11: Toffico | AG11: Supplier
A12: =A11+1 -> 6 | B12: Ktc Pro Choco Lava | C12: P06 | D12: Kitchen | E12: KTC Kitchen | G12: =VLOOKUP(B12,'Production Kitchen'!$B$5:$L$1029,10,FALSE) -> 4952.75 | I12: 1 | J12: gr/por | K12: =G12/I12 -> 4952.75 | P12: Dessert & Bakery | R12: KTC Bar | T12: Signature | V12: Iced Americano | W12: M0006 | Y12: Bar Water | AA12: Bottle | AC12: PD Sentosa | AD12: Sendi | AF12: 085799626000 | AG12: Supplier
A13: =A12+1 -> 7 | B13: Ktc Pro Sauce Barbeque | C13: P07 | D13: Kitchen | E13: KTC Kitchen | G13: =VLOOKUP(B13,'Production Kitchen'!$B$5:$L$1029,10,FALSE) -> 537.32381 | I13: 1 | J13: Porsi | K13: =G13/I13 -> 537.32381 | P13: Kitchen | R13: KTC Kitchen | T13: Main Course & Bowl | V13: Hot Moccacino | W13: M0007 | Y13: Bar Fruit | AA13: Galon | AC13: Dillco Group | AD13: Iqbal | AF13: 089663452433 | AG13: Supplier
A14: =A13+1 -> 8 | B14: Ktc Pro Sauce Bolognaise | C14: P08 | D14: Kitchen | E14: KTC Kitchen | G14: =VLOOKUP(B14,'Production Kitchen'!$B$5:$L$1029,10,FALSE) -> 2300.1407 | I14: 1 | J14: gr/pcs | K14: =G14/I14 -> 2300.1407 | P14: Bar & Kitchen | R14: KTC Dessert & Bakery | T14: Light Meals | V14: Iced Moccacino | W14: M0008 | Y14: Bar Groceries | AA14: Crat | AC14: Woodlane | AD14: Vikar | AF14: 081324510971 | AG14: Supplier
A15: =A14+1 -> 9 | B15: Ktc Pro White Sauce | C15: P09 | D15: Kitchen | E15: KTC Kitchen | G15: =VLOOKUP(B15,'Production Kitchen'!$B$5:$L$1029,10,FALSE) -> 1883.9883 | I15: 1 | J15: gr/por | K15: =G15/I15 -> 1883.9883 | P15: - | R15: Packing Bar | T15: Pizza & Pasta | V15: Hazelnut Latte Hot | W15: M0009 | Y15: Bar Packing | AA15: Tabung | AC15: Havilla Tea | AF15: 081221689133 | AG15: Supplier | AH15: Operasional Di Atas jam5 Sore
A16: =A15+1 -> 10 | B16: Ktc Pro RU Sauce | C16: P10 | D16: Kitchen | E16: KTC Kitchen | G16: =VLOOKUP(B16,'Production Kitchen'!$B$5:$L$1029,10,FALSE) -> 320.99737 | I16: 1 | J16: gr | K16: =G16/I16 -> 320.99737 | R16: Packing Kitchen | T16: Desserts | V16: Hazelnut Latte Ice | W16: M0010 | Y16: Ktc Meat | AA16: Dus | AC16: Geraldi Risol | AG16: Supplier
A17: =A16+1 -> 11 | B17: Ktc Pro Dough Pizza | C17: P11 | D17: Kitchen | E17: KTC Kitchen | G17: =VLOOKUP(B17,'Production Kitchen'!$B$5:$L$1029,10,FALSE) -> 2108.7129 | I17: 1 | J17: gr | K17: =G17/I17 -> 2108.7129 | R17: Packing Dessert & Bakery | T17: Menu Nusantara | V17: Hot Vanilla Latte | W17: M0011 | Y17: Ktc Vegetables | AC17: HOC | AG17: Supplier
A18: =A17+1 -> 12 | B18: Ktc Pro Sauce Moza | C18: P12 | D18: Kitchen | E18: KTC Kitchen | G18: =VLOOKUP(B18,'Production Kitchen'!$B$5:$L$1029,10,FALSE) -> 4554 | I18: 1 | J18: gr | K18: =G18/I18 -> 4554 | R18: Bahan Bar & Kitchen | T18: Menu Catering | V18: Iced Vanilla Latte | W18: M0012 | Y18: Ktc Bread Biscuit | AC18: Arghani | AF18: 087777112108 | AG18: Supplier
A19: =A18+1 -> 13 | B19: Tahu sambal kecap | C19: P13 | D19: Kitchen | E19: KTC Kitchen | G19: =VLOOKUP(B19,'Menu Kitchen'!$B$5:$K$2098,8,FALSE) -> 3809.2312 | I19: 1 | J19: gr | K19: =G19/I19 -> 3809.2312 | R19: BB Lain-lain | T19: Extra Kitchen | V19: Affogato | W19: M0013 | Y19: Ktc Groceries | AC19: Eden Farm | AD19: Lilis | AF19: 081383888715 | AG19: Distributor
A20: =A19+1 -> 14 | B20: Ktc Pro Sauce Bumbu Rujak | C20: P14 | D20: Kitchen | E20: KTC Kitchen | G20: =VLOOKUP(B20,'Production Kitchen'!$B$5:$L$1029,10,FALSE) -> 814.81481 | I20: 1 | J20: gr/slice | K20: =G20/I20 -> 814.81481 | R20: ATK | T20: KTC Bar | V20: Coconut Cream | W20: M0014 | Y20: Ktc Packing | AC20: Feri Supriadi (Telur , Beras , Minyak ) | AD20: Feri | AF20: 081312570820 | AG20: Distributor
A21: =A20+1 -> 15 | B21: Bakwan jagung sambal kecap | C21: P15 | D21: Kitchen | E21: KTC Kitchen | G21: =VLOOKUP(B21,'Menu Kitchen'!$B$5:$K$2098,8,FALSE) -> 5258.4812 | I21: 1 | J21: gr | K21: =G21/I21 -> 5258.4812 | R21: Service Mesin | T21: KTC Dessert & Bakery | V21: Es Kopi Soko | W21: M0015 | Y21: OP Groceries | AC21: BISS (Topside) | AD21: Ayu | AF21: 087736858365 | AG21: Supplier
A22: =A21+1 -> 16 | B22: Ktc Pro Cheese Sauce | C22: P16 | D22: Kitchen | E22: KTC Kitchen | G22: =VLOOKUP(B22,'Production Kitchen'!$B$5:$L$1029,10,FALSE) -> 1773.7816 | I22: 1 | J22: gr | K22: =G22/I22 -> 1773.7816 | R22: Bensin, Parkir, Transport | T22: KTC Kitchen | V22: Spring Berry Ice | W22: M0016 | AC22: Prima (Topside) | AD22: Maudi | AF22: 082116418738 | AG22: Supplier
A23: =A22+1 -> 17 | B23: Ktc Pro Onion Rings | C23: P17 | D23: Kitchen | E23: KTC Kitchen | G23: =VLOOKUP(B23,'Production Kitchen'!$B$5:$L$1029,10,FALSE) -> 2959 | I23: 1 | J23: gr | K23: =G23/I23 -> 2959 | R23: Internet | V23: Hot Chocolate | W23: M0017 | AC23: Sasakala Coffee | AD23: Dadang | AF23: 082240047008 | AG23: Supplier
A24: =A23+1 -> 18 | B24: Ktc Pro Macaroni Boiled | C24: P18 | D24: Kitchen | E24: KTC Kitchen | G24: =VLOOKUP(B24,'Production Kitchen'!$B$5:$L$1029,10,FALSE) -> 1593.8513 | I24: 1 | J24: gr | K24: =G24/I24 -> 1593.8513 | R24: Gas | V24: Iced Chocolate | W24: M0018 | AC24: Lingga Jaya Pack | AD24: Rohman | AF24: 082115563437 | AG24: Supplier
A25: =A24+1 -> 19 | B25: Ktc Pro Fettucini Boiled | C25: P19 | D25: Kitchen | E25: KTC Kitchen | G25: =VLOOKUP(B25,'Production Kitchen'!$B$5:$L$1029,10,FALSE) -> 1890.9279 | I25: 1 | J25: gr | K25: =G25/I25 -> 1890.9279 | R25: Kebersihan | V25: Choconutt Ice | W25: M0019 | AC25: Emergency Syrup | AD25: Denis | AF25: 081770555515 | AG25: Supplier
A26: =A25+1 -> 20 | B26: Ktc Pro Egg Wash | C26: P20 | D26: Kitchen | E26: KTC Kitchen | G26: =VLOOKUP(B26,'Production Kitchen'!$B$5:$L$1029,10,FALSE) -> 5.3734893 | I26: 1 | J26: gr | K26: =G26/I26 -> 5.3734893 | R26: Keamanan | V26: Naga Black Tea Hot | W26: M0020 | AC26: Ade Widya Plastik Cikutra | AF26: 082121297077 | AG26: Distributor
A27: =A26+1 -> 21 | B27: Ktc Pro Wings Marinate | C27: P21 | D27: Kitchen | E27: KTC Kitchen | G27: =VLOOKUP(B27,'Production Kitchen'!$B$5:$L$1029,10,FALSE) -> 8819.8396 | I27: 1 | J27: Porsi | K27: =G27/I27 -> 8819.8396 | R27: Service Listrik | V27: Naga Black Tea Ice | W27: M0021 | AC27: Kartu Empat Dimensi | AF27: 089528832388 | AG27: Distributor
A28: =A27+1 -> 22 | B28: Ktc Pro Concase | C28: P22 | D28: Kitchen | E28: KTC Kitchen | G28: =VLOOKUP(B28,'Production Kitchen'!$B$5:$L$1029,10,FALSE) -> 500.46874 | I28: 1 | J28: gr | K28: =G28/I28 -> 500.46874 | R28: Peralatan | V28: Thai Tea Hot | W28: M0022 | AC28: My Packaging | Tokopedia | AE28: link Tokped | AG28: Distributor
A29: =A28+1 -> 23 | B29: Ktc Pro Spaghetti Boiled | C29: P23 | D29: Kitchen | E29: KTC Kitchen | G29: =VLOOKUP(B29,'Production Kitchen'!$B$5:$L$1029,10,FALSE) -> 1601.7222 | I29: 1 | J29: gr/pcs | K29: =G29/I29 -> 1601.7222 | R29: OP Lain-lain | V29: Thai Tea Ice | W29: M0023 | AC29: Adijaya Mozzarella | AD29: Lala | AF29: 089530715802 | AG29: Supplier
A30: =A29+1 -> 24 | B30: Ktc Pro Rice | C30: P24 | D30: Kitchen | E30: KTC Kitchen | G30: =VLOOKUP(B30,'Production Kitchen'!$B$5:$L$1029,10,FALSE) -> 1093.9891 | I30: 1 | J30: Porsi | K30: =G30/I30 -> 1093.9891 | R30: Mutasi | T30: - | V30: Premium Tea Hot | W30: M0024 | AC30: Distributor Daging Pasar Cihapit | AD30: Tono | AF30: 081394412566 | AG30: Distributor
A31: =A30+1 -> 25 | B31: Ktc Pro Ayam Suwir | C31: P25 | D31: Kitchen | E31: KTC Kitchen | G31: =VLOOKUP(B31,'Production Kitchen'!$B$5:$L$1029,10,FALSE) -> 1114.5895 | I31: 1 | J31: gr | K31: =G31/I31 -> 1114.5895 | R31: KOL | V31: Taro Latte Hot | W31: M0025 | AC31: PD Aroma Jaya | AD31: Andri | AF31: 08882234984 | AG31: Distributor
A32: =A31+1 -> 26 | B32: KTC Pro Bumbu Magic | C32: P26 | D32: Kitchen | E32: KTC Kitchen | G32: =VLOOKUP(B32,'Production Kitchen'!$B$5:$L$1029,10,FALSE) -> 58.9875 | I32: 1 | J32: Porsi | K32: =G32/I32 -> 58.9875 | R32: Online Marketing | V32: Taro Latte Ice | W32: M0026 | AC32: Limas Raga Inti | AF32: 082121210600 | AG32: Distributor | AH32: gas
A33: =A32+1 -> 27 | B33: Ktc Pro Katsu Chicken | C33: P27 | D33: Kitchen | E33: KTC Kitchen | G33: =VLOOKUP(B33,'Production Kitchen'!$B$5:$L$1029,10,FALSE) -> 4805.2125 | I33: 1 | J33: gr | K33: =G33/I33 -> 4805.2125 | R33: Offline Marketing | V33: Matcha Latte Hot | W33: M0027 | AC33: B5 Coffee & Roastery | AE33: Jl.Bangbayang No.5 Dago Bandung | AF33: 081321534165 | AG33: Distributor
A34: =A33+1 -> 28 | B34: KTC Pro Scrumble Egg | C34: P28 | D34: Kitchen | E34: KTC Kitchen | G34: =VLOOKUP(B34,'Production Kitchen'!$B$5:$L$1029,10,FALSE) -> 2570.7587 | I34: 1 | J34: gr/pcs | K34: =G34/I34 -> 2570.7587 | R34: Renovasi & Furniture | V34: Matcha Latte Ice | W34: M0028 | AC34: Toko PD Cihapit | AG34: Direct
A35: =A34+1 -> 29 | B35: Ktc Pro Mushroom Crispy | C35: P29 | D35: Kitchen | E35: KTC Kitchen | G35: =VLOOKUP(B35,'Production Kitchen'!$B$5:$L$1029,10,FALSE) -> 6194.8333 | I35: 1 | J35: gr/pcs | K35: =G35/I35 -> 6194.8333 | R35: Piutang Karyawan | V35: Red Velvet Hot | W35: M0029 | AC35: Bara Gas | AG35: Direct
A36: =A35+1 -> 30 | B36: KTC Pro Mix Vegetable | C36: P30 | D36: Kitchen | E36: KTC Kitchen | G36: =VLOOKUP(B36,'Production Kitchen'!$B$5:$L$1029,10,FALSE) -> 864.65116 | I36: 1 | J36: gr/pcs | K36: =G36/I36 -> 864.65116 | R36: Hutang | V36: Red Velvet Ice | W36: M0030 | AC36: Borma | AG36: Direct
A37: =A36+1 -> 31 | B37: Ktc Pro Chicken Cordon Bleu | C37: P31 | D37: Kitchen | E37: KTC Kitchen | G37: =VLOOKUP(B37,'Production Kitchen'!$B$5:$L$1029,10,FALSE) -> 5399.9 | I37: 1 | J37: gr/pcs | K37: =G37/I37 -> 5399.9 | R37: Perlengkapan | V37: Lemon Squash | W37: M0031 | AC37: Pasar Cihapit | AG37: Direct
A38: =A37+1 -> 32 | B38: KTC Bumbu Oles Sate | C38: P32 | D38: Kitchen | E38: KTC Kitchen | G38: =VLOOKUP(B38,'Production Kitchen'!$B$5:$L$1029,10,FALSE) -> 65.385653 | I38: 1 | J38: pcs | K38: =G38/I38 -> 65.385653 | R38: Investasi | V38: Orange Squash | W38: M0032 | AC38: Setiabudi Market | AG38: Direct
A39: =A38+1 -> 33 | B39: KTC Pro Mix Platters | C39: P33 | D39: Kitchen | E39: KTC Kitchen | G39: =VLOOKUP(B39,'Production Kitchen'!$B$5:$L$1029,10,FALSE) -> 8481 | I39: 1 | J39: pcs | K39: =G39/I39 -> 8481 | R39: Sewa | V39: Mineral Water | W39: M0033 | AC39: Putra Asmi, Dago | AG39: Direct
A40: =A39+1 -> 34 | B40: KTC Pro Bumbu Bakar Oles | C40: P34 | D40: Kitchen | E40: KTC Kitchen | G40: =VLOOKUP(B40,'Production Kitchen'!$B$5:$L$1029,10,FALSE) -> 766.22625 | I40: 1 | J40: pcs | K40: =G40/I40 -> 766.22625 | R40: - | V40: Karma Coffee | W40: M0034 | AC40: RSB, Dago | AG40: Direct
A41: =A40+1 -> 35 | B41: KTC Pro Tempe Ungkep | C41: P35 | D41: Kitchen | E41: KTC Kitchen | G41: =VLOOKUP(B41,'Production Kitchen'!$B$5:$L$1029,10,FALSE) -> 275 | I41: 1 | J41: pcs | K41: =G41/I41 -> 275 | V41: Soko Mint | W41: M0035 | AC41: Shopee | AG41: Direct
A42: =A41+1 -> 36 | B42: Sate Telur Puyuh | C42: S001 | D42: Kitchen | E42: KTC Kitchen | G42: =VLOOKUP(B42,'Production Kitchen'!$B$5:$L$1029,10,FALSE) -> 1620.3422 | I42: 1 | J42: pcs | K42: =G42/I42 -> 1620.3422 | V42: Dreamy Berry | W42: M0036 | AC42: Tokopedia | AG42: Direct
A43: =A42+1 -> 37 | B43: Sate Jando | C43: S002 | D43: Kitchen | E43: KTC Kitchen | G43: =VLOOKUP(B43,'Production Kitchen'!$B$5:$L$1029,10,FALSE) -> 1296.7193 | I43: 1 | J43: pcs | K43: =G43/I43 -> 1296.7193 | V43: Sunfield Green | W43: M0037 | AC43: CMYK | AG43: Direct
A44: =A43+1 -> 38 | B44: Sate Usus | C44: S003 | D44: Kitchen | E44: KTC Kitchen | G44: =VLOOKUP(B44,'Production Kitchen'!$B$5:$L$1029,10,FALSE) -> 1053.4387 | I44: 1 | J44: pcs | K44: =G44/I44 -> 1053.4387 | V44: V60 Lokal | W44: M0038 | AC44: Otten Coffee | AG44: Direct
A45: =A44+1 -> 39 | B45: Sate Kulit | C45: S004 | D45: Kitchen | E45: KTC Kitchen | G45: =VLOOKUP(B45,'Production Kitchen'!$B$5:$L$1029,10,FALSE) -> 797.86044 | I45: 1 | J45: pcs | K45: =G45/I45 -> 797.86044 | V45: Japanese Lokal | W45: M0039 | AC45: Toserba Yogya | AG45: Direct
A46: =A45+1 -> 40 | B46: Sate Paru | C46: S005 | D46: Kitchen | E46: KTC Kitchen | G46: =VLOOKUP(B46,'Production Kitchen'!$B$5:$L$1029,10,FALSE) -> 1341.4338 | I46: 1 | J46: pcs | K46: =G46/I46 -> 1341.4338 | V46: Flat bottom Lokal | W46: M0040 | AC46: Atlas | AG46: Direct
A47: =A46+1 -> 41 | B47: Sate Ati Ampela | C47: S006 | D47: Kitchen | E47: KTC Kitchen | G47: =VLOOKUP(B47,'Production Kitchen'!$B$5:$L$1029,10,FALSE) -> 1193.8488 | I47: 1 | J47: pcs | K47: =G47/I47 -> 1193.8488 | V47: French press | W47: M0041 | AC47: Kurnia Mas | AG47: Direct
A48: =A47+1 -> 42 | B48: Sate Kikil | C48: S007 | D48: Kitchen | E48: KTC Kitchen | G48: =VLOOKUP(B48,'Production Kitchen'!$B$5:$L$1029,10,FALSE) -> 501.69301 | I48: 1 | J48: pcs | K48: =G48/I48 -> 501.69301 | V48: Aeropress Lokal | W48: M0042 | AC48: PD Cihapit | AG48: Direct
A49: =A48+1 -> 43 | B49: Bar Pro Chrysantemum | C49: P33 | D49: Bar | E49: KTC Bar | G49: =VLOOKUP(B49,'Production Bar'!$B$5:$L$1000,10,FALSE) -> 31.271842 | I49: 1 | J49: gr/pcs | K49: =G49/I49 -> 31.271842 | V49: Hot Vietnam Drip | W49: M0043 | AC49: The Soko | AG49: Direct
A50: =A49+1 -> 44 | B50: Bar Pro espresso | C50: P34 | D50: Bar | E50: KTC Bar | G50: =VLOOKUP(B50,'Production Bar'!$B$5:$L$1000,10,FALSE) -> 3915.9158 | I50: 1 | J50: porsi | K50: =G50/I50 -> 3915.9158 | V50: Iced Vietnam drip | W50: M0044 | AC50: Garnish Kering | AF50: 081220892963 | AG50: Direct
A51: =A50+1 -> 45 | B51: Bar Pro Rosella | C51: P35 | D51: Bar | E51: KTC Bar | G51: =VLOOKUP(B51,'Production Bar'!$B$5:$L$1000,10,FALSE) -> 17.411842 | I51: 1 | J51: gr/slice | K51: =G51/I51 -> 17.411842 | V51: Tubruk | W51: M0045 | AC51: Toko Lain | AG51: Direct
A52: =A51+1 -> 46 | B52: Bar Pro Cengkeh | C52: P36 | D52: Bar | E52: KTC Bar | G52: =VLOOKUP(B52,'Production Bar'!$B$5:$L$1000,10,FALSE) -> 23.865947 | I52: 1 | J52: gr | K52: =G52/I52 -> 23.865947 | V52: Ice cream | W52: M0046
A53: =A52+1 -> 47 | B53: Bar Pro Simple Syrup | C53: P37 | D53: Bar | E53: KTC Bar | G53: =VLOOKUP(B53,'Production Bar'!$B$5:$L$1000,10,FALSE) -> 15.983579 | I53: 1 | J53: ml | K53: =G53/I53 -> 15.983579 | V53: Extra Espresso | W53: M0047
A54: =A53+1 -> 48 | B54: Bar Pro Black Tea | C54: P38 | D54: Bar | E54: KTC Bar | G54: =VLOOKUP(B54,'Production Bar'!$B$5:$L$1000,10,FALSE) -> 1.1915702 | I54: 1 | J54: ml | K54: =G54/I54 -> 1.1915702 | V54: Charcoal Latte Ice | W54: M0048
A55: =A54+1 -> 49 | B55: Bar Pro Syrup Lemon | C55: P39 | D55: Bar | E55: KTC Bar | G55: =VLOOKUP(B55,'Production Bar'!$B$5:$L$1000,10,FALSE) -> 130.68541 | I55: 1 | J55: ml | K55: =G55/I55 -> 130.68541 | V55: Tahu Lada Garam | W55: M0049
A56: =A55+1 -> 50 | B56: Bar Pro Mix SKM | C56: P40 | D56: Bar | E56: KTC Bar | G56: =VLOOKUP(B56,'Production Bar'!$B$5:$L$1000,10,FALSE) -> 41.000863 | I56: 1 | J56: ml | K56: =G56/I56 -> 41.000863 | V56: Cireng Lada garam | W56: M0050
A57: =A56+1 -> 51 | B57: Bar Pro Thai Tea | C57: P41 | D57: Bar | E57: KTC Bar | G57: =VLOOKUP(B57,'Production Bar'!$B$5:$L$1000,10,FALSE) -> 95.743421 | I57: 1 | J57: ml | K57: =G57/I57 -> 95.743421 | V57: Cireng Bumbu | W57: M0051
A58: =A57+1 -> 52 | B58: Bar Pro Lemon Juice | C58: P42 | D58: Bar | E58: KTC Bar | G58: =VLOOKUP(B58,'Production Bar'!$B$5:$L$1000,10,FALSE) -> 39.132047 | I58: 1 | J58: ml | K58: =G58/I58 -> 39.132047 | V58: French Fries | W58: M0052
A59: =A58+1 -> 53 | B59: Bar Pro Orange Juice | C59: P43 | D59: Bar | E59: KTC Bar | G59: =VLOOKUP(B59,'Production Bar'!$B$5:$L$1000,10,FALSE) -> 39.132047 | I59: 1 | J59: ml | K59: =G59/I59 -> 39.132047 | V59: FF & Sausage Bratwurst | W59: M0053
A60: =A59+1 -> 54 | B60: Bar Pro Cold Brew | D60: Bar | E60: KTC Bar | G60: =VLOOKUP(B60,'Production Bar'!$B$5:$L$1000,10,FALSE) -> 4472.9474 | I60: 1 | J60: ml | K60: =G60/I60 -> 4472.9474 | V60: Black Magic Ice | W60: M0054
A61: =A60+1 -> 55 | B61: Bar Pro Aren Liquid | D61: Bar | E61: KTC Bar | G61: =VLOOKUP(B61,'Production Bar'!$B$5:$L$1000,10,FALSE) -> 1164.1184 | I61: 1 | J61: porsi | K61: =G61/I61 -> 1164.1184 | V61: Aglio olio pasta Spaghetti | W61: M0055
A62: =A61+1 -> 56 | B62: KTC Pro Sambal Balado | C62: P44 | D62: Kitchen | E62: KTC Kitchen | G62: =VLOOKUP(B62,'Production Kitchen'!$B$5:$L$1029,10,FALSE) -> 1057.9834 | I62: 1 | J62: porsi | K62: =G62/I62 -> 1057.9834 | V62: Charcoal Latte Hot | W62: M0056
A63: =A62+1 -> 57 | B63: KTC Pro Sambal Ijo | C63: P45 | D63: Kitchen | E63: KTC Kitchen | G63: =VLOOKUP(B63,'Production Kitchen'!$B$5:$L$1029,10,FALSE) -> 1145.4508 | I63: 1 | J63: porsi | K63: =G63/I63 -> 1145.4508 | V63: Carbonara pasta spaghetti | W63: M0057
A64: =A63+1 -> 58 | B64: KTC Pro Terong Crispy | C64: P46 | D64: Kitchen | E64: KTC Kitchen | G64: =VLOOKUP(B64,'Production Kitchen'!$B$5:$L$1029,10,FALSE) -> 3541.3447 | I64: 1 | J64: porsi | K64: =G64/I64 -> 3541.3447 | V64: Chicken Blackpepper | W64: M0058
A65: =A64+1 -> 59 | B65: KTC Pro Ayam Ungkep | C65: P47 | D65: Kitchen | E65: KTC Kitchen | G65: =VLOOKUP(B65,'Production Kitchen'!$B$5:$L$1029,10,FALSE) -> 5105.2375 | I65: 1 | J65: porsi | K65: =G65/I65 -> 5105.2375 | V65: Beef Blackpepper | W65: M0059
A66: =A65+1 -> 60 | B66: KTC Pro Dendeng Ungkep | C66: P48 | D66: Kitchen | E66: KTC Kitchen | G66: =VLOOKUP(B66,'Production Kitchen'!$B$5:$L$1029,10,FALSE) -> 12471.829 | I66: 1 | J66: porsi | K66: =G66/I66 -> 12471.829 | V66: Cheese Chicken Katsu | W66: M0060
A67: =A66+1 -> 61 | B67: KTC Pro Paru Ungkep | C67: P49 | D67: Kitchen | E67: KTC Kitchen | G67: =VLOOKUP(B67,'Production Kitchen'!$B$5:$L$1029,10,FALSE) -> 8171.2583 | I67: 1 | J67: porsi | K67: =G67/I67 -> 8171.2583 | V67: Beef Katsu Rice Bowl | W67: M0061
A68: =A67+1 -> 62 | B68: KTC Pro Telur Dadar | C68: P50 | D68: Kitchen | E68: KTC Kitchen | G68: =VLOOKUP(B68,'Production Kitchen'!$B$5:$L$1029,10,FALSE) -> 1281.8667 | I68: 1 | J68: porsi | K68: =G68/I68 -> 1281.8667 | V68: Carbonara pasta fettucini | W68: M0062
A69: =A68+1 -> 63 | B69: KTC Pro Salad | C69: P51 | D69: Kitchen | E69: KTC Kitchen | G69: =VLOOKUP(B69,'Production Kitchen'!$B$5:$L$1029,10,FALSE) -> 1766.6427 | H69: gr | I69: 16 | J69: porsi | K69: =G69/I69 -> 110.41517 | V69: Zupa Soup | W69: M0063
A70: =A69+1 -> 64 | B70: KTC Pro Ayam Bakar | C70: P52 | D70: Kitchen | E70: KTC Kitchen | G70: =VLOOKUP(B70,'Production Kitchen'!$B$5:$L$1029,10,FALSE) -> 6786.0953 | H70: gr | I70: 1 | J70: porsi | K70: =G70/I70 -> 6786.0953 | V70: Chocolatte Banana Roll | W70: M0064
A71: =A70+1 -> 65 | B71: KTC Pro Ayam Serundeng | C71: P53 | D71: Kitchen | E71: KTC Kitchen | G71: =VLOOKUP(B71,'Production Kitchen'!$B$5:$L$1029,10,FALSE) -> 8376.39 | H71: gr | I71: 1 | J71: porsi | K71: =G71/I71 -> 8376.39 | V71: Soko Mix Platters | W71: M0065
A72: =A71+1 -> 66 | B72: KTC Pro Sambal Goang | C72: P54 | D72: Kitchen | E72: KTC Kitchen | G72: =VLOOKUP(B72,'Production Kitchen'!$B$5:$L$1029,10,FALSE) -> 1937.4474 | H72: gr | I72: 1 | J72: porsi | K72: =G72/I72 -> 1937.4474 | V72: Pancake with ice cream | W72: M0066
A73: =A72+1 -> 67 | B73: KTC Pro Daging Ungkep | C73: P55 | D73: Kitchen | E73: KTC Kitchen | G73: =VLOOKUP(B73,'Production Kitchen'!$B$5:$L$1029,10,FALSE) -> 5406.6692 | H73: gr | I73: 1 | J73: porsi | K73: =G73/I73 -> 5406.6692 | V73: Choco lava | W73: M0067
A74: =A73+1 -> 68 | B74: paket anak | C74: P56 | D74: Kitchen | E74: KTC Kitchen | G74: =VLOOKUP(B74,'Menu Kitchen'!$B$5:$K$2098,8,FALSE) -> 11772.644 | H74: gr | I74: 1 | J74: porsi | K74: =G74/I74 -> 11772.644 | V74: Rice | W74: M0068
A75: =A74+1 -> 69 | B75: KTC Pro Sate Taican | C75: P57 | D75: Kitchen | E75: KTC Kitchen | G75: =VLOOKUP(B75,'Production Kitchen'!$B$5:$L$1029,10,FALSE) -> 5345.3889 | H75: gr | I75: 1 | J75: porsi | K75: =G75/I75 -> 5345.3889 | V75: Aeropress Import | W75: M0069
A76: =A75+1 -> 70 | B76: KTC Oseng Mercon | C76: P58 | D76: Kitchen | E76: KTC Kitchen | G76: =VLOOKUP(B76,'Production Kitchen'!$B$5:$L$1029,10,FALSE) -> 10028.912 | H76: gr | I76: 1 | J76: porsi | K76: =G76/I76 -> 10028.912 | V76: Flat bottom Import | W76: M0070
A77: =A76+1 -> 71 | B77: KTC Sambal Matah | C77: P59 | D77: Kitchen | E77: KTC Kitchen | G77: =VLOOKUP(B77,'Production Kitchen'!$B$5:$L$1029,10,FALSE) -> 1080.9785 | H77: gr | I77: 1 | J77: porsi | K77: =G77/I77 -> 1080.9785 | V77: French press Import | W77: M0071
A78: =A77+1 -> 72 | B78: KTC Sambal Terasi | C78: P60 | D78: Kitchen | E78: KTC Kitchen | G78: =VLOOKUP(B78,'Production Kitchen'!$B$5:$L$1029,10,FALSE) -> 1188.7298 | H78: gr | I78: 1 | J78: porsi | K78: =G78/I78 -> 1188.7298 | V78: Japanese Import | W78: M0072
A79: =A78+1 -> 73 | B79: KTC Pancake Pondan | C79: P61 | D79: Kitchen | E79: KTC Kitchen | G79: =VLOOKUP(B79,'Production Kitchen'!$B$5:$L$1029,10,FALSE) -> 10853.333 | H79: gr | I79: 1 | J79: porsi | K79: =G79/I79 -> 10853.333 | V79: Tubruk Import | W79: M0073
A80: =A79+1 -> 74 | B80: KTC Kuah Sop | C80: P62 | D80: Kitchen | E80: KTC Kitchen | G80: =VLOOKUP(B80,'Production Kitchen'!$B$5:$L$1029,10,FALSE) -> 554.29 | H80: gr | I80: 1 | J80: porsi | K80: =G80/I80 -> 554.29 | V80: V60 Import | W80: M0074
A81: =A80+1 -> 75 | B81: KTC Bakmie Boiled | C81: P63 | D81: Kitchen | E81: KTC Kitchen | G81: =VLOOKUP(B81,'Production Kitchen'!$B$5:$L$1029,10,FALSE) -> 1892.8148 | H81: gr | I81: 1 | J81: porsi | K81: =G81/I81 -> 1892.8148 | V81: Lemon Tea Hot | W81: M0075
A82: =A81+1 -> 76 | B82: KTC Gepuk Sapi | C82: P64 | D82: Kitchen | E82: KTC Kitchen | G82: =VLOOKUP(B82,'Production Kitchen'!$B$5:$L$1029,10,FALSE) -> 8794.6375 | H82: gr | I82: 1 | J82: porsi | K82: =G82/I82 -> 8794.6375 | V82: Lemon Tea Ice | W82: M0076
A83: =A82+1 -> 77 | B83: KTC Pro Sambal Kecap | C83: P65 | D83: Kitchen | E83: KTC Kitchen | G83: =VLOOKUP(B83,'Production Kitchen'!$B$5:$L$1029,10,FALSE) -> 941.17833 | H83: gr | I83: 1 | J83: porsi | K83: =G83/I83 -> 941.17833 | V83: Espresso | W83: M0077
A84: =A83+1 -> 78 | B84: KTC Pro Tempe Tepung | C84: P66 | D84: Kitchen | E84: KTC Kitchen | G84: =VLOOKUP(B84,'Production Kitchen'!$B$5:$L$1029,10,FALSE) -> 1295.4333 | H84: gr | I84: 1 | J84: porsi | K84: =G84/I84 -> 1295.4333 | V84: Magic | W84: M0078
A85: =A84+1 -> 79 | B85: KTC Pro Kuah Rawon | C85: P67 | D85: Kitchen | E85: KTC Kitchen | G85: =VLOOKUP(B85,'Production Kitchen'!$B$5:$L$1029,10,FALSE) -> 969.76 | H85: gr | I85: 1 | J85: porsi | K85: =G85/I85 -> 969.76 | V85: Picollo | W85: M0079
A86: =A85+1 -> 80 | B86: KTC Pro Sambal Ijo Sop | C86: P68 | D86: Kitchen | E86: KTC Kitchen | G86: =VLOOKUP(B86,'Production Kitchen'!$B$5:$L$1029,10,FALSE) -> 640.91789 | H86: gr | I86: 1 | J86: porsi | K86: =G86/I86 -> 640.91789 | V86: Hot Rum Latte | W86: M0080
... A88: =A87+1 -> 82 | B88: KTC Coklat isian bananaroll | C88: P69 | D88: Kitchen | E88: KTC Kitchen | G88: =VLOOKUP(B88,'Production Kitchen'!$B$5:$L$1029,10,FALSE) -> 1629.2222 | H88: gr | I88: 1 | J88: porsi | K88: =G88/I88 -> 1629.2222 | V88: Hot Caramel Latte | W88: M0082
A89: =A88+1 -> 83 | B89: Gula Hijau | C89: B001 | D89: Bar | E89: Bahan Bar | F89: Bar Groceries | G89: 17500 | H89: Kilogram | I89: 1000 | J89: gr | K89: =G89/I89 -> 17.5 | L89: PD Aroma Jaya | M89: =VLOOKUP(L89,$AC$7:$AG$51,5,FALSE) -> Distributor | N89: Check | V89: Iced Caramel Latte | W89: M0083
A90: =A89+1 -> 84 | B90: Air Galon | C90: B002 | D90: Bar & Kitchen | E90: Bahan Bar & Kitchen | F90: Bar Water | G90: 12600 | H90: Galon | I90: 19000 | J90: ml | K90: =G90/I90 -> 0.66315789 | L90: Danone | M90: =VLOOKUP(L90,$AC$7:$AG$51,5,FALSE) -> Supplier | N90: Check | V90: Beef Katsu with Fries | W90: M0084
A91: =A90+1 -> 85 | B91: Susu Evaporasi | C91: B003 | D91: Bar | E91: Bahan Kopi | F91: Bar Milk | G91: 17000 | H91: Can | I91: 380 | J91: ml | K91: =G91/I91 -> 44.736842 | L91: PD Aroma Jaya | M91: =VLOOKUP(L91,$AC$7:$AG$51,5,FALSE) -> Distributor | N91: Check | V91: Chicken Katsu with Fries | W91: M0085
A92: =A91+1 -> 86 | B92: Thai Black Tea 400 gr | C92: B004 | D92: Bar | E92: Bahan Non-Kopi | F92: Bar Tea | G92: 56000 | H92: Pack | I92: 400 | J92: gr | K92: =G92/I92 -> 140 | L92: PD Aroma Jaya | M92: =VLOOKUP(L92,$AC$7:$AG$51,5,FALSE) -> Distributor | N92: Check | V92: Choco Java Ice | W92: M0086
A93: =A92+1 -> 87 | B93: Cengkeh | C93: B005 | D93: Bar | E93: Bahan Non-Kopi | F93: Ktc Groceries | G93: 21000 | H93: Pack | I93: 100 | J93: gr | K93: =G93/I93 -> 210 | L93: PD Aroma Jaya | M93: =VLOOKUP(L93,$AC$7:$AG$51,5,FALSE) -> Distributor | N93: Check | V93: Choco Java Hot | W93: M0087
A94: =A93+1 -> 88 | B94: Much & More Woodlane Custom | C94: B006 | D94: Bar | E94: Bahan Kopi | F94: Bar Coffee | G94: 170000 | H94: Kilogram | I94: 1000 | J94: gr | K94: =G94/I94 -> 170 | L94: Woodlane | M94: =VLOOKUP(L94,$AC$7:$AG$51,5,FALSE) -> Supplier | N94: Check | V94: Kalita wave Lokal | W94: M0088
A95: =A94+1 -> 89 | B95: Soy Milk | C95: B007 | D95: Bar | E95: Bahan Bar | F95: Bar Milk | G95: 25650 | H95: Pack | I95: 1000 | J95: ml | K95: =G95/I95 -> 25.65 | L95: Toserba Yogya | M95: =VLOOKUP(L95,$AC$7:$AG$51,5,FALSE) -> Direct | N95: Check | V95: Kalita wave Import | W95: M0089
A96: =A95+1 -> 90 | B96: Ice Cream Vanilla | C96: B008 | D96: Bar & Kitchen | E96: Bahan Bar & Kitchen | F96: Bar Groceries | G96: 171440 | H96: Pail | I96: 8000 | J96: gr | K96: =G96/I96 -> 21.43 | L96: PT Sukanda Djaya | M96: =VLOOKUP(L96,$AC$7:$AG$51,5,FALSE) -> Supplier | N96: Check | V96: Mac & Cheese | W96: M0090
A97: =A96+1 -> 91 | B97: Soda Botol | C97: B009 | D97: Bar | E97: Bahan Bar | F97: Bar Water | G97: 32500 | H97: Crat | I97: =250*12 -> 3000 | J97: ml | K97: =G97/I97 -> 10.833333 | L97: PT Fatarindo Cemerlang | M97: =VLOOKUP(L97,$AC$7:$AG$51,5,FALSE) -> Supplier | N97: Check | V97: Black Magic Hot | W97: M0091
A98: =A97+1 -> 92 | B98: Rum Syrup | C98: B010 | D98: Bar | E98: Bahan Kopi | F98: Bar Syrup Puree Concentrate | G98: 145000 | H98: Bottle | I98: 750 | J98: ml | K98: =G98/I98 -> 193.33333 | L98: Emergency Syrup | M98: =VLOOKUP(L98,$AC$7:$AG$51,5,FALSE) -> Supplier | N98: Check | V98: Soko's Classic Brunch | W98: M0092
A99: =A98+1 -> 93 | B99: Syrup Salted Caramel | C99: B011 | D99: Bar | E99: Bahan Non-Kopi | F99: Bar Syrup Puree Concentrate | G99: 95000 | H99: Bottle | I99: 750 | J99: ml | K99: =G99/I99 -> 126.66667 | L99: PD Sentosa | M99: =VLOOKUP(L99,$AC$7:$AG$51,5,FALSE) -> Supplier | N99: Check | V99: Chicken Sandwich | W99: M0093
A100: =A99+1 -> 94 | B100: Strawberry Puree | C100: B012 | D100: Bar | E100: Bahan Non-Kopi | F100: Bar Syrup Puree Concentrate | G100: 216450 | H100: Bottle | I100: 2000 | J100: gr | K100: =G100/I100 -> 108.225 | L100: PD Sentosa | M100: =VLOOKUP(L100,$AC$7:$AG$51,5,FALSE) -> Supplier | N100: Check | V100: Chicken Salad Lemon Dressing | W100: M0094
A101: =A100+1 -> 95 | B101: Taro Powder | C101: B013 | D101: Bar | E101: Bahan Non-Kopi | F101: Bar Powder | G101: 150000 | H101: Pack | I101: 1000 | J101: gr | K101: =G101/I101 -> 150 | L101: PD Sentosa | M101: =VLOOKUP(L101,$AC$7:$AG$51,5,FALSE) -> Supplier | N101: Check | V101: Nachos Primero | W101: M0095
A102: =A101+1 -> 96 | B102: Red Velvet Powder | C102: B014 | D102: Bar | E102: Bahan Non-Kopi | F102: Bar Powder | G102: 150000 | H102: Pack | I102: 1000 | J102: gr | K102: =G102/I102 -> 150 | L102: PD Sentosa | M102: =VLOOKUP(L102,$AC$7:$AG$51,5,FALSE) -> Supplier | N102: Check | V102: Nachos Pollo Queso | W102: M0096
...

Sheet Kesimpulan Menu
A1: The Soko Coffee Tea Chocolate
I2: =AVERAGE(I6:I176) -> #N/A | J2: 0.36 | K2: 1 | L2: 0.2 | N2: 0.38
H3: Dine In | K3: Online Delivery
A4: No | B4: Divisi | C4: Kategori | D4: Menu | F4: Kode | G4: HPP Net | H4: Harga Jual | I4: Margin Cost % | J4: Checker | K4: Target Price | L4: Merch Cost | M4: Margin Cost % | N4: Checker | O4: Harga Awal | P4: Description | Q4: Deskripsi | R4: Keterangan | S4: Fix Online
A5: 1 | B5: Bar | C5: Coffee | D5: Es Kopi Soko | F5: =VLOOKUP(D5,Master!$V$7:$W$1000,2,FALSE) -> M0015 | G5: =VLOOKUP(D5,'Menu Bar'!$B$6:$I$1948,8,FALSE) -> 8309.2542 | H5: 26000 | I5: =G5/H5 -> 0.3195867 | J5: =IF(I5<=$J$2,"Good Price","Bad Price") -> Good Price | K5: =1000+H5 -> 27000 | L5: =K5*$L$2 -> 5400 | M5: =G5/(K5-L5) -> 0.38468769 | N5: =IF(M5<=$N$2,"Good Price","Bad Price") -> Bad Price | O5: 27000 | Q5: kopi espresso di atasnya dengan susu panas atau krim berbusa dan sering dibumbui dengan kayu manis
A6: =A5+1 -> 2 | B6: Bar | C6: Coffee | D6: Cappucino Ice | F6: =VLOOKUP(D6,Master!$V$7:$W$1000,2,FALSE) -> M0002 | G6: =VLOOKUP(D6,'Menu Bar'!$B$6:$I$1948,8,FALSE) -> 6735.6121 | H6: 26000 | I6: =G6/H6 -> 0.25906201 | J6: =IF(I6<=$J$2,"Good Price","Bad Price") -> Good Price | K6: =1000+H6 -> 27000 | L6: =K6*$L$2 -> 5400 | M6: =G6/(K6-L6) -> 0.3118339 | N6: =IF(M6<=$N$2,"Good Price","Bad Price") -> Good Price
A7: =A6+1 -> 3 | B7: Bar | C7: Coffee | D7: Cappucino Hot | F7: =VLOOKUP(D7,Master!$V$7:$W$1000,2,FALSE) -> M0001 | G7: =VLOOKUP(D7,'Menu Bar'!$B$6:$I$1948,8,FALSE) -> 7222.6053 | H7: 24000 | I7: =G7/H7 -> 0.30094189 | J7: =IF(I7<=$J$2,"Good Price","Bad Price") -> Good Price | K7: =1000+H7 -> 25000 | L7: =K7*$L$2 -> 5000 | M7: =G7/(K7-L7) -> 0.36113026 | N7: =IF(M7<=$N$2,"Good Price","Bad Price") -> Good Price
A8: =A7+1 -> 4 | B8: Bar | C8: Coffee | D8: Iced Cafe Latte | F8: =VLOOKUP(D8,Master!$V$7:$W$1000,2,FALSE) -> M0003 | G8: =VLOOKUP(D8,'Menu Bar'!$B$6:$I$1948,8,FALSE) -> 6408.2182 | H8: 26000 | I8: =G8/H8 -> 0.24646993 | J8: =IF(I8<=$J$2,"Good Price","Bad Price") -> Good Price | K8: =1000+H8 -> 27000 | L8: =K8*$L$2 -> 5400 | M8: =G8/(K8-L8) -> 0.29667677 | N8: =IF(M8<=$N$2,"Good Price","Bad Price") -> Good Price
A9: =A8+1 -> 5 | B9: Bar | C9: Coffee | D9: Hot Cafe Latte | F9: =VLOOKUP(D9,Master!$V$7:$W$1000,2,FALSE) -> M0004 | G9: =VLOOKUP(D9,'Menu Bar'!$B$6:$I$1948,8,FALSE) -> 7885.5863 | H9: 24000 | I9: =G9/H9 -> 0.3285661 | J9: =IF(I9<=$J$2,"Good Price","Bad Price") -> Good Price | K9: =1000+H9 -> 25000 | L9: =K9*$L$2 -> 5000 | M9: =G9/(K9-L9) -> 0.39427932 | N9: =IF(M9<=$N$2,"Good Price","Bad Price") -> Bad Price
A10: =A9+1 -> 6 | B10: Bar | C10: Coffee | D10: Iced Americano | E10: Black Coffee Ice | F10: =VLOOKUP(D10,Master!$V$7:$W$1000,2,FALSE) -> M0006 | G10: =VLOOKUP(D10,'Menu Bar'!$B$6:$I$1948,8,FALSE) -> 4483.9474 | H10: 24000 | I10: =G10/H10 -> 0.18683114 | J10: =IF(I10<=$J$2,"Good Price","Bad Price") -> Good Price | K10: =1000+H10 -> 25000 | L10: =K10*$L$2 -> 5000 | M10: =G10/(K10-L10) -> 0.22419737 | N10: =IF(M10<=$N$2,"Good Price","Bad Price") -> Good Price
A11: =A10+1 -> 7 | B11: Bar | C11: Coffee | D11: Hot Americano | E11: Black Coffee Hot | F11: =VLOOKUP(D11,Master!$V$7:$W$1000,2,FALSE) -> M0005 | G11: =VLOOKUP(D11,'Menu Bar'!$B$6:$I$1948,8,FALSE) -> 4756.7632 | H11: 22000 | I11: =G11/H11 -> 0.21621651 | J11: =IF(I11<=$J$2,"Good Price","Bad Price") -> Good Price | K11: =1000+H11 -> 23000 | L11: =K11*$L$2 -> 4600 | M11: =G11/(K11-L11) -> 0.25851974 | N11: =IF(M11<=$N$2,"Good Price","Bad Price") -> Good Price
A12: =A11+1 -> 8 | B12: Bar | C12: Coffee | D12: Hot Vietnam Drip | E12: Vietnam Drip Ice 26K | F12: =VLOOKUP(D12,Master!$V$7:$W$1000,2,FALSE) -> M0043 | G12: =VLOOKUP(D12,'Menu Bar'!$B$6:$I$1948,8,FALSE) -> 5875.6821 | H12: 24000 | I12: =G12/H12 -> 0.24482009 | J12: =IF(I12<=$J$2,"Good Price","Bad Price") -> Good Price | K12: =1000+H12 -> 25000 | L12: =K12*$L$2 -> 5000 | M12: =G12/(K12-L12) -> 0.2937841 | N12: =IF(M12<=$N$2,"Good Price","Bad Price") -> Good Price
A13: =A12+1 -> 9 | B13: Bar | C13: Coffee | D13: Japanese Lokal | E13: Japanese | F13: =VLOOKUP(D13,Master!$V$7:$W$1000,2,FALSE) -> M0039 | G13: =VLOOKUP(D13,'Menu Bar'!$B$6:$I$1948,8,FALSE) -> 8806.5789 | H13: 27000 | I13: =G13/H13 -> 0.32616959 | J13: =IF(I13<=$J$2,"Good Price","Bad Price") -> Good Price | K13: 27000 | L13: =K13*$L$2 -> 5400 | M13: =G13/(K13-L13) -> 0.40771199 | N13: =IF(M13<=$N$2,"Good Price","Bad Price") -> Bad Price
A14: =A13+1 -> 10 | B14: Bar | C14: Coffee | D14: V60 Lokal | E14: V60 | F14: =VLOOKUP(D14,Master!$V$7:$W$1000,2,FALSE) -> M0038 | G14: =VLOOKUP(D14,'Menu Bar'!$B$6:$I$1948,8,FALSE) -> 8882.8421 | H14: 26000 | I14: =G14/H14 -> 0.34164777 | J14: =IF(I14<=$J$2,"Good Price","Bad Price") -> Good Price | K14: 26000 | L14: =K14*$L$2 -> 5200 | M14: =G14/(K14-L14) -> 0.42705972 | N14: =IF(M14<=$N$2,"Good Price","Bad Price") -> Bad Price
A15: =A14+1 -> 11 | B15: Bar | C15: Coffee | D15: Aeropress Lokal | E15: Aeropress | F15: =VLOOKUP(D15,Master!$V$7:$W$1000,2,FALSE) -> M0042 | G15: =VLOOKUP(D15,'Menu Bar'!$B$6:$I$1948,8,FALSE) -> 8423.1447 | H15: 28000 | I15: =G15/H15 -> 0.3008266 | J15: =IF(I15<=$J$2,"Good Price","Bad Price") -> Good Price | K15: 28000 | L15: =K15*$L$2 -> 5600 | M15: =G15/(K15-L15) -> 0.37603325 | N15: =IF(M15<=$N$2,"Good Price","Bad Price") -> Good Price
A16: =A15+1 -> 12 | B16: Bar | C16: Coffee | D16: Iced Vanilla Latte | F16: =VLOOKUP(D16,Master!$V$7:$W$1000,2,FALSE) -> M0012 | G16: =VLOOKUP(D16,'Menu Bar'!$B$6:$I$1948,8,FALSE) -> 9911.3061 | H16: 28000 | I16: =G16/H16 -> 0.35397522 | J16: =IF(I16<=$J$2,"Good Price","Bad Price") -> Good Price | K16: =1000+H16 -> 29000 | L16: =K16*$L$2 -> 5800 | M16: =G16/(K16-L16) -> 0.42721147 | N16: =IF(M16<=$N$2,"Good Price","Bad Price") -> Bad Price
A17: =A16+1 -> 13 | B17: Bar | C17: Coffee | D17: Hot Vanilla Latte | F17: =VLOOKUP(D17,Master!$V$7:$W$1000,2,FALSE) -> M0011 | G17: =VLOOKUP(D17,'Menu Bar'!$B$6:$I$1948,8,FALSE) -> 10070.586 | H17: 27000 | I17: =G17/H17 -> 0.37298468 | J17: =IF(I17<=$J$2,"Good Price","Bad Price") -> Bad Price | K17: =1000+H17 -> 28000 | L17: =K17*$L$2 -> 5600 | M17: =G17/(K17-L17) -> 0.44957975 | N17: =IF(M17<=$N$2,"Good Price","Bad Price") -> Bad Price
A18: =A17+1 -> 14 | B18: Bar | C18: Coffee | D18: Iced Caramel Latte | F18: =VLOOKUP(D18,Master!$V$7:$W$1000,2,FALSE) -> M0083 | G18: =VLOOKUP(D18,'Menu Bar'!$B$6:$I$1948,8,FALSE) -> 9911.3061 | H18: 28000 | I18: =G18/H18 -> 0.35397522 | J18: =IF(I18<=$J$2,"Good Price","Bad Price") -> Good Price | K18: =1000+H18 -> 29000 | L18: =K18*$L$2 -> 5800 | M18: =G18/(K18-L18) -> 0.42721147 | N18: =IF(M18<=$N$2,"Good Price","Bad Price") -> Bad Price
A19: =A18+1 -> 15 | B19: Bar | C19: Coffee | D19: Hot Caramel Latte | F19: =VLOOKUP(D19,Master!$V$7:$W$1000,2,FALSE) -> M0082 | G19: =VLOOKUP(D19,'Menu Bar'!$B$6:$I$1948,8,FALSE) -> 10070.586 | H19: 27000 | I19: =G19/H19 -> 0.37298468 | J19: =IF(I19<=$J$2,"Good Price","Bad Price") -> Bad Price | K19: =1000+H19 -> 28000 | L19: =K19*$L$2 -> 5600 | M19: =G19/(K19-L19) -> 0.44957975 | N19: =IF(M19<=$N$2,"Good Price","Bad Price") -> Bad Price
A20: =A19+1 -> 16 | B20: Bar | C20: Coffee | D20: Hazelnut Latte Ice | F20: =VLOOKUP(D20,Master!$V$7:$W$1000,2,FALSE) -> M0010 | G20: =VLOOKUP(D20,'Menu Bar'!$B$6:$I$1948,8,FALSE) -> 9911.3061 | H20: 28000 | I20: =G20/H20 -> 0.35397522 | J20: =IF(I20<=$J$2,"Good Price","Bad Price") -> Good Price | K20: =1000+H20 -> 29000 | L20: =K20*$L$2 -> 5800 | M20: =G20/(K20-L20) -> 0.42721147 | N20: =IF(M20<=$N$2,"Good Price","Bad Price") -> Bad Price
A21: =A20+1 -> 17 | B21: Bar | C21: Coffee | D21: Hazelnut Latte Hot | F21: =VLOOKUP(D21,Master!$V$7:$W$1000,2,FALSE) -> M0009 | G21: =VLOOKUP(D21,'Menu Bar'!$B$6:$I$1948,8,FALSE) -> 10070.586 | H21: 27000 | I21: =G21/H21 -> 0.37298468 | J21: =IF(I21<=$J$2,"Good Price","Bad Price") -> Bad Price | K21: =1000+H21 -> 28000 | L21: =K21*$L$2 -> 5600 | M21: =G21/(K21-L21) -> 0.44957975 | N21: =IF(M21<=$N$2,"Good Price","Bad Price") -> Bad Price
A22: =A21+1 -> 18 | B22: Bar | C22: Coffee | D22: Butterscotch Latte Ice | F22: =VLOOKUP(D22,Master!$V$7:$W$1000,2,FALSE) -> B031 | G22: =VLOOKUP(D22,'Menu Bar'!$B$6:$I$1948,8,FALSE) -> 9480.3797 | H22: 28000 | I22: =G22/H22 -> 0.33858499 | J22: =IF(I22<=$J$2,"Good Price","Bad Price") -> Good Price | K22: =1000+H22 -> 29000 | L22: =K22*$L$2 -> 5800 | M22: =G22/(K22-L22) -> 0.40863706 | N22: =IF(M22<=$N$2,"Good Price","Bad Price") -> Bad Price
A23: =A22+1 -> 19 | B23: Bar | C23: Coffee | D23: Butterscotch Latte Hot | F23: =VLOOKUP(D23,Master!$V$7:$W$1000,2,FALSE) -> B031 | G23: =VLOOKUP(D23,'Menu Bar'!$B$6:$I$1948,8,FALSE) -> 9566.7347 | H23: 27000 | I23: =G23/H23 -> 0.35432351 | J23: =IF(I23<=$J$2,"Good Price","Bad Price") -> Good Price | K23: =1000+H23 -> 28000 | L23: =K23*$L$2 -> 5600 | M23: =G23/(K23-L23) -> 0.42708637 | N23: =IF(M23<=$N$2,"Good Price","Bad Price") -> Bad Price
A24: =A23+1 -> 20 | B24: Bar | C24: Coffee | D24: Iced Moccacino | E24: Moccachino Ice | F24: =VLOOKUP(D24,Master!$V$7:$W$1000,2,FALSE) -> M0008 | G24: =VLOOKUP(D24,'Menu Bar'!$B$6:$I$1948,8,FALSE) -> 10792.973 | H24: 29000 | I24: =G24/H24 -> 0.37217147 | J24: =IF(I24<=$J$2,"Good Price","Bad Price") -> Bad Price | K24: =1000+H24 -> 30000 | L24: =K24*$L$2 -> 6000 | M24: =G24/(K24-L24) -> 0.4497072 | N24: =IF(M24<=$N$2,"Good Price","Bad Price") -> Bad Price
A25: =A24+1 -> 21 | B25: Bar | C25: Coffee | D25: Hot Moccacino | E25: Moccachino Hot | F25: =VLOOKUP(D25,Master!$V$7:$W$1000,2,FALSE) -> M0007 | G25: =VLOOKUP(D25,'Menu Bar'!$B$6:$I$1948,8,FALSE) -> 7555.7179 | H25: 27000 | I25: =G25/H25 -> 0.2798414 | J25: =IF(I25<=$J$2,"Good Price","Bad Price") -> Good Price | K25: =1000+H25 -> 28000 | L25: =K25*$L$2 -> 5600 | M25: =G25/(K25-L25) -> 0.33730883 | N25: =IF(M25<=$N$2,"Good Price","Bad Price") -> Good Price
A26: =A25+1 -> 22 | B26: Bar | C26: Milk Base | D26: Choco Java Ice | E26: Chocolate Java Ice | F26: =VLOOKUP(D26,Master!$V$7:$W$1000,2,FALSE) -> M0086 | G26: =VLOOKUP(D26,'Menu Bar'!$B$6:$I$1948,8,FALSE) -> 8937.0378 | H26: 26000 | I26: =G26/H26 -> 0.34373222 | J26: =IF(I26<=$J$2,"Good Price","Bad Price") -> Good Price | K26: =1000+H26 -> 27000 | L26: =K26*$L$2 -> 5400 | M26: =G26/(K26-L26) -> 0.41375175 | N26: =IF(M26<=$N$2,"Good Price","Bad Price") -> Bad Price
A27: =A26+1 -> 23 | B27: Bar | C27: Milk Base | D27: Choco Java Hot | E27: Chocolate Java Hot | F27: =VLOOKUP(D27,Master!$V$7:$W$1000,2,FALSE) -> M0087 | G27: =VLOOKUP(D27,'Menu Bar'!$B$6:$I$1948,8,FALSE) -> 8881.6316 | H27: 24000 | I27: =G27/H27 -> 0.37006798 | J27: =IF(I27<=$J$2,"Good Price","Bad Price") -> Bad Price | K27: =1000+H27 -> 25000 | L27: =K27*$L$2 -> 5000 | M27: =G27/(K27-L27) -> 0.44408158 | N27: =IF(M27<=$N$2,"Good Price","Bad Price") -> Bad Price
A28: =A27+1 -> 24 | B28: Bar | C28: Milk Base | D28: Dark Choco Ice | F28: =VLOOKUP(D28,Master!$V$7:$W$1000,2,FALSE) -> B013 | G28: =VLOOKUP(D28,'Menu Bar'!$B$6:$I$1948,8,FALSE) -> 7347.5368 | H28: 26000 | I28: =G28/H28 -> 0.28259757 | J28: =IF(I28<=$J$2,"Good Price","Bad Price") -> Good Price | K28: =1000+H28 -> 27000 | L28: =K28*$L$2 -> 5400 | M28: =G28/(K28-L28) -> 0.34016374 | N28: =IF(M28<=$N$2,"Good Price","Bad Price") -> Good Price
A29: =A28+1 -> 25 | B29: Bar | C29: Milk Base | D29: Dark Choco Hot | F29: =VLOOKUP(D29,Master!$V$7:$W$1000,2,FALSE) -> B037 | G29: =VLOOKUP(D29,'Menu Bar'!$B$6:$I$1948,8,FALSE) -> 6137.5368 | H29: 24000 | I29: =G29/H29 -> 0.2557307 | J29: =IF(I29<=$J$2,"Good Price","Bad Price") -> Good Price | K29: =1000+H29 -> 25000 | L29: =K29*$L$2 -> 5000 | M29: =G29/(K29-L29) -> 0.30687684 | N29: =IF(M29<=$N$2,"Good Price","Bad Price") -> Good Price
A30: =A29+1 -> 26 | B30: Bar | C30: Milk Base | D30: Matcha Latte Ice | F30: =VLOOKUP(D30,Master!$V$7:$W$1000,2,FALSE) -> M0028 | G30: =VLOOKUP(D30,'Menu Bar'!$B$6:$I$1948,8,FALSE) -> 8454.0378 | H30: 26000 | I30: =G30/H30 -> 0.3251553 | J30: =IF(I30<=$J$2,"Good Price","Bad Price") -> Good Price | K30: =1000+H30 -> 27000 | L30: =K30*$L$2 -> 5400 | M30: =G30/(K30-L30) -> 0.39139064 | N30: =IF(M30<=$N$2,"Good Price","Bad Price") -> Bad Price
A31: =A30+1 -> 27 | B31: Bar | C31: Milk Base | D31: Matcha Latte Hot | F31: =VLOOKUP(D31,Master!$V$7:$W$1000,2,FALSE) -> M0027 | G31: =VLOOKUP(D31,'Menu Bar'!$B$6:$I$1948,8,FALSE) -> 8881.6316 | H31: 24000 | I31: =G31/H31 -> 0.37006798 | J31: =IF(I31<=$J$2,"Good Price","Bad Price") -> Bad Price | K31: =1000+H31 -> 25000 | L31: =K31*$L$2 -> 5000 | M31: =G31/(K31-L31) -> 0.44408158 | N31: =IF(M31<=$N$2,"Good Price","Bad Price") -> Bad Price
A32: =A31+1 -> 28 | B32: Bar | C32: Milk Base | D32: Taro Latte Ice | F32: =VLOOKUP(D32,Master!$V$7:$W$1000,2,FALSE) -> M0026 | G32: =VLOOKUP(D32,'Menu Bar'!$B$6:$I$1948,8,FALSE) -> 7327.0378 | H32: 26000 | I32: =G32/H32 -> 0.28180915 | J32: =IF(I32<=$J$2,"Good Price","Bad Price") -> Good Price | K32: =1000+H32 -> 27000 | L32: =K32*$L$2 -> 5400 | M32: =G32/(K32-L32) -> 0.33921472 | N32: =IF(M32<=$N$2,"Good Price","Bad Price") -> Good Price
A33: =A32+1 -> 29 | B33: Bar | C33: Milk Base | D33: Taro Latte Hot | F33: =VLOOKUP(D33,Master!$V$7:$W$1000,2,FALSE) -> M0025 | G33: =VLOOKUP(D33,'Menu Bar'!$B$6:$I$1948,8,FALSE) -> 7271.6316 | H33: 24000 | I33: =G33/H33 -> 0.30298465 | J33: =IF(I33<=$J$2,"Good Price","Bad Price") -> Good Price | K33: =1000+H33 -> 25000 | L33: =K33*$L$2 -> 5000 | M33: =G33/(K33-L33) -> 0.36358158 | N33: =IF(M33<=$N$2,"Good Price","Bad Price") -> Good Price
A34: =A33+1 -> 30 | B34: Bar | C34: Milk Base | D34: Charcoal Latte Ice | F34: =VLOOKUP(D34,Master!$V$7:$W$1000,2,FALSE) -> M0048 | G34: =VLOOKUP(D34,'Menu Bar'!$B$6:$I$1948,8,FALSE) -> 6348.471 | H34: 26000 | I34: =G34/H34 -> 0.24417196 | J34: =IF(I34<=$J$2,"Good Price","Bad Price") -> Good Price | K34: =1000+H34 -> 27000 | L34: =K34*$L$2 -> 5400 | M34: =G34/(K34-L34) -> 0.29391069 | N34: =IF(M34<=$N$2,"Good Price","Bad Price") -> Good Price
A35: =A34+1 -> 31 | B35: Bar | C35: Milk Base | D35: Charcoal Latte Hot | F35: =VLOOKUP(D35,Master!$V$7:$W$1000,2,FALSE) -> M0056 | G35: =VLOOKUP(D35,'Menu Bar'!$B$6:$I$1948,8,FALSE) -> 6229.4737 | H35: 24000 | I35: =G35/H35 -> 0.2595614 | J35: =IF(I35<=$J$2,"Good Price","Bad Price") -> Good Price | K35: =1000+H35 -> 25000 | L35: =K35*$L$2 -> 5000 | M35: =G35/(K35-L35) -> 0.31147368 | N35: =IF(M35<=$N$2,"Good Price","Bad Price") -> Good Price
A36: =A35+1 -> 32 | B36: Bar | C36: Milk Base | D36: Tiramisu Latte Ice | E36: Tiramisu Coffee Ice | F36: =VLOOKUP(D36,Master!$V$7:$W$1000,2,FALSE) -> B005 | G36: =VLOOKUP(D36,'Menu Bar'!$B$6:$I$1948,8,FALSE) -> 10187.605 | H36: 28000 | I36: =G36/H36 -> 0.36384304 | J36: =IF(I36<=$J$2,"Good Price","Bad Price") -> Bad Price | K36: =1000+H36 -> 29000 | L36: =K36*$L$2 -> 5800 | M36: =G36/(K36-L36) -> 0.43912091 | N36: =IF(M36<=$N$2,"Good Price","Bad Price") -> Bad Price
A37: =A36+1 -> 33 | B37: Bar | C37: Milk Base | D37: Tiramisu Latte Hot | E37: Tiramisu Coffee Hot | F37: =VLOOKUP(D37,Master!$V$7:$W$1000,2,FALSE) -> B006 | G37: =VLOOKUP(D37,'Menu Bar'!$B$6:$I$1948,8,FALSE) -> 9006.7768 | H37: 27000 | I37: =G37/H37 -> 0.33358433 | J37: =IF(I37<=$J$2,"Good Price","Bad Price") -> Good Price | K37: =1000+H37 -> 28000 | L37: =K37*$L$2 -> 5600 | M37: =G37/(K37-L37) -> 0.40208825 | N37: =IF(M37<=$N$2,"Good Price","Bad Price") -> Bad Price
A38: =A37+1 -> 34 | B38: Bar | C38: Milk Base | D38: Red Velvet Ice | F38: =VLOOKUP(D38,Master!$V$7:$W$1000,2,FALSE) -> M0030 | G38: =VLOOKUP(D38,'Menu Bar'!$B$6:$I$1948,8,FALSE) -> 7327.0378 | H38: 26000 | I38: =G38/H38 -> 0.28180915 | J38: =IF(I38<=$J$2,"Good Price","Bad Price") -> Good Price | K38: =1000+H38 -> 27000 | L38: =K38*$L$2 -> 5400 | M38: =G38/(K38-L38) -> 0.33921472 | N38: =IF(M38<=$N$2,"Good Price","Bad Price") -> Good Price
A39: =A38+1 -> 35 | B39: Bar | C39: Milk Base | D39: Red Velvet Hot | F39: =VLOOKUP(D39,Master!$V$7:$W$1000,2,FALSE) -> M0029 | G39: =VLOOKUP(D39,'Menu Bar'!$B$6:$I$1948,8,FALSE) -> 7271.6316 | H39: 24000 | I39: =G39/H39 -> 0.30298465 | J39: =IF(I39<=$J$2,"Good Price","Bad Price") -> Good Price | K39: =1000+H39 -> 25000 | L39: =K39*$L$2 -> 5000 | M39: =G39/(K39-L39) -> 0.36358158 | N39: =IF(M39<=$N$2,"Good Price","Bad Price") -> Good Price
A40: =A39+1 -> 36 | B40: Bar | C40: Coffee | D40: Affogato | F40: =VLOOKUP(D40,Master!$V$7:$W$1000,2,FALSE) -> M0013 | G40: =VLOOKUP(D40,'Menu Bar'!$B$6:$I$1948,8,FALSE) -> 6528.4047 | H40: 26000 | I40: =G40/H40 -> 0.25109249 | J40: =IF(I40<=$J$2,"Good Price","Bad Price") -> Good Price | K40: 26000 | L40: =K40*$L$2 -> 5200 | M40: =G40/(K40-L40) -> 0.31386561 | N40: =IF(M40<=$N$2,"Good Price","Bad Price") -> Good Price
A41: =A40+1 -> 37 | B41: Bar | C41: Coffee | D41: Chocogato | F41: =VLOOKUP(D41,Master!$V$7:$W$1000,2,FALSE) -> B032 | G41: =VLOOKUP(D41,'Menu Bar'!$B$6:$I$1948,8,FALSE) -> 7551.9047 | H41: 26000 | I41: =G41/H41 -> 0.29045787 | J41: =IF(I41<=$J$2,"Good Price","Bad Price") -> Good Price | K41: 26000 | L41: =K41*$L$2 -> 5200 | M41: =G41/(K41-L41) -> 0.36307234 | N41: =IF(M41<=$N$2,"Good Price","Bad Price") -> Good Price
A42: =A41+1 -> 38 | B42: Bar | D42: Mineral Water | F42: =VLOOKUP(D42,Master!$V$7:$W$1000,2,FALSE) -> M0033 | G42: =VLOOKUP(D42,'Menu Bar'!$B$6:$I$1948,8,FALSE) -> 1557.2917 | H42: 10000 | I42: =G42/H42 -> 0.15572917 | J42: =IF(I42<=$J$2,"Good Price","Bad Price") -> Good Price | K42: =1000+H42 -> 11000 | L42: =K42*$L$2 -> 2200 | M42: =G42/(K42-L42) -> 0.17696496 | N42: =IF(M42<=$N$2,"Good Price","Bad Price") -> Good Price
A43: =A42+1 -> 39 | B43: Bar | C43: Signature | D43: Karma Coffee | F43: =VLOOKUP(D43,Master!$V$7:$W$1000,2,FALSE) -> M0034 | G43: =VLOOKUP(D43,'Menu Bar'!$B$6:$I$1948,8,FALSE) -> 10115.774 | H43: 28000 | I43: =G43/H43 -> 0.36127766 | J43: =IF(I43<=$J$2,"Good Price","Bad Price") -> Bad Price | K43: =1000+H43 -> 29000 | L43: =K43*$L$2 -> 5800 | M43: =G43/(K43-L43) -> 0.43602476 | N43: =IF(M43<=$N$2,"Good Price","Bad Price") -> Bad Price
A44: =A43+1 -> 40 | B44: Bar | C44: Signature | D44: Soko Mint | F44: =VLOOKUP(D44,Master!$V$7:$W$1000,2,FALSE) -> M0035 | G44: =VLOOKUP(D44,'Menu Bar'!$B$6:$I$1948,8,FALSE) -> 12542.076 | H44: 28000 | I44: =G44/H44 -> 0.4479313 | J44: =IF(I44<=$J$2,"Good Price","Bad Price") -> Bad Price | K44: 28000 | L44: =K44*$L$2 -> 5600 | M44: =G44/(K44-L44) -> 0.55991412 | N44: =IF(M44<=$N$2,"Good Price","Bad Price") -> Bad Price
A45: =A44+1 -> 41 | B45: Bar | C45: Signature | D45: Dreamy Berry | F45: =VLOOKUP(D45,Master!$V$7:$W$1000,2,FALSE) -> M0036 | G45: =VLOOKUP(D45,'Menu Bar'!$B$6:$I$1948,8,FALSE) -> 6931.1347 | H45: 29000 | I45: =G45/H45 -> 0.23900465 | J45: =IF(I45<=$J$2,"Good Price","Bad Price") -> Good Price | K45: 29000 | L45: =K45*$L$2 -> 5800 | M45: =G45/(K45-L45) -> 0.29875581 | N45: =IF(M45<=$N$2,"Good Price","Bad Price") -> Good Price
A46: =A45+1 -> 42 | B46: Bar | C46: Mocktail & Squash | D46: Sunfield Green | F46: =VLOOKUP(D46,Master!$V$7:$W$1000,2,FALSE) -> M0037 | G46: =VLOOKUP(D46,'Menu Bar'!$B$6:$I$1948,8,FALSE) -> 11528.536 | H46: 29000 | I46: =G46/H46 -> 0.39753574 | J46: =IF(I46<=$J$2,"Good Price","Bad Price") -> Bad Price | K46: =1000+H46 -> 30000 | L46: =K46*$L$2 -> 6000 | M46: =G46/(K46-L46) -> 0.48035569 | N46: =IF(M46<=$N$2,"Good Price","Bad Price") -> Bad Price
A47: =A46+1 -> 43 | B47: Bar | C47: Mocktail & Squash | D47: Tropical Sunrise | F47: =VLOOKUP(D47,Master!$V$7:$W$1000,2,FALSE) -> M0126 | G47: =VLOOKUP(D47,'Menu Bar'!$B$6:$I$1948,8,FALSE) -> 11405.489 | H47: 29000 | I47: =G47/H47 -> 0.39329273 | J47: =IF(I47<=$J$2,"Good Price","Bad Price") -> Bad Price | K47: =1000+H47 -> 30000 | L47: =K47*$L$2 -> 6000 | M47: =G47/(K47-L47) -> 0.47522872 | N47: =IF(M47<=$N$2,"Good Price","Bad Price") -> Bad Price
A48: =A47+1 -> 44 | B48: Bar | C48: Mocktail & Squash | D48: Spring Berry Ice | E48: Spring Berry | F48: =VLOOKUP(D48,Master!$V$7:$W$1000,2,FALSE) -> M0016 | G48: =VLOOKUP(D48,'Menu Bar'!$B$6:$I$1948,8,FALSE) -> 7929.9388 | H48: 29000 | I48: =G48/H48 -> 0.27344617 | J48: =IF(I48<=$J$2,"Good Price","Bad Price") -> Good Price | K48: =1000+H48 -> 30000 | L48: =K48*$L$2 -> 6000 | M48: =G48/(K48-L48) -> 0.33041412 | N48: =IF(M48<=$N$2,"Good Price","Bad Price") -> Good Price
A49: =A48+1 -> 45 | B49: Bar | C49: Chocolate & Tea | D49: Naga Black Tea Ice | F49: =VLOOKUP(D49,Master!$V$7:$W$1000,2,FALSE) -> M0021 | G49: =VLOOKUP(D49,'Menu Bar'!$B$6:$I$1948,8,FALSE) -> 2420.7343 | H49: 15000 | I49: =G49/H49 -> 0.16138229 | J49: =IF(I49<=$J$2,"Good Price","Bad Price") -> Good Price | K49: =1000+H49 -> 16000 | L49: =K49*$L$2 -> 3200 | M49: =G49/(K49-L49) -> 0.18911987 | N49: =IF(M49<=$N$2,"Good Price","Bad Price") -> Good Price
A50: =A49+1 -> 46 | B50: Bar | C50: Chocolate & Tea | D50: Naga Black Tea Hot | F50: =VLOOKUP(D50,Master!$V$7:$W$1000,2,FALSE) -> M0020 | G50: =VLOOKUP(D50,'Menu Bar'!$B$6:$I$1948,8,FALSE) -> 849.54586 | H50: 10000 | I50: =G50/H50 -> 0.084954586 | J50: =IF(I50<=$J$2,"Good Price","Bad Price") -> Good Price | K50: =1000+H50 -> 11000 | L50: =K50*$L$2 -> 2200 | M50: =G50/(K50-L50) -> 0.096539302 | N50: =IF(M50<=$N$2,"Good Price","Bad Price") -> Good Price
A51: =A50+1 -> 47 | B51: Bar | C51: Chocolate & Tea | D51: Lemon Tea Ice | F51: =VLOOKUP(D51,Master!$V$7:$W$1000,2,FALSE) -> M0076 | G51: =VLOOKUP(D51,'Menu Bar'!$B$6:$I$1948,8,FALSE) -> 6782.1323 | H51: 22000 | I51: =G51/H51 -> 0.30827874 | J51: =IF(I51<=$J$2,"Good Price","Bad Price") -> Good Price | K51: =1000+H51 -> 23000 | L51: =K51*$L$2 -> 4600 | M51: =G51/(K51-L51) -> 0.36859414 | N51: =IF(M51<=$N$2,"Good Price","Bad Price") -> Good Price
A52: =A51+1 -> 48 | B52: Bar | C52: Chocolate & Tea | D52: Lemon Tea Hot | F52: =VLOOKUP(D52,Master!$V$7:$W$1000,2,FALSE) -> M0075 | G52: =VLOOKUP(D52,'Menu Bar'!$B$6:$I$1948,8,FALSE) -> 5004.018 | H52: 19000 | I52: =G52/H52 -> 0.26336937 | J52: =IF(I52<=$J$2,"Good Price","Bad Price") -> Good Price | K52: =1000+H52 -> 20000 | L52: =K52*$L$2 -> 4000 | M52: =G52/(K52-L52) -> 0.31275112 | N52: =IF(M52<=$N$2,"Good Price","Bad Price") -> Good Price
A53: =A52+1 -> 49 | B53: Bar | C53: Chocolate & Tea | D53: Lychee Ice Tea | E53: Lychee tea | F53: =VLOOKUP(D53,Master!$V$7:$W$1000,2,FALSE) -> M0149 | G53: =VLOOKUP(D53,'Menu Bar'!$B$6:$I$1948,8,FALSE) -> 3202.4569 | H53: 24000 | I53: =G53/H53 -> 0.13343571 | J53: =IF(I53<=$J$2,"Good Price","Bad Price") -> Good Price | K53: =1000+H53 -> 25000 | L53: =K53*$L$2 -> 5000 | M53: =G53/(K53-L53) -> 0.16012285 | N53: =IF(M53<=$N$2,"Good Price","Bad Price") -> Good Price
A54: =A53+1 -> 50 | B54: Bar | C54: Chocolate & Tea | D54: Lemon Tea Peach Ice | E54: Lemon Peach | F54: =VLOOKUP(D54,Master!$V$7:$W$1000,2,FALSE) -> B012 | G54: =VLOOKUP(D54,'Menu Bar'!$B$6:$I$1948,8,FALSE) -> 4248.994 | H54: 26000 | I54: =G54/H54 -> 0.16342285 | J54: =IF(I54<=$J$2,"Good Price","Bad Price") -> Good Price | K54: =1000+H54 -> 27000 | L54: =K54*$L$2 -> 5400 | M54: =G54/(K54-L54) -> 0.19671268 | N54: =IF(M54<=$N$2,"Good Price","Bad Price") -> Good Price
A55: =A54+1 -> 51 | B55: Bar | C55: Chocolate & Tea | D55: Lemon Tea Cola | F55: =VLOOKUP(D55,Master!$V$7:$W$1000,2,FALSE) -> B043 | G55: =VLOOKUP(D55,'Menu Bar'!$B$6:$I$1948,8,FALSE) -> #N/A | H55: 26000 | I55: =G55/H55 -> #N/A | J55: =IF(I55<=$J$2,"Good Price","Bad Price") -> #N/A | K55: =1000+H55 -> 27000 | L55: =K55*$L$2 -> 5400 | M55: =G55/(K55-L55) -> #N/A | N55: =IF(M55<=$N$2,"Good Price","Bad Price") -> #N/A
A56: =A55+1 -> 52 | B56: Bar | C56: Mocktail & Squash | D56: Lemon Squash | F56: =VLOOKUP(D56,Master!$V$7:$W$1000,2,FALSE) -> M0031 | G56: =VLOOKUP(D56,'Menu Bar'!$B$6:$I$1948,8,FALSE) -> 8071.5864 | H56: 27000 | I56: =G56/H56 -> 0.29894764 | J56: =IF(I56<=$J$2,"Good Price","Bad Price") -> Good Price | K56: =1000+H56 -> 28000 | L56: =K56*$L$2 -> 5600 | M56: =G56/(K56-L56) -> 0.36033868 | N56: =IF(M56<=$N$2,"Good Price","Bad Price") -> Good Price
A57: =A56+1 -> 53 | B57: Bar | C57: Mocktail & Squash | D57: Orange Squash | F57: =VLOOKUP(D57,Master!$V$7:$W$1000,2,FALSE) -> M0032 | G57: =VLOOKUP(D57,'Menu Bar'!$B$6:$I$1948,8,FALSE) -> 7303.6494 | H57: 27000 | I57: =G57/H57 -> 0.27050553 | J57: =IF(I57<=$J$2,"Good Price","Bad Price") -> Good Price | K57: =1000+H57 -> 28000 | L57: =K57*$L$2 -> 5600 | M57: =G57/(K57-L57) -> 0.32605578 | N57: =IF(M57<=$N$2,"Good Price","Bad Price") -> Good Price
A58: =A57+1 -> 54 | B58: Bar | C58: Chocolate & Tea | D58: Thai Tea Ice | F58: =VLOOKUP(D58,Master!$V$7:$W$1000,2,FALSE) -> M0023 | G58: =VLOOKUP(D58,'Menu Bar'!$B$6:$I$1948,8,FALSE) -> 4505.1089 | H58: 22000 | I58: =G58/H58 -> 0.20477768 | J58: =IF(I58<=$J$2,"Good Price","Bad Price") -> Good Price | K58: =1000+H58 -> 23000 | L58: =K58*$L$2 -> 4600 | M58: =G58/(K58-L58) -> 0.24484287 | N58: =IF(M58<=$N$2,"Good Price","Bad Price") -> Good Price
A59: =A58+1 -> 55 | B59: Bar | C59: Chocolate & Tea | D59: Thai Tea Hot | F59: =VLOOKUP(D59,Master!$V$7:$W$1000,2,FALSE) -> M0022 | G59: =VLOOKUP(D59,'Menu Bar'!$B$6:$I$1948,8,FALSE) -> 5416.5496 | H59: 20000 | I59: =G59/H59 -> 0.27082748 | J59: =IF(I59<=$J$2,"Good Price","Bad Price") -> Good Price | K59: =1000+H59 -> 21000 | L59: =K59*$L$2 -> 4200 | M59: =G59/(K59-L59) -> 0.32241367 | N59: =IF(M59<=$N$2,"Good Price","Bad Price") -> Good Price
A60: =A59+1 -> 56 | B60: Bar | C60: Chocolate & Tea | D60: Premium Tea Hot | F60: =VLOOKUP(D60,Master!$V$7:$W$1000,2,FALSE) -> M0024 | G60: =VLOOKUP(D60,'Menu Bar'!$B$6:$I$1948,8,FALSE) -> 4790.6579 | H60: 26000 | I60: =G60/H60 -> 0.18425607 | J60: =IF(I60<=$J$2,"Good Price","Bad Price") -> Good Price | K60: =1000+H60 -> 27000 | L60: =K60*$L$2 -> 5400 | M60: =G60/(K60-L60) -> 0.22178972 | N60: =IF(M60<=$N$2,"Good Price","Bad Price") -> Good Price
A61: =A60+1 -> 57 | B61: Bar | C61: Mocktail & Squash | D61: Baby Purple | F61: =VLOOKUP(D61,Master!$V$7:$W$1000,2,FALSE) -> B011 | G61: =VLOOKUP(D61,'Menu Bar'!$B$6:$I$1948,8,FALSE) -> 11695.741 | H61: 28000 | I61: =G61/H61 -> 0.41770504 | J61: =IF(I61<=$J$2,"Good Price","Bad Price") -> Bad Price | K61: =1000+H61 -> 29000 | L61: =K61*$L$2 -> 5800 | M61: =G61/(K61-L61) -> 0.50412677 | N61: =IF(M61<=$N$2,"Good Price","Bad Price") -> Bad Price
A62: =A61+1 -> 58 | B62: Bar | C62: Coffee | D62: Cream Cheese Coffee Ice | E62: Cream Cheese Coffee | F62: =VLOOKUP(D62,Master!$V$7:$W$1000,2,FALSE) -> B008 | G62: =VLOOKUP(D62,'Menu Bar'!$B$6:$I$1948,8,FALSE) -> 10095.084 | H62: 29000 | I62: =G62/H62 -> 0.34810635 | J62: =IF(I62<=$J$2,"Good Price","Bad Price") -> Good Price | K62: =1000+H62 -> 30000 | L62: =K62*$L$2 -> 6000 | M62: =G62/(K62-L62) -> 0.4206285 | N62: =IF(M62<=$N$2,"Good Price","Bad Price") -> Bad Price
A63: =A62+1 -> 59 | B63: Bar | C63: Coffee | D63: Creamy Brulle Ice | E63: Creambrulle Ice | F63: =VLOOKUP(D63,Master!$V$7:$W$1000,2,FALSE) -> B033 | G63: =VLOOKUP(D63,'Menu Bar'!$B$6:$I$1948,8,FALSE) -> 8552.8212 | H63: 28000 | I63: =G63/H63 -> 0.3054579 | J63: =IF(I63<=$J$2,"Good Price","Bad Price") -> Good Price | K63: 28000 | L63: =K63*$L$2 -> 5600 | M63: =G63/(K63-L63) -> 0.38182237 | N63: =IF(M63<=$N$2,"Good Price","Bad Price") -> Bad Price
A64: =A63+1 -> 60 | B64: Bar | C64: Coffee | D64: Creamy Brulle Hot | E64: Creambrulle Hot | F64: =VLOOKUP(D64,Master!$V$7:$W$1000,2,FALSE) -> B034 | G64: =VLOOKUP(D64,'Menu Bar'!$B$6:$I$1948,8,FALSE) -> 6918.3032 | H64: 27000 | I64: =G64/H64 -> 0.25623345 | J64: =IF(I64<=$J$2,"Good Price","Bad Price") -> Good Price | K64: 27000 | L64: =K64*$L$2 -> 5400 | M64: =G64/(K64-L64) -> 0.32029181 | N64: =IF(M64<=$N$2,"Good Price","Bad Price") -> Good Price
A65: =A64+1 -> 61 | B65: Bar | C65: Coffee | D65: Matcha Coffe Ice | E65: Matcha Coffee | F65: =VLOOKUP(D65,Master!$V$7:$W$1000,2,FALSE) -> B007 | G65: =VLOOKUP(D65,'Menu Bar'!$B$6:$I$1948,8,FALSE) -> 13521.31 | H65: 33000 | I65: =G65/H65 -> 0.40973667 | J65: =IF(I65<=$J$2,"Good Price","Bad Price") -> Bad Price | K65: =1000+H65 -> 34000 | L65: =K65*$L$2 -> 6800 | M65: =G65/(K65-L65) -> 0.49710699 | N65: =IF(M65<=$N$2,"Good Price","Bad Price") -> Bad Price
A66: =A65+1 -> 62 | B66: Bar | C66: Mocktail & Squash | D66: Kiwi Delight | F66: =VLOOKUP(D66,Master!$V$7:$W$1000,2,FALSE) -> B009 | G66: =VLOOKUP(D66,'Menu Bar'!$B$6:$I$1948,8,FALSE) -> 6369.3474 | H66: 27000 | I66: =G66/H66 -> 0.23590175 | J66: =IF(I66<=$J$2,"Good Price","Bad Price") -> Good Price | K66: =1000+H66 -> 28000 | L66: =K66*$L$2 -> 5600 | M66: =G66/(K66-L66) -> 0.28434586 | N66: =IF(M66<=$N$2,"Good Price","Bad Price") -> Good Price
A67: =A66+1 -> 63 | B67: Bar | C67: Mocktail & Squash | D67: Mango Tango | F67: =VLOOKUP(D67,Master!$V$7:$W$1000,2,FALSE) -> B010 | G67: =VLOOKUP(D67,'Menu Bar'!$B$6:$I$1948,8,FALSE) -> #N/A | H67: 27000 | I67: =G67/H67 -> #N/A | J67: =IF(I67<=$J$2,"Good Price","Bad Price") -> #N/A | K67: =1000+H67 -> 28000 | L67: =K67*$L$2 -> 5600 | M67: =G67/(K67-L67) -> #N/A | N67: =IF(M67<=$N$2,"Good Price","Bad Price") -> #N/A
A68: =A67+1 -> 64 | B68: Bar | C68: Mocktail & Squash | D68: Strawberry Dream | F68: =VLOOKUP(D68,Master!$V$7:$W$1000,2,FALSE) -> B010 | G68: =VLOOKUP(D68,'Menu Bar'!$B$6:$I$1948,8,FALSE) -> 6605.2974 | H68: 27000 | I68: =G68/H68 -> 0.24464064 | J68: =IF(I68<=$J$2,"Good Price","Bad Price") -> Good Price | K68: =1000+H68 -> 28000 | L68: =K68*$L$2 -> 5600 | M68: =G68/(K68-L68) -> 0.29487935 | N68: =IF(M68<=$N$2,"Good Price","Bad Price") -> Good Price
A69: =A68+1 -> 65 | B69: Bar | C69: Desserts | D69: Tropical Ice Cream Scoop | F69: =VLOOKUP(D69,Master!$V$7:$W$1000,2,FALSE) -> M0165 | G69: =VLOOKUP(D69,'Menu Bar'!$B$6:$I$1948,8,FALSE) -> 7209.3214 | H69: 20000 | I69: =G69/H69 -> 0.36046607 | J69: =IF(I69<=$J$2,"Good Price","Bad Price") -> Bad Price | K69: 20000 | L69: =K69*$L$2 -> 4000 | M69: =G69/(K69-L69) -> 0.45058259 | N69: =IF(M69<=$N$2,"Good Price","Bad Price") -> Bad Price
A70: =A69+1 -> 66 | B70: Bar | C70: Coffee | D70: Extra Espresso | F70: =VLOOKUP(D70,Master!$V$7:$W$1000,2,FALSE) -> M0047 | G70: =VLOOKUP(D70,'Menu Bar'!$B$6:$I$1948,8,FALSE) -> 4063.9547 | H70: 18000 | I70: =G70/H70 -> 0.22577526 | J70: =IF(I70<=$J$2,"Good Price","Bad Price") -> Good Price | K70: =1000+H70 -> 19000 | L70: =K70*$L$2 -> 3800 | M70: =G70/(K70-L70) -> 0.26736544 | N70: =IF(M70<=$N$2,"Good Price","Bad Price") -> Good Price
A71: =A70+1 -> 67 | E71: Cincau | H71: 26000 | K71: =1000+H71 -> 27000 | L71: =K71*$L$2 -> 5400 | M71: =G71/(K71-L71) -> 0 | N71: =IF(M71<=$N$2,"Good Price","Bad Price") -> Good Price
A72: =A71+1 -> 68 | E72: Es Cendol | H72: 26000 | K72: =1000+H72 -> 27000 | L72: =K72*$L$2 -> 5400 | M72: =G72/(K72-L72) -> 0 | N72: =IF(M72<=$N$2,"Good Price","Bad Price") -> Good Price
A73: =A72+1 -> 69 | E73: Wedang Jahe | H73: 28000 | K73: =1000+H73 -> 29000 | L73: =K73*$L$2 -> 5800 | M73: =G73/(K73-L73) -> 0 | N73: =IF(M73<=$N$2,"Good Price","Bad Price") -> Good Price
A74: =A73+1 -> 70 | E74: Bajigur | H74: 22000 | K74: =1000+H74 -> 23000 | L74: =K74*$L$2 -> 4600 | M74: =G74/(K74-L74) -> 0 | N74: =IF(M74<=$N$2,"Good Price","Bad Price") -> Good Price
A75: =A74+1 -> 71 | E75: Bandrek | H75: 24000 | K75: =1000+H75 -> 25000 | L75: =K75*$L$2 -> 5000 | M75: =G75/(K75-L75) -> 0 | N75: =IF(M75<=$N$2,"Good Price","Bad Price") -> Good Price
A76: =A75+1 -> 72 | E76: Kopi Jahe Dingin | H76: 26000 | K76: =1000+H76 -> 27000 | L76: =K76*$L$2 -> 5400 | M76: =G76/(K76-L76) -> 0 | N76: =IF(M76<=$N$2,"Good Price","Bad Price") -> Good Price
A77: =A76+1 -> 73 | E77: Kopi Jahe Panas | H77: 24000 | K77: =1000+H77 -> 25000 | L77: =K77*$L$2 -> 5000 | M77: =G77/(K77-L77) -> 0 | N77: =IF(M77<=$N$2,"Good Price","Bad Price") -> Good Price
A78: =A77+1 -> 74 | E78: Black Raspberry | G78: =VLOOKUP(E78,'Menu Bar'!$B$6:$J$1982,8,FALSE) -> 9198.8929 | H78: 28000 | I78: =G78/H78 -> 0.32853189 | J78: =IF(I78<=$J$2,"Good Price","Bad Price") -> Good Price | K78: =1000+H78 -> 29000 | L78: =K78*$L$2 -> 5800 | M78: =G78/(K78-L78) -> 0.39650401 | N78: =IF(M78<=$N$2,"Good Price","Bad Price") -> Bad Price
A79: =A78+1 -> 75 | E79: Black Apple | G79: =VLOOKUP(E79,'Menu Bar'!$B$6:$J$1982,8,FALSE) -> 4503.3032 | H79: 28000 | I79: =G79/H79 -> 0.16083226 | J79: =IF(I79<=$J$2,"Good Price","Bad Price") -> Good Price | K79: =1000+H79 -> 29000 | L79: =K79*$L$2 -> 5800 | M79: =G79/(K79-L79) -> 0.19410789 | N79: =IF(M79<=$N$2,"Good Price","Bad Price") -> Good Price
A80: =A79+1 -> 76 | E80: Black Lemon | G80: =VLOOKUP(E80,'Menu Bar'!$B$6:$J$1982,8,FALSE) -> 7848.3871 | H80: 28000 | I80: =G80/H80 -> 0.28029954 | J80: =IF(I80<=$J$2,"Good Price","Bad Price") -> Good Price | K80: =1000+H80 -> 29000 | L80: =K80*$L$2 -> 5800 | M80: =G80/(K80-L80) -> 0.33829255 | N80: =IF(M80<=$N$2,"Good Price","Bad Price") -> Good Price
A81: =A80+1 -> 77 | F81: z | G81: z | H81: z | I81: z | J81: z | K81: =1000+H81 -> #VALUE! | L81: =K81*$L$2 -> #VALUE! | M81: =G81/(K81-L81) -> #VALUE! | N81: =IF(M81<=$N$2,"Good Price","Bad Price") -> #VALUE!
A82: =A81+1 -> 78 | B82: Kitchen | C82: Light Meals | D82: Nachos Primero | F82: =VLOOKUP(D82,Master!$V$7:$W$1000,2,FALSE) -> M0095 | G82: =VLOOKUP(D82,'Menu Kitchen'!$B$6:$I$2085,8,FALSE) -> 8580.1548 | H82: 20000 | I82: =G82/H82 -> 0.42900774 | J82: =IF(I82<=$J$2,"Good Price","Bad Price") -> Bad Price | K82: =1000+H82 -> 21000 | L82: =K82*$L$2 -> 4200 | M82: =G82/(K82-L82) -> 0.5107235 | N82: =IF(M82<=$N$2,"Good Price","Bad Price") -> Bad Price
A83: =A82+1 -> 79 | B83: Kitchen | C83: Light Meals | D83: French Fries | F83: =VLOOKUP(D83,Master!$V$7:$W$1000,2,FALSE) -> M0052 | G83: =VLOOKUP(D83,'Menu Kitchen'!$B$6:$I$2085,8,FALSE) -> 8253.52 | H83: 17000 | I83: =G83/H83 -> 0.48550118 | J83: =IF(I83<=$J$2,"Good Price","Bad Price") -> Bad Price | K83: =1000+H83 -> 18000 | L83: =K83*$L$2 -> 3600 | M83: =G83/(K83-L83) -> 0.57316111 | N83: =IF(M83<=$N$2,"Good Price","Bad Price") -> Bad Price
A84: =A83+1 -> 80 | B84: Kitchen | C84: Main Course & Bowl | D84: FF & Sausage Bratwurst | F84: =VLOOKUP(D84,Master!$V$7:$W$1000,2,FALSE) -> M0053 | G84: =VLOOKUP(D84,'Menu Kitchen'!$B$6:$I$2085,8,FALSE) -> 8964.4683 | H84: 22000 | I84: =G84/H84 -> 0.40747583 | J84: =IF(I84<=$J$2,"Good Price","Bad Price") -> Bad Price | K84: =1000+H84 -> 23000 | L84: =K84*$L$2 -> 4600 | M84: =G84/(K84-L84) -> 0.48719937 | N84: =IF(M84<=$N$2,"Good Price","Bad Price") -> Bad Price
A85: =A84+1 -> 81 | B85: Kitchen | C85: Main Course & Bowl | D85: Crispy Chicken Dice | F85: =VLOOKUP(D85,Master!$V$7:$W$1000,2,FALSE) -> M0099 | G85: =VLOOKUP(D85,'Menu Kitchen'!$B$6:$I$2085,8,FALSE) -> 9150.35 | H85: 22000 | I85: =G85/H85 -> 0.415925 | J85: =IF(I85<=$J$2,"Good Price","Bad Price") -> Bad Price | K85: =1000+H85 -> 23000 | L85: =K85*$L$2 -> 4600 | M85: =G85/(K85-L85) -> 0.49730163 | N85: =IF(M85<=$N$2,"Good Price","Bad Price") -> Bad Price
A86: =A85+1 -> 82 | B86: Kitchen | C86: Light Meals | D86: Cireng Bumbu | E86: Cireng Bumbu Rujak | F86: =VLOOKUP(D86,Master!$V$7:$W$1000,2,FALSE) -> M0051 | G86: =VLOOKUP(D86,'Menu Kitchen'!$B$6:$I$2085,8,FALSE) -> 9465.2963 | H86: 19000 | I86: =G86/H86 -> 0.49817349 | J86: =IF(I86<=$J$2,"Good Price","Bad Price") -> Bad Price | K86: =1000+H86 -> 20000 | L86: =K86*$L$2 -> 4000 | M86: =G86/(K86-L86) -> 0.59158102 | N86: =IF(M86<=$N$2,"Good Price","Bad Price") -> Bad Price
A87: =A86+1 -> 83 | B87: Kitchen | C87: Light Meals | D87: Cireng Lada garam | F87: =VLOOKUP(D87,Master!$V$7:$W$1000,2,FALSE) -> M0050 | G87: =VLOOKUP(D87,'Menu Kitchen'!$B$6:$I$2085,8,FALSE) -> 9404.34 | H87: 20000 | I87: =G87/H87 -> 0.470217 | J87: =IF(I87<=$J$2,"Good Price","Bad Price") -> Bad Price | K87: =1000+H87 -> 21000 | L87: =K87*$L$2 -> 4200 | M87: =G87/(K87-L87) -> 0.55978214 | N87: =IF(M87<=$N$2,"Good Price","Bad Price") -> Bad Price
A88: =A87+1 -> 84 | B88: Kitchen | C88: Light Meals | D88: Tahu Lada Garam | F88: =VLOOKUP(D88,Master!$V$7:$W$1000,2,FALSE) -> M0049 | G88: =VLOOKUP(D88,'Menu Kitchen'!$B$6:$I$2085,8,FALSE) -> 4868.215 | H88: 20000 | I88: =G88/H88 -> 0.24341075 | J88: =IF(I88<=$J$2,"Good Price","Bad Price") -> Good Price | K88: =1000+H88 -> 21000 | L88: =K88*$L$2 -> 4200 | M88: =G88/(K88-L88) -> 0.2897747 | N88: =IF(M88<=$N$2,"Good Price","Bad Price") -> Good Price
A89: =A88+1 -> 85 | B89: Kitchen | C89: Light Meals | D89: Tahu Pletok | F89: =VLOOKUP(D89,Master!$V$7:$W$1000,2,FALSE) -> B021 | G89: =VLOOKUP(D89,'Menu Kitchen'!$B$6:$I$2085,8,FALSE) -> 9631.7962 | H89: 19000 | I89: =G89/H89 -> 0.50693664 | J89: =IF(I89<=$J$2,"Good Price","Bad Price") -> Bad Price | K89: =1000+H89 -> 20000 | L89: =K89*$L$2 -> 4000 | M89: =G89/(K89-L89) -> 0.60198726 | N89: =IF(M89<=$N$2,"Good Price","Bad Price") -> Bad Price
A90: =A89+1 -> 86 | B90: Kitchen | C90: Light Meals | D90: Tempe Tepung | E90: Tempe Crispy | F90: =VLOOKUP(D90,Master!$V$7:$W$1000,2,FALSE) -> B022 | G90: =VLOOKUP(D90,'Menu Kitchen'!$B$6:$I$2085,8,FALSE) -> 5615.131 | H90: 17000 | I90: =G90/H90 -> 0.33030183 | J90: =IF(I90<=$J$2,"Good Price","Bad Price") -> Good Price | K90: =1000+H90 -> 18000 | L90: =K90*$L$2 -> 3600 | M90: =G90/(K90-L90) -> 0.38993966 | N90: =IF(M90<=$N$2,"Good Price","Bad Price") -> Bad Price
A91: =A90+1 -> 87 | B91: Kitchen | C91: Main Course & Bowl | D91: Bakso Cuanki | F91: =VLOOKUP(D91,Master!$V$7:$W$1000,2,FALSE) -> B030 | G91: =VLOOKUP(D91,'Menu Kitchen'!$B$6:$I$2085,8,FALSE) -> 8102.3111 | H91: 25000 | I91: =G91/H91 -> 0.32409244 | J91: =IF(I91<=$J$2,"Good Price","Bad Price") -> Good Price | K91: =1000+H91 -> 26000 | L91: =K91*$L$2 -> 5200 | M91: =G91/(K91-L91) -> 0.38953419 | N91: =IF(M91<=$N$2,"Good Price","Bad Price") -> Bad Price
A92: =A91+1 -> 88 | B92: Kitchen | C92: Light Meals | D92: Bala-Bala | F92: =VLOOKUP(D92,Master!$V$7:$W$1000,2,FALSE) -> B024 | G92: =VLOOKUP(D92,'Menu Kitchen'!$B$6:$I$2085,8,FALSE) -> 6553.8 | H92: 20000 | I92: =G92/H92 -> 0.32769 | J92: =IF(I92<=$J$2,"Good Price","Bad Price") -> Good Price | K92: =1000+H92 -> 21000 | L92: =K92*$L$2 -> 4200 | M92: =G92/(K92-L92) -> 0.39010714 | N92: =IF(M92<=$N$2,"Good Price","Bad Price") -> Bad Price
A93: =A92+1 -> 89 | B93: Kitchen | C93: Extra Kitchen | D93: Sate Telur Puyuh | F93: =VLOOKUP(D93,Master!$V$7:$W$1000,2,FALSE) -> S001 | G93: =VLOOKUP(D93,'Production Kitchen'!B9:L1030,10,FALSE) -> 1620.3422 | H93: 4000 | I93: =G93/H93 -> 0.40508554 | J93: =IF(I93<=$J$2,"Good Price","Bad Price") -> Bad Price | K93: =1000+H93 -> 5000 | L93: =K93*$L$2 -> 1000 | M93: =G93/(K93-L93) -> 0.40508554 | N93: =IF(M93<=$N$2,"Good Price","Bad Price") -> Bad Price
A94: =A93+1 -> 90 | B94: Kitchen | C94: Extra Kitchen | D94: Sate Jando | F94: =VLOOKUP(D94,Master!$V$7:$W$1000,2,FALSE) -> S002 | G94: =VLOOKUP(D94,'Production Kitchen'!B9:L1031,10,FALSE) -> 1296.7193 | H94: 4000 | I94: =G94/H94 -> 0.32417984 | J94: =IF(I94<=$J$2,"Good Price","Bad Price") -> Good Price | K94: =1000+H94 -> 5000 | L94: =K94*$L$2 -> 1000 | M94: =G94/(K94-L94) -> 0.32417984 | N94: =IF(M94<=$N$2,"Good Price","Bad Price") -> Good Price
A95: =A94+1 -> 91 | B95: Kitchen | C95: Extra Kitchen | D95: Sate Kikil | F95: =VLOOKUP(D95,Master!$V$7:$W$1000,2,FALSE) -> S007 | G95: =VLOOKUP(D95,'Production Kitchen'!B9:L1032,10,FALSE) -> 501.69301 | H95: 4000 | I95: =G95/H95 -> 0.12542325 | J95: =IF(I95<=$J$2,"Good Price","Bad Price") -> Good Price | K95: =1000+H95 -> 5000 | L95: =K95*$L$2 -> 1000 | M95: =G95/(K95-L95) -> 0.12542325 | N95: =IF(M95<=$N$2,"Good Price","Bad Price") -> Good Price
A96: =A95+1 -> 92 | B96: Kitchen | C96: Extra Kitchen | D96: Sate Kulit | F96: =VLOOKUP(D96,Master!$V$7:$W$1000,2,FALSE) -> S004 | G96: =VLOOKUP(D96,'Production Kitchen'!B9:L1033,10,FALSE) -> 797.86044 | H96: 4000 | I96: =G96/H96 -> 0.19946511 | J96: =IF(I96<=$J$2,"Good Price","Bad Price") -> Good Price | K96: =1000+H96 -> 5000 | L96: =K96*$L$2 -> 1000 | M96: =G96/(K96-L96) -> 0.19946511 | N96: =IF(M96<=$N$2,"Good Price","Bad Price") -> Good Price
A97: =A96+1 -> 93 | B97: Kitchen | C97: Extra Kitchen | D97: Sate Usus | F97: =VLOOKUP(D97,Master!$V$7:$W$1000,2,FALSE) -> S003 | G97: =VLOOKUP(D97,'Production Kitchen'!B9:L1034,10,FALSE) -> 1053.4387 | H97: 4000 | I97: =G97/H97 -> 0.26335967 | J97: =IF(I97<=$J$2,"Good Price","Bad Price") -> Good Price | K97: =1000+H97 -> 5000 | L97: =K97*$L$2 -> 1000 | M97: =G97/(K97-L97) -> 0.26335967 | N97: =IF(M97<=$N$2,"Good Price","Bad Price") -> Good Price
A98: =A97+1 -> 94 | B98: Kitchen | C98: Extra Kitchen | D98: Sate Paru | F98: =VLOOKUP(D98,Master!$V$7:$W$1000,2,FALSE) -> S005 | G98: =VLOOKUP(D98,'Production Kitchen'!B9:L1035,10,FALSE) -> 1341.4338 | H98: 4000 | I98: =G98/H98 -> 0.33535845 | J98: =IF(I98<=$J$2,"Good Price","Bad Price") -> Good Price | K98: =1000+H98 -> 5000 | L98: =K98*$L$2 -> 1000 | M98: =G98/(K98-L98) -> 0.33535845 | N98: =IF(M98<=$N$2,"Good Price","Bad Price") -> Good Price
A99: =A98+1 -> 95 | B99: Kitchen | C99: Extra Kitchen | D99: Sate Ati Ampela | F99: =VLOOKUP(D99,Master!$V$7:$W$1000,2,FALSE) -> S006 | G99: =VLOOKUP(D99,'Production Kitchen'!B9:L1036,10,FALSE) -> 1193.8488 | H99: 4000 | I99: =G99/H99 -> 0.29846219 | J99: =IF(I99<=$J$2,"Good Price","Bad Price") -> Good Price | K99: =1000+H99 -> 5000 | L99: =K99*$L$2 -> 1000 | M99: =G99/(K99-L99) -> 0.29846219 | N99: =IF(M99<=$N$2,"Good Price","Bad Price") -> Good Price
A100: =A99+1 -> 96 | B100: Kitchen | C100: Desserts | D100: Pancake | E100: Chocoberry Pancake | F100: =VLOOKUP(D100,Master!$V$7:$W$1000,2,FALSE) -> B004 | G100: =VLOOKUP(D100,'Menu Kitchen'!$B$6:$I$2085,8,FALSE) -> 14382.317 | H100: 35000 | I100: =G100/H100 -> 0.41092333 | J100: =IF(I100<=$J$2,"Good Price","Bad Price") -> Bad Price | K100: 35000 | L100: =K100*$L$2 -> 7000 | M100: =G100/(K100-L100) -> 0.51365417 | N100: =IF(M100<=$N$2,"Good Price","Bad Price") -> Bad Price
...

Sheet Menu Kitchen
A1: Resep Menu Kitchen
A2: The Soko Coffee Tea Chocolate
A5: Kode | B5: Menu | C5: Bahan | D5: Recipe QTY | E5: Satuan | F5: Hrg. Satuan | G5: HPP | H5: OH. Cost | I5: HPP Net | J5: Checker | K5: Ket
A6: =VLOOKUP(B6,Master!$V$7:$W$150,2,FALSE) -> M0049 | B6: Tahu Lada Garam | G6: =SUM(G7:G18) -> 4425.65 | H6: 0.1 | I6: =G6+(G6*H6) -> 4868.215 | J6: FALSE | K6: FALSE
C7: Tahu | D7: 3 | E7: =VLOOKUP(C7,Master!$B$6:$N$1000,9,FALSE) -> unit | F7: =VLOOKUP(C7,Master!$B$6:$N$1000,10,FALSE) -> 800 | G7: =D7*F7 -> 2400
C8: Cabe Rawit | D8: 5 | E8: =VLOOKUP(C8,Master!$B$6:$N$1000,9,FALSE) -> gr | F8: =VLOOKUP(C8,Master!$B$6:$N$1000,10,FALSE) -> 50 | G8: =D8*F8 -> 250
C9: Daun Bawang | D9: 3 | E9: =VLOOKUP(C9,Master!$B$6:$N$1000,9,FALSE) -> gr | F9: =VLOOKUP(C9,Master!$B$6:$N$1000,10,FALSE) -> 13 | G9: =D9*F9 -> 39
C10: Bawang Putih | D10: 2 | E10: =VLOOKUP(C10,Master!$B$6:$N$1000,9,FALSE) -> gr | F10: =VLOOKUP(C10,Master!$B$6:$N$1000,10,FALSE) -> 40 | G10: =D10*F10 -> 80
C11: Daun Jeruk | D11: 2 | E11: =VLOOKUP(C11,Master!$B$6:$N$1000,9,FALSE) -> gr | F11: =VLOOKUP(C11,Master!$B$6:$N$1000,10,FALSE) -> 64.2 | G11: =D11*F11 -> 128.4
C12: Cabe Merah Besar | D12: 4 | E12: =VLOOKUP(C12,Master!$B$6:$N$1000,9,FALSE) -> gr | F12: =VLOOKUP(C12,Master!$B$6:$N$1000,10,FALSE) -> 40 | G12: =D12*F12 -> 160
C13: Tepung | D13: 5 | E13: =VLOOKUP(C13,Master!$B$6:$N$1000,9,FALSE) -> gr | F13: =VLOOKUP(C13,Master!$B$6:$N$1000,10,FALSE) -> 14.25 | G13: =D13*F13 -> 71.25
C14: Powder Chicken | D14: 2 | E14: =VLOOKUP(C14,Master!$B$6:$N$1000,9,FALSE) -> gr | F14: =VLOOKUP(C14,Master!$B$6:$N$1000,10,FALSE) -> 38.5 | G14: =D14*F14 -> 77
C15: Merica | D15: 2 | E15: =VLOOKUP(C15,Master!$B$6:$N$1000,9,FALSE) -> gr | F15: =VLOOKUP(C15,Master!$B$6:$N$1000,10,FALSE) -> 90 | G15: =D15*F15 -> 180 | J15: cari barang subtitusi
C16: Lunch Box Ukuran M | D16: 1 | E16: =VLOOKUP(C16,Master!$B$6:$N$1000,9,FALSE) -> pcs | F16: =VLOOKUP(C16,Master!$B$6:$N$1000,10,FALSE) -> 1040 | G16: =D16*F16 -> 1040
A19: =VLOOKUP(B19,Master!$V$7:$W$150,2,FALSE) -> M0052 | B19: French Fries | G19: =SUM(G20:G25) -> 7503.2 | H19: 0.1 | I19: =G19+(G19*H19) -> 8253.52 | J19: FALSE | K19: FALSE
C20: Potato Cringkle Cut | D20: 150 | E20: =VLOOKUP(C20,Master!$B$6:$N$1000,9,FALSE) -> gr | F20: =VLOOKUP(C20,Master!$B$6:$N$1000,10,FALSE) -> 39.738 | G20: =D20*F20 -> 5960.7
C21: Powder Chicken | D21: 3 | E21: =VLOOKUP(C21,Master!$B$6:$N$1000,9,FALSE) -> gr | F21: =VLOOKUP(C21,Master!$B$6:$N$1000,10,FALSE) -> 38.5 | G21: =D21*F21 -> 115.5
C22: Chilli Sauce | D22: 10 | E22: =VLOOKUP(C22,Master!$B$6:$N$1000,9,FALSE) -> gr | F22: =VLOOKUP(C22,Master!$B$6:$N$1000,10,FALSE) -> 22.2 | G22: =D22*F22 -> 222
C23: Tomato | D23: 10 | E23: =VLOOKUP(C23,Master!$B$6:$N$1000,9,FALSE) -> gr | F23: =VLOOKUP(C23,Master!$B$6:$N$1000,10,FALSE) -> 16.5 | G23: =D23*F23 -> 165
C24: Lunch Box Ukuran M | D24: 1 | E24: =VLOOKUP(C24,Master!$B$6:$N$1000,9,FALSE) -> pcs | F24: =VLOOKUP(C24,Master!$B$6:$N$1000,10,FALSE) -> 1040 | G24: =D24*F24 -> 1040
A26: =VLOOKUP(B26,Master!$V$7:$W$150,2,FALSE) -> M0053 | B26: FF & Sausage Bratwurst | G26: =SUM(G27:G34) -> 8149.5167 | H26: 0.1 | I26: =G26+(G26*H26) -> 8964.4683 | J26: FALSE | K26: FALSE
C27: Potato Cringkle Cut | D27: 75 | E27: =VLOOKUP(C27,Master!$B$6:$N$1000,9,FALSE) -> gr | F27: =VLOOKUP(C27,Master!$B$6:$N$1000,10,FALSE) -> 39.738 | G27: =D27*F27 -> 2980.35
C28: Sosis | D28: 1 | E28: =VLOOKUP(C28,Master!$B$6:$N$1000,9,FALSE) -> pcs | F28: =VLOOKUP(C28,Master!$B$6:$N$1000,10,FALSE) -> 4666.6667 | G28: =D28*F28 -> 4666.6667
C29: Powder Chicken | D29: 3 | E29: =VLOOKUP(C29,Master!$B$6:$N$1000,9,FALSE) -> gr | F29: =VLOOKUP(C29,Master!$B$6:$N$1000,10,FALSE) -> 38.5 | G29: =D29*F29 -> 115.5
C30: Tomato | D30: 10 | E30: =VLOOKUP(C30,Master!$B$6:$N$1000,9,FALSE) -> gr | F30: =VLOOKUP(C30,Master!$B$6:$N$1000,10,FALSE) -> 16.5 | G30: =D30*F30 -> 165
C31: Chilli Sauce | D31: 10 | E31: =VLOOKUP(C31,Master!$B$6:$N$1000,9,FALSE) -> gr | F31: =VLOOKUP(C31,Master!$B$6:$N$1000,10,FALSE) -> 22.2 | G31: =D31*F31 -> 222
C32: Lunch Box Ukuran M | D32: 1 | E32: =VLOOKUP(C32,Master!$B$6:$N$1000,9,FALSE) -> pcs
A35: =VLOOKUP(B35,Master!$V$7:$W$150,2,FALSE) -> M0055 | B35: Aglio olio pasta Spaghetti | G35: =SUM(G36:G47) -> 7550.7222 | H35: 0.1 | I35: =G35+(G35*H35) -> 8305.7944 | J35: FALSE | K35: FALSE
C36: Ktc Pro Spaghetti Boiled | D36: 1 | E36: =VLOOKUP(C36,Master!$B$6:$N$1000,9,FALSE) -> gr/pcs | F36: =VLOOKUP(C36,Master!$B$6:$N$1000,10,FALSE) -> 1601.7222 | G36: =D36*F36 -> 1601.7222
C37: Smoked Beef | D37: 20 | E37: =VLOOKUP(C37,Master!$B$6:$N$1000,9,FALSE) -> gr | F37: =VLOOKUP(C37,Master!$B$6:$N$1000,10,FALSE) -> 86 | G37: =D37*F37 -> 1720
C38: Jamur Champignon | D38: 10 | E38: =VLOOKUP(C38,Master!$B$6:$N$1000,9,FALSE) -> gr | F38: =VLOOKUP(C38,Master!$B$6:$N$1000,10,FALSE) -> 45 | G38: =D38*F38 -> 450
C39: Bawang Bombay | D39: 5 | E39: =VLOOKUP(C39,Master!$B$6:$N$1000,9,FALSE) -> gr | F39: =VLOOKUP(C39,Master!$B$6:$N$1000,10,FALSE) -> 40 | G39: =D39*F39 -> 200
C40: Cabe Rawit | D40: 5 | E40: =VLOOKUP(C40,Master!$B$6:$N$1000,9,FALSE) -> gr | F40: =VLOOKUP(C40,Master!$B$6:$N$1000,10,FALSE) -> 50 | G40: =D40*F40 -> 250
C41: Bawang Putih | D41: 5 | E41: =VLOOKUP(C41,Master!$B$6:$N$1000,9,FALSE) -> gr | F41: =VLOOKUP(C41,Master!$B$6:$N$1000,10,FALSE) -> 40 | G41: =D41*F41 -> 200
C42: Cabe Merah Besar | D42: 5 | E42: =VLOOKUP(C42,Master!$B$6:$N$1000,9,FALSE) -> gr | F42: =VLOOKUP(C42,Master!$B$6:$N$1000,10,FALSE) -> 40 | G42: =D42*F42 -> 200
C43: Merica | D43: 2 | E43: =VLOOKUP(C43,Master!$B$6:$N$1000,9,FALSE) -> gr | F43: =VLOOKUP(C43,Master!$B$6:$N$1000,10,FALSE) -> 90 | G43: =D43*F43 -> 180
C44: Powder Chicken | D44: 2 | E44: =VLOOKUP(C44,Master!$B$6:$N$1000,9,FALSE) -> gr | F44: =VLOOKUP(C44,Master!$B$6:$N$1000,10,FALSE) -> 38.5 | G44: =D44*F44 -> 77
C45: Leaf Oregano | D45: 1 | E45: =VLOOKUP(C45,Master!$B$6:$N$1000,9,FALSE) -> gr | F45: =VLOOKUP(C45,Master!$B$6:$N$1000,10,FALSE) -> 280 | G45: =D45*F45 -> 280
C46: Tortilla Corn | D46: 0.8 | E46: =VLOOKUP(C46,Master!$B$6:$N$1000,9,FALSE) -> pcs | F46: =VLOOKUP(C46,Master!$B$6:$N$1000,10,FALSE) -> 1690 | G46: =D46*F46 -> 1352
C47: Lunch Box Ukuran M | D47: 1 | E47: =VLOOKUP(C47,Master!$B$6:$N$1000,9,FALSE) -> pcs | F47: =VLOOKUP(C47,Master!$B$6:$N$1000,10,FALSE) -> 1040 | G47: =D47*F47 -> 1040
A48: =VLOOKUP(B48,Master!$V$7:$W$150,2,FALSE) -> M0125 | B48: Aglio olio pasta Fettucini | G48: =SUM(G49:G60) -> 7839.9279 | H48: 0.1 | I48: =G48+(G48*H48) -> 8623.9207 | J48: FALSE | K48: FALSE
C49: Ktc Pro Fettucini Boiled | D49: 1 | E49: =VLOOKUP(C49,Master!$B$6:$N$1000,9,FALSE) -> gr | F49: =VLOOKUP(C49,Master!$B$6:$N$1000,10,FALSE) -> 1890.9279 | G49: =D49*F49 -> 1890.9279
C50: Smoked Beef | D50: 20 | E50: =VLOOKUP(C50,Master!$B$6:$N$1000,9,FALSE) -> gr | F50: =VLOOKUP(C50,Master!$B$6:$N$1000,10,FALSE) -> 86 | G50: =D50*F50 -> 1720
C51: Jamur Champignon | D51: 10 | E51: =VLOOKUP(C51,Master!$B$6:$N$1000,9,FALSE) -> gr | F51: =VLOOKUP(C51,Master!$B$6:$N$1000,10,FALSE) -> 45 | G51: =D51*F51 -> 450
C52: Bawang Bombay | D52: 5 | E52: =VLOOKUP(C52,Master!$B$6:$N$1000,9,FALSE) -> gr | F52: =VLOOKUP(C52,Master!$B$6:$N$1000,10,FALSE) -> 40 | G52: =D52*F52 -> 200
C53: Cabe Rawit | D53: 5 | E53: =VLOOKUP(C53,Master!$B$6:$N$1000,9,FALSE) -> gr | F53: =VLOOKUP(C53,Master!$B$6:$N$1000,10,FALSE) -> 50 | G53: =D53*F53 -> 250
C54: Bawang Putih | D54: 5 | E54: =VLOOKUP(C54,Master!$B$6:$N$1000,9,FALSE) -> gr | F54: =VLOOKUP(C54,Master!$B$6:$N$1000,10,FALSE) -> 40 | G54: =D54*F54 -> 200
C55: Cabe Merah Besar | D55: 5 | E55: =VLOOKUP(C55,Master!$B$6:$N$1000,9,FALSE) -> gr | F55: =VLOOKUP(C55,Master!$B$6:$N$1000,10,FALSE) -> 40 | G55: =D55*F55 -> 200
C56: Merica | D56: 2 | E56: =VLOOKUP(C56,Master!$B$6:$N$1000,9,FALSE) -> gr | F56: =VLOOKUP(C56,Master!$B$6:$N$1000,10,FALSE) -> 90 | G56: =D56*F56 -> 180
C57: Powder Chicken | D57: 2 | E57: =VLOOKUP(C57,Master!$B$6:$N$1000,9,FALSE) -> gr | F57: =VLOOKUP(C57,Master!$B$6:$N$1000,10,FALSE) -> 38.5 | G57: =D57*F57 -> 77
C58: Leaf Oregano | D58: 1 | E58: =VLOOKUP(C58,Master!$B$6:$N$1000,9,FALSE) -> gr | F58: =VLOOKUP(C58,Master!$B$6:$N$1000,10,FALSE) -> 280 | G58: =D58*F58 -> 280
C59: Tortilla Corn | D59: 0.8 | E59: =VLOOKUP(C59,Master!$B$6:$N$1000,9,FALSE) -> pcs | F59: =VLOOKUP(C59,Master!$B$6:$N$1000,10,FALSE) -> 1690 | G59: =D59*F59 -> 1352
C60: Lunch Box Ukuran M | D60: 1 | E60: =VLOOKUP(C60,Master!$B$6:$N$1000,9,FALSE) -> pcs | F60: =VLOOKUP(C60,Master!$B$6:$N$1000,10,FALSE) -> 1040 | G60: =D60*F60 -> 1040
A61: =VLOOKUP(B61,Master!$V$7:$W$150,2,FALSE) -> M0057 | B61: Carbonara pasta spaghetti | G61: =SUM(G62:G73) -> 10210.156 | H61: 0.1 | I61: =G61+(G61*H61) -> 11231.171 | J61: FALSE | K61: FALSE
C62: Ktc Pro Spaghetti Boiled | D62: 1 | E62: =VLOOKUP(C62,Master!$B$6:$N$1000,9,FALSE) -> gr/pcs | F62: =VLOOKUP(C62,Master!$B$6:$N$1000,10,FALSE) -> 1601.7222 | G62: =D62*F62 -> 1601.7222
C63: UHT | D63: 100 | E63: =VLOOKUP(C63,Master!$B$6:$N$1000,9,FALSE) -> ml | F63: =VLOOKUP(C63,Master!$B$6:$N$1000,10,FALSE) -> 17.094333 | G63: =D63*F63 -> 1709.4333
C64: Cooking Cream | D64: 20 | E64: =VLOOKUP(C64,Master!$B$6:$N$1000,9,FALSE) -> ml | F64: =VLOOKUP(C64,Master!$B$6:$N$1000,10,FALSE) -> 66 | G64: =D64*F64 -> 1320
C65: Smoked Beef | D65: 20 | E65: =VLOOKUP(C65,Master!$B$6:$N$1000,9,FALSE) -> gr | F65: =VLOOKUP(C65,Master!$B$6:$N$1000,10,FALSE) -> 86 | G65: =D65*F65 -> 1720
C66: Jamur Champignon | D66: 10 | E66: =VLOOKUP(C66,Master!$B$6:$N$1000,9,FALSE) -> gr | F66: =VLOOKUP(C66,Master!$B$6:$N$1000,10,FALSE) -> 45 | G66: =D66*F66 -> 450
C67: Bawang Bombay | D67: 5 | E67: =VLOOKUP(C67,Master!$B$6:$N$1000,9,FALSE) -> gr | F67: =VLOOKUP(C67,Master!$B$6:$N$1000,10,FALSE) -> 40 | G67: =D67*F67 -> 200
C68: Powder Chicken | D68: 2 | E68: =VLOOKUP(C68,Master!$B$6:$N$1000,9,FALSE) -> gr | F68: =VLOOKUP(C68,Master!$B$6:$N$1000,10,FALSE) -> 38.5 | G68: =D68*F68 -> 77
C69: Merica | D69: 2 | E69: =VLOOKUP(C69,Master!$B$6:$N$1000,9,FALSE) -> gr | F69: =VLOOKUP(C69,Master!$B$6:$N$1000,10,FALSE) -> 90 | G69: =D69*F69 -> 180
C70: Leaf Oregano | D70: 2 | E70: =VLOOKUP(C70,Master!$B$6:$N$1000,9,FALSE) -> gr | F70: =VLOOKUP(C70,Master!$B$6:$N$1000,10,FALSE) -> 280 | G70: =D70*F70 -> 560
C71: Tortilla Corn | D71: 0.8 | E71: =VLOOKUP(C71,Master!$B$6:$N$1000,9,FALSE) -> pcs | F71: =VLOOKUP(C71,Master!$B$6:$N$1000,10,FALSE) -> 1690 | G71: =D71*F71 -> 1352
C72: Lunch Box Ukuran M | D72: 1 | E72: =VLOOKUP(C72,Master!$B$6:$N$1000,9,FALSE) -> pcs | F72: =VLOOKUP(C72,Master!$B$6:$N$1000,10,FALSE) -> 1040 | G72: =D72*F72 -> 1040
A74: =VLOOKUP(B74,Master!$V$7:$W$150,2,FALSE) -> M0062 | B74: Carbonara pasta fettucini | G74: =SUM(G75:G86) -> 10461.248 | H74: 0.1 | I74: =G74+(G74*H74) -> 11507.373 | J74: FALSE | K74: FALSE
C75: Ktc Pro Fettucini Boiled | D75: 1 | E75: =VLOOKUP(C75,Master!$B$6:$N$1000,9,FALSE) -> gr | F75: =VLOOKUP(C75,Master!$B$6:$N$1000,10,FALSE) -> 1890.9279 | G75: =D75*F75 -> 1890.9279
C76: UHT | D76: 120 | E76: =VLOOKUP(C76,Master!$B$6:$N$1000,9,FALSE) -> ml | F76: =VLOOKUP(C76,Master!$B$6:$N$1000,10,FALSE) -> 17.094333 | G76: =D76*F76 -> 2051.32
C77: Cooking Cream | D77: 30 | E77: =VLOOKUP(C77,Master!$B$6:$N$1000,9,FALSE) -> ml | F77: =VLOOKUP(C77,Master!$B$6:$N$1000,10,FALSE) -> 66 | G77: =D77*F77 -> 1980
C78: Smoked Beef | D78: 20 | E78: =VLOOKUP(C78,Master!$B$6:$N$1000,9,FALSE) -> gr | F78: =VLOOKUP(C78,Master!$B$6:$N$1000,10,FALSE) -> 86 | G78: =D78*F78 -> 1720
C79: Jamur Champignon | D79: 10 | E79: =VLOOKUP(C79,Master!$B$6:$N$1000,9,FALSE) -> gr | F79: =VLOOKUP(C79,Master!$B$6:$N$1000,10,FALSE) -> 45 | G79: =D79*F79 -> 450
C80: Bawang Bombay | D80: 5 | E80: =VLOOKUP(C80,Master!$B$6:$N$1000,9,FALSE) -> gr | F80: =VLOOKUP(C80,Master!$B$6:$N$1000,10,FALSE) -> 40 | G80: =D80*F80 -> 200
C81: Powder Chicken | D81: 2 | E81: =VLOOKUP(C81,Master!$B$6:$N$1000,9,FALSE) -> gr | F81: =VLOOKUP(C81,Master!$B$6:$N$1000,10,FALSE) -> 38.5 | G81: =D81*F81 -> 77
C82: Merica | D82: 2 | E82: =VLOOKUP(C82,Master!$B$6:$N$1000,9,FALSE) -> gr | F82: =VLOOKUP(C82,Master!$B$6:$N$1000,10,FALSE) -> 90 | G82: =D82*F82 -> 180
C83: Leaf Oregano | D83: 2 | E83: =VLOOKUP(C83,Master!$B$6:$N$1000,9,FALSE) -> gr | F83: =VLOOKUP(C83,Master!$B$6:$N$1000,10,FALSE) -> 280 | G83: =D83*F83 -> 560
C84: Tortilla Corn | D84: 0.8 | E84: =VLOOKUP(C84,Master!$B$6:$N$1000,9,FALSE) -> pcs | F84: =VLOOKUP(C84,Master!$B$6:$N$1000,10,FALSE) -> 1690 | G84: =D84*F84 -> 1352
C85: Lunch Box Ukuran M | D85: 1 | E85: =VLOOKUP(C85,Master!$B$6:$N$1000,9,FALSE) -> pcs
A87: =VLOOKUP(B87,Master!$V$7:$W$150,2,FALSE) -> M0058 | B87: Chicken Blackpepper | G87: =SUM(G88:G99) -> 9585.1348 | H87: 0.1 | I87: =G87+(G87*H87) -> 10543.648 | J87: FALSE | K87: FALSE
C88: Ayam Boneless Dada | D88: 60 | E88: =VLOOKUP(C88,Master!$B$6:$N$1000,9,FALSE) -> gr | F88: =VLOOKUP(C88,Master!$B$6:$N$1000,10,FALSE) -> 50 | G88: =D88*F88 -> 3000
C89: Ktc Pro Rice | D89: 1 | E89: =VLOOKUP(C89,Master!$B$6:$N$1000,9,FALSE) -> Porsi | F89: =VLOOKUP(C89,Master!$B$6:$N$1000,10,FALSE) -> 1093.9891 | G89: =D89*F89 -> 1093.9891
C90: KTC Pro Scrumble Egg | D90: 1 | E90: =VLOOKUP(C90,Master!$B$6:$N$1000,9,FALSE) -> gr/pcs | F90: =VLOOKUP(C90,Master!$B$6:$N$1000,10,FALSE) -> 2570.7587 | G90: =D90*F90 -> 2570.7587
C91: Ktc Pro Sauce Blackpepper | D91: 1 | E91: =VLOOKUP(C91,Master!$B$6:$N$1000,9,FALSE) -> gr/por | F91: =VLOOKUP(C91,Master!$B$6:$N$1000,10,FALSE) -> 1363.1871 | G91: =D91*F91 -> 1363.1871
C92: Paprika Green | D92: 2 | E92: =VLOOKUP(C92,Master!$B$6:$N$1000,9,FALSE) -> gr | F92: =VLOOKUP(C92,Master!$B$6:$N$1000,10,FALSE) -> 58.6 | G92: =D92*F92 -> 117.2
C93: Bawang Bombay | D93: 10 | E93: =VLOOKUP(C93,Master!$B$6:$N$1000,9,FALSE) -> gr | F93: =VLOOKUP(C93,Master!$B$6:$N$1000,10,FALSE) -> 40 | G93: =D93*F93 -> 400
C94: Lunch Box Ukuran M | D94: 1 | E94: =VLOOKUP(C94,Master!$B$6:$N$1000,9,FALSE) -> pcs | F94: =VLOOKUP(C94,Master!$B$6:$N$1000,10,FALSE) -> 1040 | G94: =D94*F94 -> 1040
A100: =VLOOKUP(B100,Master!$V$7:$W$150,2,FALSE) -> M0059 | B100: Beef Blackpepper | G100: =SUM(G101:G112) -> 14205.135 | H100: 0.1 | I100: =G100+(G100*H100) -> 15625.648 | J100: FALSE | K100: FALSE
C101: Daging Sapi Has Dalam | D101: 60 | E101: =VLOOKUP(C101,Master!$B$6:$N$1000,9,FALSE) -> gr | F101: =VLOOKUP(C101,Master!$B$6:$N$1000,10,FALSE) -> 127 | G101: =D101*F101 -> 7620
C102: Ktc Pro Rice | D102: 1 | E102: =VLOOKUP(C102,Master!$B$6:$N$1000,9,FALSE) -> Porsi | F102: =VLOOKUP(C102,Master!$B$6:$N$1000,10,FALSE) -> 1093.9891 | G102: =D102*F102 -> 1093.9891
C103: KTC Pro Scrumble Egg | D103: 1 | E103: =VLOOKUP(C103,Master!$B$6:$N$1000,9,FALSE) -> gr/pcs | F103: =VLOOKUP(C103,Master!$B$6:$N$1000,10,FALSE) -> 2570.7587 | G103: =D103*F103 -> 2570.7587
C104: Ktc Pro Sauce Blackpepper | D104: 1 | E104: =VLOOKUP(C104,Master!$B$6:$N$1000,9,FALSE) -> gr/por | F104: =VLOOKUP(C104,Master!$B$6:$N$1000,10,FALSE) -> 1363.1871 | G104: =D104*F104 -> 1363.1871
C105: Paprika Green | D105: 2 | E105: =VLOOKUP(C105,Master!$B$6:$N$1000,9,FALSE) -> gr | F105: =VLOOKUP(C105,Master!$B$6:$N$1000,10,FALSE) -> 58.6 | G105: =D105*F105 -> 117.2
C106: Bawang Bombay | D106: 10 | E106: =VLOOKUP(C106,Master!$B$6:$N$1000,9,FALSE) -> gr | F106: =VLOOKUP(C106,Master!$B$6:$N$1000,10,FALSE) -> 40 | G106: =D106*F106 -> 400
C107: Lunch Box Ukuran M | D107: 1 | E107: =VLOOKUP(C107,Master!$B$6:$N$1000,9,FALSE) -> pcs | F107: =VLOOKUP(C107,Master!$B$6:$N$1000,10,FALSE) -> 1040 | G107: =D107*F107 -> 1040
A113: =VLOOKUP(B113,Master!$V$7:$W$150,2,FALSE) -> M0063 | B113: Zupa Soup | G113: =SUM(G114:G124) -> 11299.864 | H113: 0.1 | I113: =G113+(G113*H113) -> 12429.85 | J113: FALSE | K113: FALSE
C114: Cooking Cream | D114: 30 | E114: =VLOOKUP(C114,Master!$B$6:$N$1000,9,FALSE) -> ml | F114: =VLOOKUP(C114,Master!$B$6:$N$1000,10,FALSE) -> 66 | G114: =D114*F114 -> 1980 | K114: Tidak Bisa Take Away
C115: UHT | D115: 120 | E115: =VLOOKUP(C115,Master!$B$6:$N$1000,9,FALSE) -> ml | F115: =VLOOKUP(C115,Master!$B$6:$N$1000,10,FALSE) -> 17.094333 | G115: =D115*F115 -> 2051.32
C116: Bawang Bombay | D116: 5 | E116: =VLOOKUP(C116,Master!$B$6:$N$1000,9,FALSE) -> gr | F116: =VLOOKUP(C116,Master!$B$6:$N$1000,10,FALSE) -> 40 | G116: =D116*F116 -> 200
C117: KTC Pro Mix Vegetable | D117: 1 | E117: =VLOOKUP(C117,Master!$B$6:$N$1000,9,FALSE) -> gr/pcs | F117: =VLOOKUP(C117,Master!$B$6:$N$1000,10,FALSE) -> 864.65116 | G117: =D117*F117 -> 864.65116
C118: Ayam Boneless Dada | D118: 60 | E118: =VLOOKUP(C118,Master!$B$6:$N$1000,9,FALSE) -> gr | F118: =VLOOKUP(C118,Master!$B$6:$N$1000,10,FALSE) -> 50 | G118: =D118*F118 -> 3000
C119: Tepung | D119: 3 | E119: =VLOOKUP(C119,Master!$B$6:$N$1000,9,FALSE) -> gr | F119: =VLOOKUP(C119,Master!$B$6:$N$1000,10,FALSE) -> 14.25 | G119: =D119*F119 -> 42.75
...

Sheet Production Kitchen
A1: Resep Production Kitchen
A2: The Soko Coffee Tea Chocolate
B4: 1 | C4: 2 | D4: 3 | E4: 4 | F4: 5 | G4: 6 | H4: 7 | I4: 8 | J4: 9 | K4: 10 | L4: 11
A5: No | B5: Menu | C5: Bahan | D5: Recipe QTY | E5: Satuan | F5: Hrg. Satuan | G5: HPP | H5: OH. Cost | I5: HPP Net | J5: Portion | K5: Harga/Porsi | L5: Yield Portion
A6: 1 | B6: Ktc Pro Cream Soup | D6: =SUM(D7:D15) -> 175 | E6: ml | G6: =SUM(G7:G16) -> 5076.07 | H6: 0.1 | I6: =G6+(G6*H6) -> 5583.677 | J6: 1 | K6: =I6/J6 -> 5583.677 | L6: =D6/J6 -> 175
C7: Cooking Cream | D7: 30 | E7: =VLOOKUP(C7,Master!$B$6:$N$1000,9,FALSE) -> ml | F7: =VLOOKUP(C7,Master!B7:N337,10,FALSE) -> 66 | G7: =D7*F7 -> 1980
C8: UHT | D8: 120 | E8: =VLOOKUP(C8,Master!$B$6:$N$1000,9,FALSE) -> ml | F8: =VLOOKUP(C8,Master!$B$7:$N$1000,10,FALSE) -> 17.094333 | G8: =D8*F8 -> 2051.32
C9: Bawang Bombay | D9: 5 | E9: =VLOOKUP(C9,Master!$B$6:$N$1000,9,FALSE) -> gr | F9: =VLOOKUP(C9,Master!$B$7:$N$1000,10,FALSE) -> 40 | G9: =D9*F9 -> 200
C10: Air Galon | D10: 0 | E10: =VLOOKUP(C10,Master!$B$6:$N$1000,9,FALSE) -> ml | F10: =VLOOKUP(C10,Master!$B$7:$N$1000,10,FALSE) -> 0.66315789 | G10: =D10*F10 -> 0
C11: Tepung | D11: 3 | E11: =VLOOKUP(C11,Master!$B$6:$N$1000,9,FALSE) -> gr | F11: =VLOOKUP(C11,Master!$B$7:$N$1000,10,FALSE) -> 14.25 | G11: =D11*F11 -> 42.75
C12: Mentega Curah | D12: 3 | E12: =VLOOKUP(C12,Master!$B$6:$N$1000,9,FALSE) -> gr | F12: =VLOOKUP(C12,Master!$B$7:$N$1000,10,FALSE) -> 39 | G12: =D12*F12 -> 117
C13: Parsley | D13: 2 | E13: =VLOOKUP(C13,Master!$B$6:$N$1000,9,FALSE) -> gr | F13: =VLOOKUP(C13,Master!$B$7:$N$1000,10,FALSE) -> 60 | G13: =D13*F13 -> 120
C14: Powder Chicken | D14: 10 | E14: =VLOOKUP(C14,Master!$B$6:$N$1000,9,FALSE) -> gr | F14: =VLOOKUP(C14,Master!$B$7:$N$1000,10,FALSE) -> 38.5 | G14: =D14*F14 -> 385
C15: Merica | D15: 2 | E15: =VLOOKUP(C15,Master!$B$6:$N$1000,9,FALSE) -> gr | F15: =VLOOKUP(C15,Master!$B$7:$N$1000,10,FALSE) -> 90 | G15: =D15*F15 -> 180
A17: 2 | B17: Ktc Pro Sauce Blackpepper | D17: =SUM(D18:D27) -> 1947 | E17: =VLOOKUP(B17,Master!B6:N243,9,FALSE) -> gr/por | G17: =SUM(G18:G27) -> 37177.829 | H17: 0.1 | I17: =G17+(G17*H17) -> 40895.612 | J17: 30 | K17: =I17/J17 -> 1363.1871 | L17: =D17/J17 -> 64.9
C18: Bawang Putih | D18: 40 | E18: =VLOOKUP(C18,Master!$B$6:$N$260,9,FALSE) -> gr | F18: =VLOOKUP(C18,Master!$B$7:$N$309,10,FALSE) -> 40 | G18: =D18*F18 -> 1600
C19: Bawang Bombay | D19: 100 | E19: =VLOOKUP(C19,Master!$B$6:$N$243,9,FALSE) -> gr | F19: =VLOOKUP(C19,Master!$B$7:$N$309,10,FALSE) -> 40 | G19: =D19*F19 -> 4000
C20: Merica | D20: 5 | E20: =VLOOKUP(C20,Master!$B$6:$N$243,9,FALSE) -> gr | F20: =VLOOKUP(C20,Master!$B$7:$N$309,10,FALSE) -> 90 | G20: =D20*F20 -> 450
C21: Tomato | D21: 1000 | E21: =VLOOKUP(C21,Master!$B$6:$N$243,9,FALSE) -> gr | F21: =VLOOKUP(C21,Master!$B$7:$N$309,10,FALSE) -> 16.5 | G21: =D21*F21 -> 16500
C22: Lada Hitam Biji | D22: 25 | E22: =VLOOKUP(C22,Master!$B$6:$N$243,9,FALSE) -> gr | F22: =VLOOKUP(C22,Master!$B$7:$N$309,10,FALSE) -> 26 | G22: =D22*F22 -> 650
C23: Oyster Sauce Panda | D23: 150 | E23: =VLOOKUP(C23,Master!$B$6:$N$243,9,FALSE) -> gr | F23: =VLOOKUP(C23,Master!$B$7:$N$309,10,FALSE) -> 75 | G23: =D23*F23 -> 11250
C24: Gula Merah / Aren Padat Kiloan | D24: 105 | E24: =VLOOKUP(C24,Master!$B$6:$N$243,9,FALSE) -> gr | F24: =VLOOKUP(C24,Master!$B$7:$N$309,10,FALSE) -> 17 | G24: =D24*F24 -> 1785
C25: Kecap Manis | D25: 20 | E25: =VLOOKUP(C25,Master!$B$6:$N$243,9,FALSE) -> gr | F25: =VLOOKUP(C25,Master!$B$7:$N$309,10,FALSE) -> 29.0625 | G25: =D25*F25 -> 581.25
C26: Garam | D26: 2 | E26: =VLOOKUP(C26,Master!$B$6:$N$243,9,FALSE) -> gr | F26: =VLOOKUP(C26,Master!$B$7:$N$309,10,FALSE) -> 15 | G26: =D26*F26 -> 30
C27: Air Galon | D27: 500 | E27: =VLOOKUP(C27,Master!$B$6:$N$243,9,FALSE) -> ml | F27: =VLOOKUP(C27,Master!$B$7:$N$309,10,FALSE) -> 0.66315789 | G27: =D27*F27 -> 331.57895
A28: 3 | B28: Ktc Pro Pancake | D28: =SUM(D29:D35) -> 527 | E28: =VLOOKUP(B28,Master!B6:N243,9,FALSE) -> gr/slice | G28: =SUM(G29:G35) -> 15722.2 | H28: 0.1 | I28: =G28+(G28*H28) -> 17294.42 | J28: 3 | K28: =I28/J28 -> 5764.8067 | L28: =D28/J28 -> 175.66667
C29: Tepung | D29: 200 | E29: =VLOOKUP(C29,Master!$B$6:$N$1000,9,FALSE) -> gr | F29: =VLOOKUP(C29,Master!$B$7:$N$1000,10,FALSE) -> 14.25 | G29: =D29*F29 -> 2850
C30: Baking Powder | D30: 2 | E30: =VLOOKUP(C30,Master!$B$6:$N$1000,9,FALSE) -> gr | F30: =VLOOKUP(C30,Master!$B$7:$N$1000,10,FALSE) -> 148.33333 | G30: =D30*F30 -> 296.66667
C31: Soda Kue | D31: 2 | E31: =VLOOKUP(C31,Master!$B$6:$N$1000,9,FALSE) -> gr | F31: =VLOOKUP(C31,Master!$B$7:$N$1000,10,FALSE) -> 83.333333 | G31: =D31*F31 -> 166.66667
C32: Mentega Curah | D32: 60 | E32: =VLOOKUP(C32,Master!$B$6:$N$1000,9,FALSE) -> gr | F32: =VLOOKUP(C32,Master!$B$7:$N$1000,10,FALSE) -> 39 | G32: =D32*F32 -> 2340
C33: UHT | D33: 200 | E33: =VLOOKUP(C33,Master!$B$6:$N$1000,9,FALSE) -> ml | F33: =VLOOKUP(C33,Master!$B$7:$N$1000,10,FALSE) -> 17.094333 | G33: =D33*F33 -> 3418.8667
C34: Telur Ayam | D34: 3 | E34: =VLOOKUP(C34,Master!$B$6:$N$1000,9,FALSE) -> pcs | F34: =VLOOKUP(C34,Master!$B$7:$N$1000,10,FALSE) -> 1866.6667 | G34: =D34*F34 -> 5600
C35: Gula pasir | D35: 60 | E35: =VLOOKUP(C35,Master!$B$6:$N$1000,9,FALSE) -> gr | F35: =VLOOKUP(C35,Master!$B$7:$N$1000,10,FALSE) -> 17.5 | G35: =D35*F35 -> 1050
A37: 4 | B37: Ktc Pro Choco Lava | D37: =SUM(D38:D43) -> 408 | E37: =VLOOKUP(B37,Master!B6:N243,9,FALSE) -> gr/por | G37: =SUM(G38:G42) -> 22512.5 | H37: 0.1 | I37: =G37+(G37*H37) -> 24763.75 | J37: 5 | K37: =I37/J37 -> 4952.75 | L37: =D37/J37 -> 81.6
C38: Dark Chocolate | D38: 210 | E38: =VLOOKUP(C38,Master!$B$6:$N$1000,9,FALSE) -> gr | F38: =VLOOKUP(C38,Master!$B$7:$N$1000,10,FALSE) -> 56 | G38: =D38*F38 -> 11760
C39: Mentega Curah | D39: 90 | E39: =VLOOKUP(C39,Master!$B$6:$N$1000,9,FALSE) -> gr | F39: =VLOOKUP(C39,Master!$B$7:$N$1000,10,FALSE) -> 39 | G39: =D39*F39 -> 3510
C40: Tepung | D40: 60 | E40: =VLOOKUP(C40,Master!$B$6:$N$1000,9,FALSE) -> gr | F40: =VLOOKUP(C40,Master!$B$7:$N$1000,10,FALSE) -> 14.25 | G40: =D40*F40 -> 855
C41: Telur Ayam | D41: 3 | E41: =VLOOKUP(C41,Master!$B$6:$N$1000,9,FALSE) -> pcs | F41: =VLOOKUP(C41,Master!$B$7:$N$1000,10,FALSE) -> 1866.6667 | G41: =D41*F41 -> 5600
C42: Gula pasir | D42: 45 | E42: =VLOOKUP(C42,Master!$B$6:$N$1000,9,FALSE) -> gr | F42: =VLOOKUP(C42,Master!$B$7:$N$1000,10,FALSE) -> 17.5 | G42: =D42*F42 -> 787.5
A44: 5 | B44: Ktc Pro Sauce Barbeque | D44: =SUM(D45:D56) -> 1411.5 | E44: =VLOOKUP(B44,Master!B13:N250,9,FALSE) -> Porsi | G44: =SUM(G45:G57) -> 30774 | H44: 0.1 | I44: =G44+(G44*H44) -> 33851.4 | J44: 63 | K44: =I44/J44 -> 537.32381 | L44: =D44/J44 -> 22.404762
C45: Jahe | D45: 20 | E45: =VLOOKUP(C45,Master!$B$6:$N$1000,9,FALSE) -> gr | F45: =VLOOKUP(C45,Master!$B$7:$N$1000,10,FALSE) -> 16 | G45: =D45*F45 -> 320
C46: Minyak Goreng | D46: 0 | E46: =VLOOKUP(C46,Master!$B$6:$N$1000,9,FALSE) -> ml | F46: =VLOOKUP(C46,Master!$B$7:$N$1000,10,FALSE) -> 16.222222 | G46: =D46*F46 -> 0
C47: Bawang Putih | D47: 200 | E47: =VLOOKUP(C47,Master!$B$6:$N$1000,9,FALSE) -> gr | F47: =VLOOKUP(C47,Master!$B$7:$N$1000,10,FALSE) -> 40 | G47: =D47*F47 -> 8000
C48: Bawang Bombay | D48: 80 | E48: =VLOOKUP(C48,Master!$B$6:$N$1000,9,FALSE) -> gr | F48: =VLOOKUP(C48,Master!$B$7:$N$1000,10,FALSE) -> 40 | G48: =D48*F48 -> 3200
C49: Tomato | D49: 1000 | E49: =VLOOKUP(C49,Master!$B$6:$N$1000,9,FALSE) -> gr | F49: =VLOOKUP(C49,Master!$B$7:$N$1000,10,FALSE) -> 16.5 | G49: =D49*F49 -> 16500
C50: Chilli Sauce | D50: 0 | E50: =VLOOKUP(C50,Master!$B$6:$N$1000,9,FALSE) -> gr | F50: =VLOOKUP(C50,Master!$B$7:$N$1000,10,FALSE) -> 22.2 | G50: =D50*F50 -> 0
C51: Gula Merah / Aren Padat Kiloan | D51: 105 | E51: =VLOOKUP(C51,Master!$B$6:$N$1000,9,FALSE) -> gr | F51: =VLOOKUP(C51,Master!$B$7:$N$1000,10,FALSE) -> 17 | G51: =D51*F51 -> 1785
C52: Leaf Oregano | D52: 1 | E52: =VLOOKUP(C52,Master!$B$6:$N$1000,9,FALSE) -> gr | F52: =VLOOKUP(C52,Master!$B$7:$N$1000,10,FALSE) -> 280 | G52: =D52*F52 -> 280
C53: Leaf Bay | D53: 1 | E53: =VLOOKUP(C53,Master!$B$6:$N$1000,9,FALSE) -> gr | F53: =VLOOKUP(C53,Master!$B$7:$N$1000,10,FALSE) -> 380 | G53: =D53*F53 -> 380
C54: Beef Powder | D54: 3 | E54: =VLOOKUP(C54,Master!$B$6:$N$1000,9,FALSE) -> gr | F54: =VLOOKUP(C54,Master!$B$7:$N$1000,10,FALSE) -> 38 | G54: =D54*F54 -> 114
C55: Cengkeh | D55: 0.5 | E55: =VLOOKUP(C55,Master!$B$6:$N$1000,9,FALSE) -> gr | F55: =VLOOKUP(C55,Master!$B$7:$N$1000,10,FALSE) -> 210 | G55: =D55*F55 -> 105
C56: Merica | D56: 1 | E56: =VLOOKUP(C56,Master!$B$6:$N$1000,9,FALSE) -> gr | F56: =VLOOKUP(C56,Master!$B$7:$N$1000,10,FALSE) -> 90 | G56: =D56*F56 -> 90
A58: 5 | B58: Ktc Pro Sauce Bolognaise | D58: =SUM(D59:D73) -> 1789 | E58: =VLOOKUP(B58,Master!B7:N263,9,FALSE) -> gr/pcs | G58: =SUM(G59:G73) -> 62731.111 | H58: 0.1 | I58: =G58+(G58*H58) -> 69004.222 | J58: 30 | K58: =I58/J58 -> 2300.1407 | L58: =D58/J58 -> 59.633333
C59: Minyak Goreng | D59: 50 | E59: =VLOOKUP(C59,Master!$B$6:$N$1000,9,FALSE) -> ml | F59: =VLOOKUP(C59,Master!$B$7:$N$1000,10,FALSE) -> 16.222222 | G59: =D59*F59 -> 811.11111
C60: Daging Sapi Has Dalam | D60: 250 | E60: =VLOOKUP(C60,Master!$B$6:$N$1000,9,FALSE) -> gr | F60: =VLOOKUP(C60,Master!$B$7:$N$1000,10,FALSE) -> 127 | G60: =D60*F60 -> 31750
C61: Wortel Grade A | D61: 300 | E61: =VLOOKUP(C61,Master!$B$6:$N$1000,9,FALSE) -> gr | F61: =VLOOKUP(C61,Master!$B$7:$N$1000,10,FALSE) -> 18 | G61: =D61*F61 -> 5400
C62: Bawang Putih | D62: 50 | E62: =VLOOKUP(C62,Master!$B$6:$N$1000,9,FALSE) -> gr | F62: =VLOOKUP(C62,Master!$B$7:$N$1000,10,FALSE) -> 40 | G62: =D62*F62 -> 2000
C63: Bawang Bombay | D63: 100 | E63: =VLOOKUP(C63,Master!$B$6:$N$1000,9,FALSE) -> gr | F63: =VLOOKUP(C63,Master!$B$7:$N$1000,10,FALSE) -> 40 | G63: =D63*F63 -> 4000
C64: Tomato | D64: 1000 | E64: =VLOOKUP(C64,Master!$B$6:$N$1000,9,FALSE) -> gr | F64: =VLOOKUP(C64,Master!$B$7:$N$1000,10,FALSE) -> 16.5 | G64: =D64*F64 -> 16500
C65: Leaf Bay | D65: 2 | E65: =VLOOKUP(C65,Master!$B$6:$N$1000,9,FALSE) -> gr | F65: =VLOOKUP(C65,Master!$B$7:$N$1000,10,FALSE) -> 380 | G65: =D65*F65 -> 760
C66: Leaf Oregano | D66: 2 | E66: =VLOOKUP(C66,Master!$B$6:$N$1000,9,FALSE) -> gr | F66: =VLOOKUP(C66,Master!$B$7:$N$1000,10,FALSE) -> 280 | G66: =D66*F66 -> 560
C67: Garam | D67: 10 | E67: =VLOOKUP(C67,Master!$B$6:$N$1000,9,FALSE) -> gr | F67: =VLOOKUP(C67,Master!$B$7:$N$1000,10,FALSE) -> 15 | G67: =D67*F67 -> 150
C68: Gula hijau | D68: 20 | E68: =VLOOKUP(C68,Master!$B$6:$N$1000,9,FALSE) -> gr | F68: =VLOOKUP(C68,Master!$B$7:$N$1000,10,FALSE) -> 17.5 | G68: =D68*F68 -> 350
C69: Merica | D69: 5 | E69: =VLOOKUP(C69,Master!$B$6:$N$1000,9,FALSE) -> gr | F69: =VLOOKUP(C69,Master!$B$7:$N$1000,10,FALSE) -> 90 | G69: =D69*F69 -> 450
A74: 6 | B74: Ktc Pro White Sauce | D74: =SUM(D75:D78) -> 1252 | E74: =VLOOKUP(B74,Master!B7:N279,9,FALSE) -> gr/por | G74: =SUM(G75:G78) -> 34254.333 | H74: 0.1 | I74: =G74+(G74*H74) -> 37679.767 | J74: 20 | K74: =I74/J74 -> 1883.9883 | L74: =D74/J74 -> 62.6
C75: Cooking Cream | D75: 250 | E75: =VLOOKUP(C75,Master!$B$6:$N$1000,9,FALSE) -> ml | F75: =VLOOKUP(C75,Master!$B$7:$N$1000,10,FALSE) -> 66 | G75: =D75*F75 -> 16500
C76: UHT | D76: 1000 | E76: =VLOOKUP(C76,Master!$B$6:$N$1000,9,FALSE) -> ml | F76: =VLOOKUP(C76,Master!$B$7:$N$1000,10,FALSE) -> 17.094333 | G76: =D76*F76 -> 17094.333
C77: Leaf Oregano | D77: 1 | E77: =VLOOKUP(C77,Master!$B$6:$N$1000,9,FALSE) -> gr | F77: =VLOOKUP(C77,Master!$B$7:$N$1000,10,FALSE) -> 280 | G77: =D77*F77 -> 280
C78: Leaf Bay | D78: 1 | E78: =VLOOKUP(C78,Master!$B$6:$N$1000,9,FALSE) -> gr | F78: =VLOOKUP(C78,Master!$B$7:$N$1000,10,FALSE) -> 380 | G78: =D78*F78 -> 380
A79: 7 | B79: Ktc Pro Dough Pizza | D79: =SUM(D80:D84) -> 1741 | E79: =VLOOKUP(B79,Master!B12:N284,9,FALSE) -> gr | G79: =SUM(G80:G84) -> 19170.117 | H79: 0.1 | I79: =G79+(G79*H79) -> 21087.129 | J79: 10 | K79: =I79/J79 -> 2108.7129 | L79: =D79/J79 -> 174.1
C80: Tepung | D80: 1000 | E80: =VLOOKUP(C80,Master!$B$6:$N$1000,9,FALSE) -> gr | F80: =VLOOKUP(C80,Master!$B$7:$N$1000,10,FALSE) -> 14.25 | G80: =D80*F80 -> 14250
C81: Ragi Fermipan | D81: 1 | E81: =VLOOKUP(C81,Master!$B$6:$N$1000,9,FALSE) -> sachet | F81: =VLOOKUP(C81,Master!$B$7:$N$1000,10,FALSE) -> 2200 | G81: =D81*F81 -> 2200
C82: Gula pasir | D82: 40 | E82: =VLOOKUP(C82,Master!$B$6:$N$1000,9,FALSE) -> gr | F82: =VLOOKUP(C82,Master!$B$7:$N$1000,10,FALSE) -> 17.5 | G82: =D82*F82 -> 700
C83: Air Galon | D83: 600 | E83: =VLOOKUP(C83,Master!$B$6:$N$1000,9,FALSE) -> ml | F83: =VLOOKUP(C83,Master!$B$7:$N$1000,10,FALSE) -> 0.66315789 | G83: =D83*F83 -> 397.89474
C84: Minyak Goreng | D84: 100 | E84: =VLOOKUP(C84,Master!$B$6:$N$1000,9,FALSE) -> ml | F84: =VLOOKUP(C84,Master!$B$7:$N$1000,10,FALSE) -> 16.222222 | G84: =D84*F84 -> 1622.2222
A85: 8 | B85: Ktc Pro Sauce Moza | D85: =SUM(D86:D88) -> 50 | E85: =VLOOKUP(B85,Master!B18:N290,9,FALSE) -> gr | G85: =SUM(G86:G88) -> 4140 | H85: 0.1 | I85: =G85+(G85*H85) -> 4554 | J85: 1 | K85: =I85/J85 -> 4554 | L85: =D85/J85 -> 50
C86: Mozzarella Cheese | D86: 20 | E86: =VLOOKUP(C86,Master!$B$6:$N$1000,9,FALSE) -> gr | F86: =VLOOKUP(C86,Master!$B$7:$N$1000,10,FALSE) -> 108 | G86: =D86*F86 -> 2160
C87: Cooking Cream | D87: 30 | E87: =VLOOKUP(C87,Master!$B$6:$N$1000,9,FALSE) -> ml | F87: =VLOOKUP(C87,Master!$B$7:$N$1000,10,FALSE) -> 66 | G87: =D87*F87 -> 1980
A89: 9 | B89: Ktc Pro Sauce Bumbu Rujak | D89: =SUM(D90:D94) -> 447 | E89: =VLOOKUP(B89,Master!B7:N294,9,FALSE) -> gr/slice | G89: =SUM(G90:G94) -> 20000 | H89: 0.1 | I89: =G89+(G89*H89) -> 22000 | J89: 27 | K89: =I89/J89 -> 814.81481 | L89: =D89/J89 -> 16.555556
C90: Gula Merah / Aren Padat Kiloan | D90: 350 | E90: =VLOOKUP(C90,Master!$B$6:$N$1000,9,FALSE) -> gr | F90: =VLOOKUP(C90,Master!$B$7:$N$1000,10,FALSE) -> 17 | G90: =D90*F90 -> 5950
C91: Cabe Rawit | D91: 50 | E91: =VLOOKUP(C91,Master!$B$6:$N$1000,9,FALSE) -> gr | F91: =VLOOKUP(C91,Master!$B$7:$N$1000,10,FALSE) -> 50 | G91: =D91*F91 -> 2500
C92: Asam Jawa Kemasan | D92: 45 | E92: =VLOOKUP(C92,Master!$B$6:$N$1000,9,FALSE) -> gr | F92: =VLOOKUP(C92,Master!$B$7:$N$1000,10,FALSE) -> 256 | G92: =D92*F92 -> 11520
C93: Garam | D93: 2 | E93: =VLOOKUP(C93,Master!$B$6:$N$1000,9,FALSE) -> gr | F93: =VLOOKUP(C93,Master!$B$7:$N$1000,10,FALSE) -> 15 | G93: =D93*F93 -> 30
A95: 10 | B95: Ktc Pro Egg Wash | D95: =SUM(D96:D97) -> 501 | E95: =VLOOKUP(B95,Master!B13:N300,9,FALSE) -> gr | G95: =SUM(G96:G97) -> 2198.2456 | H95: 0.1 | I95: =G95+(G95*H95) -> 2418.0702 | J95: 450 | K95: =I95/J95 -> 5.3734893 | L95: =D95/J95 -> 1.1133333
C96: Telur Ayam | D96: 1 | E96: =VLOOKUP(C96,Master!$B$6:$N$1000,9,FALSE) -> pcs | F96: =VLOOKUP(C96,Master!$B$7:$N$1000,10,FALSE) -> 1866.6667 | G96: =D96*F96 -> 1866.6667
C97: Air Galon | D97: 500 | E97: =VLOOKUP(C97,Master!$B$6:$N$1000,9,FALSE) -> ml | F97: =VLOOKUP(C97,Master!$B$7:$N$1000,10,FALSE) -> 0.66315789 | G97: =D97*F97 -> 331.57895
A98: 11 | B98: Ktc Pro Wings Marinate | D98: =SUM(D99:D102) -> 3502 | E98: =VLOOKUP(B98,Master!B16:N303,9,FALSE) -> Porsi | G98: =SUM(G99:G103) -> 144324.65 | H98: 0.1 | I98: =G98+(G98*H98) -> 158757.11 | J98: 18 | K98: =I98/J98 -> 8819.8396 | L98: =D98/J98 -> 194.55556
C99: Ayam Sayap | D99: 3000 | E99: =VLOOKUP(C99,Master!$B$6:$N$1000,9,FALSE) -> gr | F99: =VLOOKUP(C99,Master!$B$7:$N$1000,10,FALSE) -> 45 | G99: =D99*F99 -> 135000
C100: Tomato | D100: 500 | E100: =VLOOKUP(C100,Master!$B$6:$N$1000,9,FALSE) -> gr | F100: =VLOOKUP(C100,Master!$B$7:$N$1000,10,FALSE) -> 16.5 | G100: =D100*F100 -> 8250
C101: Ktc Pro Sauce Barbeque | D101: 2 | E101: =VLOOKUP(C101,Master!$B$6:$N$1000,9,FALSE) -> Porsi | F101: =VLOOKUP(C101,Master!$B$7:$N$1000,10,FALSE) -> 537.32381 | G101: =D101*F101 -> 1074.6476
A104: 12 | B104: Ktc Pro Spaghetti Boiled | D104: =SUM(D105:D107) -> 1100 | E104: =VLOOKUP(B104,Master!B22:N309,9,FALSE) -> gr/pcs | G104: =SUM(G105:G107) -> 29122.222 | H104: 0.1 | I104: =G104+(G104*H104) -> 32034.444 | J104: 20 | K104: =I104/J104 -> 1601.7222 | L104: =D104/J104 -> 55
C105: Pasta Spaghetti | D105: 1000 | E105: =VLOOKUP(C105,Master!$B$6:$N$1000,9,FALSE) -> gr | F105: =VLOOKUP(C105,Master!$B$7:$N$1000,10,FALSE) -> 27.5 | G105: =D105*F105 -> 27500
C106: Air Galon | D106: 0 | E106: =VLOOKUP(C106,Master!$B$6:$N$1000,9,FALSE) -> ml | F106: =VLOOKUP(C106,Master!$B$7:$N$1000,10,FALSE) -> 0.66315789 | G106: =D106*F106 -> 0
C107: Minyak Goreng | D107: 100 | E107: =VLOOKUP(C107,Master!$B$6:$N$1000,9,FALSE) -> ml | F107: =VLOOKUP(C107,Master!$B$7:$N$1000,10,FALSE) -> 16.222222 | G107: =D107*F107 -> 1622.2222
A108: 13 | B108: Ktc Pro Rice | D108: =SUM(D109:D110) -> 25000 | E108: =VLOOKUP(B108,Master!B26:N313,9,FALSE) -> Porsi | G108: =SUM(G109:G110) -> 364000 | H108: 0.1 | I108: =G108+(G108*H108) -> 400400 | J108: 366 | K108: =I108/J108 -> 1093.9891 | L108: =D108/J108 -> 68.306011
C109: Beras Rojo Lele | D109: 25000 | E109: =VLOOKUP(C109,Master!$B$6:$N$1000,9,FALSE) -> gr | F109: =VLOOKUP(C109,Master!$B$7:$N$1000,10,FALSE) -> 14.56 | G109: =D109*F109 -> 364000
C110: Air Galon | D110: 0 | E110: =VLOOKUP(C110,Master!$B$6:$N$1000,9,FALSE) -> ml | F110: =VLOOKUP(C110,Master!$B$7:$N$1000,10,FALSE) -> 0.66315789 | G110: =D110*F110 -> 0
A111: 14 | B111: Ktc Pro Katsu Chicken | D111: =SUM(D112:D118) -> 383 | E111: =VLOOKUP(B111,Master!B29:N316,9,FALSE) -> gr | G111: =SUM(G112:G118) -> 17473.5 | H111: 0.1 | I111: =G111+(G111*H111) -> 19220.85 | J111: 4 | K111: =I111/J111 -> 4805.2125 | L111: =D111/J111 -> 95.75
C112: Ayam Boneless Dada | D112: 320 | E112: =VLOOKUP(C112,Master!$B$6:$N$1000,9,FALSE) -> gr | F112: =VLOOKUP(C112,Master!$B$7:$N$1000,10,FALSE) -> 50 | G112: =D112*F112 -> 16000
C113: Tepung Roti Halus | D113: 30 | E113: =VLOOKUP(C113,Master!$B$6:$N$1000,9,FALSE) -> gr | F113: =VLOOKUP(C113,Master!$B$7:$N$1000,10,FALSE) -> 21.25 | G113: =D113*F113 -> 637.5
...

Sheet Menu Bar
A1: Resep Menu Bar
A2: The Soko Coffee Tea Chocolate
A5: Kode | B5: Menu | C5: Bahan | D5: Recipe QTY | E5: Satuan | F5: Hrg. Satuan | G5: HPP | H5: OH. Cost | I5: HPP Net | K5: Checker
A6: =VLOOKUP(B6,Master!$V$7:$W$150,2,FALSE) -> M0001 | B6: Cappucino Hot | G6: =SUM(G7:G10) -> 6280.5263 | H6: 0.15 | I6: =G6+(G6*H6) -> 7222.6053 | J6: TRUE | K6: TRUE
C7: Beans | D7: 18 | E7: =VLOOKUP(C7,Master!$B$6:$N$1000,9,FALSE) -> gr | F7: =VLOOKUP(C7,Master!$B$6:$N$1000,10,FALSE) -> 195 | G7: =D7*F7 -> 3510 | J7: split atau tidak?
C8: Air Galon | D8: 0 | E8: =VLOOKUP(C8,Master!$B$6:$N$1000,9,FALSE) -> ml | F8: =VLOOKUP(C8,Master!$B$6:$N$1000,10,FALSE) -> 0.66315789 | G8: =D8*F8 -> 0 | J8: Split
C9: Freshmilk | D9: 120 | E9: =VLOOKUP(C9,Master!$B$6:$N$1000,9,FALSE) -> ml | F9: =VLOOKUP(C9,Master!$B$6:$N$1000,10,FALSE) -> 18.421053 | G9: =D9*F9 -> 2210.5263
C10: Packing Cup Hot 8 Oz | D10: 1 | E10: =VLOOKUP(C10,Master!$B$6:$N$1000,9,FALSE) -> pcs | F10: =VLOOKUP(C10,Master!$B$6:$N$1000,10,FALSE) -> 560 | G10: =D10*F10 -> 560 | J10: cup ganti wrna
A11: =VLOOKUP(B11,Master!$V$7:$W$150,2,FALSE) -> M0002 | B11: Cappucino Ice | G11: =SUM(G12:G15) -> 5857.054 | H11: 0.15 | I11: =G11+(G11*H11) -> 6735.6121 | J11: TRUE | K11: TRUE
C12: Beans | D12: 18 | E12: =VLOOKUP(C12,Master!$B$6:$N$1000,9,FALSE) -> gr | F12: =VLOOKUP(C12,Master!$B$6:$N$1000,10,FALSE) -> 195 | G12: =D12*F12 -> 3510 | K12: CUT
C13: Bar Pro Simple Syrup | D13: 30 | E13: =VLOOKUP(C13,Master!$B$6:$N$1000,9,FALSE) -> ml | F13: =VLOOKUP(C13,Master!$B$6:$N$1000,10,FALSE) -> 15.983579 | G13: =D13*F13 -> 479.50737
C14: UHT | D14: 80 | E14: =VLOOKUP(C14,Master!$B$6:$N$1000,9,FALSE) -> ml | F14: =VLOOKUP(C14,Master!$B$6:$N$1000,10,FALSE) -> 17.094333 | G14: =D14*F14 -> 1367.5467
C15: Cup Oval 12 Oz Custom Soko | D15: 1 | E15: =VLOOKUP(C15,Master!$B$6:$N$1000,9,FALSE) -> pcs | F15: =VLOOKUP(C15,Master!$B$6:$N$1000,10,FALSE) -> 500 | G15: =D15*F15 -> 500 | J15: cup plastik ganti baru
A16: =VLOOKUP(B16,Master!$V$7:$W$150,2,FALSE) -> M0003 | B16: Iced Cafe Latte | G16: =SUM(G17:G20) -> 5572.3637 | H16: 0.15 | I16: =G16+(G16*H16) -> 6408.2182 | J16: TRUE | K16: TRUE
C17: Beans | D17: 18 | E17: =VLOOKUP(C17,Master!$B$6:$N$1000,9,FALSE) -> gr | F17: =VLOOKUP(C17,Master!$B$6:$N$1000,10,FALSE) -> 195 | G17: =D17*F17 -> 3510
C18: Air Galon | D18: 36 | E18: =VLOOKUP(C18,Master!$B$6:$N$1000,9,FALSE) -> ml | F18: =VLOOKUP(C18,Master!$B$6:$N$1000,10,FALSE) -> 0.66315789 | G18: =D18*F18 -> 23.873684
C19: UHT | D19: 90 | E19: =VLOOKUP(C19,Master!$B$6:$N$1000,9,FALSE) -> ml | F19: =VLOOKUP(C19,Master!$B$6:$N$1000,10,FALSE) -> 17.094333 | G19: =D19*F19 -> 1538.49
C20: Cup Oval 12 Oz Custom Soko | D20: 1 | E20: =VLOOKUP(C20,Master!$B$6:$N$1000,9,FALSE) -> pcs | F20: =VLOOKUP(C20,Master!$B$6:$N$1000,10,FALSE) -> 500 | G20: =D20*F20 -> 500
A21: =VLOOKUP(B21,Master!$V$7:$W$150,2,FALSE) -> M0004 | B21: Hot Cafe Latte | G21: =SUM(G22:G25) -> 6857.0316 | H21: 0.15 | I21: =G21+(G21*H21) -> 7885.5863 | J21: TRUE | K21: TRUE
C22: Beans | D22: 18 | E22: =VLOOKUP(C22,Master!$B$6:$N$1000,9,FALSE) -> gr | F22: =VLOOKUP(C22,Master!$B$6:$N$1000,10,FALSE) -> 195 | G22: =D22*F22 -> 3510 | J22: split atau tidak?
C23: Air Galon | D23: 36 | E23: =VLOOKUP(C23,Master!$B$6:$N$1000,9,FALSE) -> ml | F23: =VLOOKUP(C23,Master!$B$6:$N$1000,10,FALSE) -> 0.66315789 | G23: =D23*F23 -> 23.873684 | J23: Tidak di Split
C24: Freshmilk | D24: 150 | E24: =VLOOKUP(C24,Master!$B$6:$N$1000,9,FALSE) -> ml | F24: =VLOOKUP(C24,Master!$B$6:$N$1000,10,FALSE) -> 18.421053 | G24: =D24*F24 -> 2763.1579
C25: Packing Cup Hot 8 Oz | D25: 1 | E25: =VLOOKUP(C25,Master!$B$6:$N$1000,9,FALSE) -> pcs | F25: =VLOOKUP(C25,Master!$B$6:$N$1000,10,FALSE) -> 560 | G25: =D25*F25 -> 560
A26: =VLOOKUP(B26,Master!$V$7:$W$150,2,FALSE) -> M0005 | B26: Hot Americano | G26: =SUM(G27:G29) -> 4136.3158 | H26: 0.15 | I26: =G26+(G26*H26) -> 4756.7632 | J26: TRUE | K26: TRUE
C27: Beans | D27: 18 | E27: =VLOOKUP(C27,Master!$B$6:$N$1000,9,FALSE) -> gr | F27: =VLOOKUP(C27,Master!$B$6:$N$1000,10,FALSE) -> 195 | G27: =D27*F27 -> 3510
C28: Air Galon | D28: 100 | E28: =VLOOKUP(C28,Master!$B$6:$N$1000,9,FALSE) -> ml | F28: =VLOOKUP(C28,Master!$B$6:$N$1000,10,FALSE) -> 0.66315789 | G28: =D28*F28 -> 66.315789
C29: Packing Cup Hot 8 Oz | D29: 1 | E29: =VLOOKUP(C29,Master!$B$6:$N$1000,9,FALSE) -> pcs | F29: =VLOOKUP(C29,Master!$B$6:$N$1000,10,FALSE) -> 560 | G29: =D29*F29 -> 560
A30: =VLOOKUP(B30,Master!$V$7:$W$150,2,FALSE) -> M0006 | B30: Iced Americano | G30: =SUM(G31:G33) -> 4076.3158 | H30: 0.1 | I30: =G30+(G30*H30) -> 4483.9474 | J30: TRUE | K30: TRUE
C31: Beans | D31: 18 | E31: =VLOOKUP(C31,Master!$B$6:$N$1000,9,FALSE) -> gr | F31: =VLOOKUP(C31,Master!$B$6:$N$1000,10,FALSE) -> 195 | G31: =D31*F31 -> 3510
C32: Air Galon | D32: 100 | E32: =VLOOKUP(C32,Master!$B$6:$N$1000,9,FALSE) -> ml | F32: =VLOOKUP(C32,Master!$B$6:$N$1000,10,FALSE) -> 0.66315789 | G32: =D32*F32 -> 66.315789
C33: Cup Oval 12 Oz Custom Soko | D33: 1 | E33: =VLOOKUP(C33,Master!$B$6:$N$1000,9,FALSE) -> pcs | F33: =VLOOKUP(C33,Master!$B$6:$N$1000,10,FALSE) -> 500 | G33: =D33*F33 -> 500
A34: =VLOOKUP(B34,Master!$V$7:$W$150,2,FALSE) -> M0007 | B34: Hot Moccacino | G34: =SUM(G35:G39) -> 6570.1895 | H34: 0.15 | I34: =G34+(G34*H34) -> 7555.7179 | J34: TRUE | K34: TRUE
C35: Beans | D35: 18 | E35: =VLOOKUP(C35,Master!$B$6:$N$1000,9,FALSE) -> gr | F35: =VLOOKUP(C35,Master!$B$6:$N$1000,10,FALSE) -> 195 | G35: =D35*F35 -> 3510
C36: Air Galon | D36: 36 | E36: =VLOOKUP(C36,Master!$B$6:$N$1000,9,FALSE) -> ml | F36: =VLOOKUP(C36,Master!$B$6:$N$1000,10,FALSE) -> 0.66315789 | G36: =D36*F36 -> 23.873684
C37: Freshmilk | D37: 15 | E37: =VLOOKUP(C37,Master!$B$6:$N$1000,9,FALSE) -> ml | F37: =VLOOKUP(C37,Master!$B$6:$N$1000,10,FALSE) -> 18.421053 | G37: =D37*F37 -> 276.31579
C38: Powder Chocolate Origin Java Srawana | D38: 10 | E38: =VLOOKUP(C38,Master!$B$6:$N$1000,9,FALSE) -> gr | F38: =VLOOKUP(C38,Master!$B$6:$N$1000,10,FALSE) -> 220 | G38: =D38*F38 -> 2200
C39: Packing Cup Hot 8 Oz | D39: 1 | E39: =VLOOKUP(C39,Master!$B$6:$N$1000,9,FALSE) -> pcs | F39: =VLOOKUP(C39,Master!$B$6:$N$1000,10,FALSE) -> 560 | G39: =D39*F39 -> 560
A40: =VLOOKUP(B40,Master!$V$7:$W$150,2,FALSE) -> M0008 | B40: Iced Moccacino | G40: =SUM(G41:G45) -> 9385.1937 | H40: 0.15 | I40: =G40+(G40*H40) -> 10792.973 | J40: TRUE | K40: TRUE
C41: Beans | D41: 18 | E41: =VLOOKUP(C41,Master!$B$6:$N$1000,9,FALSE) -> gr | F41: =VLOOKUP(C41,Master!$B$6:$N$1000,10,FALSE) -> 195 | G41: =D41*F41 -> 3510
C42: Air Galon | D42: 36 | E42: =VLOOKUP(C42,Master!$B$6:$N$1000,9,FALSE) -> ml | F42: =VLOOKUP(C42,Master!$B$6:$N$1000,10,FALSE) -> 0.66315789 | G42: =D42*F42 -> 23.873684
C43: UHT | D43: 120 | E43: =VLOOKUP(C43,Master!$B$6:$N$1000,9,FALSE) -> ml | F43: =VLOOKUP(C43,Master!$B$6:$N$1000,10,FALSE) -> 17.094333 | G43: =D43*F43 -> 2051.32
C44: Powder Chocolate Origin Java Srawana | D44: 15 | E44: =VLOOKUP(C44,Master!$B$6:$N$1000,9,FALSE) -> gr | F44: =VLOOKUP(C44,Master!$B$6:$N$1000,10,FALSE) -> 220 | G44: =D44*F44 -> 3300
C45: Cup Oval 12 Oz Custom Soko | D45: 1 | E45: =VLOOKUP(C45,Master!$B$6:$N$1000,9,FALSE) -> pcs | F45: =VLOOKUP(C45,Master!$B$6:$N$1000,10,FALSE) -> 500 | G45: =D45*F45 -> 500
A46: =VLOOKUP(B46,Master!$V$7:$W$150,2,FALSE) -> M0009 | B46: Hazelnut Latte Hot | G46: =SUM(G47:G51) -> 8757.0316 | H46: 0.15 | I46: =G46+(G46*H46) -> 10070.586 | J46: TRUE | K46: TRUE
C47: Beans | D47: 18 | E47: =VLOOKUP(C47,Master!$B$6:$N$1000,9,FALSE) -> gr | F47: =VLOOKUP(C47,Master!$B$6:$N$1000,10,FALSE) -> 195 | G47: =D47*F47 -> 3510
C48: Air Galon | D48: 36 | E48: =VLOOKUP(C48,Master!$B$6:$N$1000,9,FALSE) -> ml | F48: =VLOOKUP(C48,Master!$B$6:$N$1000,10,FALSE) -> 0.66315789 | G48: =D48*F48 -> 23.873684
C49: Freshmilk | D49: 150 | E49: =VLOOKUP(C49,Master!$B$6:$N$1000,9,FALSE) -> ml | F49: =VLOOKUP(C49,Master!$B$6:$N$1000,10,FALSE) -> 18.421053 | G49: =D49*F49 -> 2763.1579
C50: Voya Hazelnut | D50: 15 | E50: =VLOOKUP(C50,Master!$B$6:$N$1000,9,FALSE) -> ml | F50: =VLOOKUP(C50,Master!$B$6:$N$1000,10,FALSE) -> 126.66667 | G50: =D50*F50 -> 1900
C51: Packing Cup Hot 8 Oz | D51: 1 | E51: =VLOOKUP(C51,Master!$B$6:$N$1000,9,FALSE) -> pcs | F51: =VLOOKUP(C51,Master!$B$6:$N$1000,10,FALSE) -> 560 | G51: =D51*F51 -> 560
A52: =VLOOKUP(B52,Master!$V$7:$W$150,2,FALSE) -> M0010 | B52: Hazelnut Latte Ice | G52: =SUM(G53:G57) -> 8618.527 | H52: 0.15 | I52: =G52+(G52*H52) -> 9911.3061 | J52: TRUE | K52: TRUE
C53: Beans | D53: 18 | E53: =VLOOKUP(C53,Master!$B$6:$N$1000,9,FALSE) -> gr | F53: =VLOOKUP(C53,Master!$B$6:$N$1000,10,FALSE) -> 195 | G53: =D53*F53 -> 3510
C54: Air Galon | D54: 36 | E54: =VLOOKUP(C54,Master!$B$6:$N$1000,9,FALSE) -> ml | F54: =VLOOKUP(C54,Master!$B$6:$N$1000,10,FALSE) -> 0.66315789 | G54: =D54*F54 -> 23.873684
C55: UHT | D55: 120 | E55: =VLOOKUP(C55,Master!$B$6:$N$1000,9,FALSE) -> ml | F55: =VLOOKUP(C55,Master!$B$6:$N$1000,10,FALSE) -> 17.094333 | G55: =D55*F55 -> 2051.32
C56: Voya Hazelnut | D56: 20 | E56: =VLOOKUP(C56,Master!$B$6:$N$1000,9,FALSE) -> ml | F56: =VLOOKUP(C56,Master!$B$6:$N$1000,10,FALSE) -> 126.66667 | G56: =D56*F56 -> 2533.3333
C57: Cup Oval 12 Oz Custom Soko | D57: 1 | E57: =VLOOKUP(C57,Master!$B$6:$N$1000,9,FALSE) -> pcs | F57: =VLOOKUP(C57,Master!$B$6:$N$1000,10,FALSE) -> 500 | G57: =D57*F57 -> 500
A58: =VLOOKUP(B58,Master!$V$7:$W$150,2,FALSE) -> M0012 | B58: Iced Vanilla Latte | G58: =SUM(G59:G63) -> 8618.527 | H58: 0.15 | I58: =G58+(G58*H58) -> 9911.3061 | J58: TRUE | K58: TRUE
C59: Beans | D59: 18 | E59: =VLOOKUP(C59,Master!$B$6:$N$1000,9,FALSE) -> gr | F59: =VLOOKUP(C59,Master!$B$6:$N$1000,10,FALSE) -> 195 | G59: =D59*F59 -> 3510
C60: Air Galon | D60: 36 | E60: =VLOOKUP(C60,Master!$B$6:$N$1000,9,FALSE) -> ml | F60: =VLOOKUP(C60,Master!$B$6:$N$1000,10,FALSE) -> 0.66315789 | G60: =D60*F60 -> 23.873684
C61: UHT | D61: 120 | E61: =VLOOKUP(C61,Master!$B$6:$N$1000,9,FALSE) -> ml | F61: =VLOOKUP(C61,Master!$B$6:$N$1000,10,FALSE) -> 17.094333 | G61: =D61*F61 -> 2051.32
C62: Voya Vanilla | D62: 20 | E62: =VLOOKUP(C62,Master!$B$6:$N$1000,9,FALSE) -> ml | F62: =VLOOKUP(C62,Master!$B$6:$N$1000,10,FALSE) -> 126.66667 | G62: =D62*F62 -> 2533.3333
C63: Cup Oval 12 Oz Custom Soko | D63: 1 | E63: =VLOOKUP(C63,Master!$B$6:$N$1000,9,FALSE) -> pcs | F63: =VLOOKUP(C63,Master!$B$6:$N$1000,10,FALSE) -> 500 | G63: =D63*F63 -> 500
A64: =VLOOKUP(B64,Master!$V$7:$W$150,2,FALSE) -> M0011 | B64: Hot Vanilla Latte | G64: =SUM(G65:G69) -> 8757.0316 | H64: 0.15 | I64: =G64+(G64*H64) -> 10070.586 | J64: TRUE | K64: TRUE
C65: Beans | D65: 18 | E65: =VLOOKUP(C65,Master!$B$6:$N$1000,9,FALSE) -> gr | F65: =VLOOKUP(C65,Master!$B$6:$N$1000,10,FALSE) -> 195 | G65: =D65*F65 -> 3510
C66: Air Galon | D66: 36 | E66: =VLOOKUP(C66,Master!$B$6:$N$1000,9,FALSE) -> ml | F66: =VLOOKUP(C66,Master!$B$6:$N$1000,10,FALSE) -> 0.66315789 | G66: =D66*F66 -> 23.873684
C67: Freshmilk | D67: 150 | E67: =VLOOKUP(C67,Master!$B$6:$N$1000,9,FALSE) -> ml | F67: =VLOOKUP(C67,Master!$B$6:$N$1000,10,FALSE) -> 18.421053 | G67: =D67*F67 -> 2763.1579
C68: Voya Vanilla | D68: 15 | E68: =VLOOKUP(C68,Master!$B$6:$N$1000,9,FALSE) -> ml | F68: =VLOOKUP(C68,Master!$B$6:$N$1000,10,FALSE) -> 126.66667 | G68: =D68*F68 -> 1900
C69: Packing Cup Hot 8 Oz | D69: 1 | E69: =VLOOKUP(C69,Master!$B$6:$N$243,9,FALSE) -> pcs | F69: =VLOOKUP(C69,Master!$B$6:$N$243,10,FALSE) -> 560 | G69: =D69*F69 -> 560
A70: =VLOOKUP(B70,Master!$V$7:$W$150,2,FALSE) -> M0013 | B70: Affogato | G70: =SUM(G71:G73) -> 5676.8737 | H70: 0.15 | I70: =G70+(G70*H70) -> 6528.4047 | J70: TRUE | K70: TRUE
C71: Beans | D71: 18 | E71: =VLOOKUP(C71,Master!$B$6:$N$1000,9,FALSE) -> gr | F71: =VLOOKUP(C71,Master!$B$6:$N$1000,10,FALSE) -> 195 | G71: =D71*F71 -> 3510
C72: Air Galon | D72: 36 | E72: =VLOOKUP(C72,Master!$B$6:$N$1000,9,FALSE) -> ml | F72: =VLOOKUP(C72,Master!$B$6:$N$1000,10,FALSE) -> 0.66315789 | G72: =D72*F72 -> 23.873684
C73: Ice Cream Vanilla | D73: 100 | E73: =VLOOKUP(C73,Master!$B$6:$N$1000,9,FALSE) -> gr | F73: =VLOOKUP(C73,Master!$B$6:$N$1000,10,FALSE) -> 21.43 | G73: =D73*F73 -> 2143
A74: =VLOOKUP(B74,Master!$V$7:$W$150,2,FALSE) -> M0015 | B74: Es Kopi Soko | G74: =SUM(G75:G80) -> 7225.4384 | H74: 0.15 | I74: =G74+(G74*H74) -> 8309.2542 | J74: TRUE | K74: TRUE
C75: Beans | D75: 18 | E75: =VLOOKUP(C75,Master!$B$6:$N$1000,9,FALSE) -> gr | F75: =VLOOKUP(C75,Master!$B$6:$N$1000,10,FALSE) -> 195 | G75: =D75*F75 -> 3510
C76: Air Galon | D76: 0 | E76: =VLOOKUP(C76,Master!$B$6:$N$1000,9,FALSE) -> ml | F76: =VLOOKUP(C76,Master!$B$6:$N$1000,10,FALSE) -> 0.66315789 | G76: =D76*F76 -> 0
C77: Bar Pro Aren Liquid | D77: 1 | E77: =VLOOKUP(C77,Master!$B$6:$N$1000,9,FALSE) -> porsi | F77: =VLOOKUP(C77,Master!$B$6:$N$1000,10,FALSE) -> 1164.1184 | G77: =D77*F77 -> 1164.1184
C78: Whip Cream | D78: 0 | E78: =VLOOKUP(C78,Master!$B$6:$N$1000,9,FALSE) -> ml | F78: =VLOOKUP(C78,Master!$B$6:$N$1000,10,FALSE) -> 40 | G78: =D78*F78 -> 0
C79: UHT | D79: 120 | E79: =VLOOKUP(C79,Master!$B$6:$N$1000,9,FALSE) -> ml | F79: =VLOOKUP(C79,Master!$B$6:$N$1000,10,FALSE) -> 17.094333 | G79: =D79*F79 -> 2051.32
C80: Cup Oval 12 Oz Custom Soko | D80: 1 | E80: =VLOOKUP(C80,Master!$B$6:$N$1000,9,FALSE) -> pcs | F80: =VLOOKUP(C80,Master!$B$6:$N$1000,10,FALSE) -> 500 | G80: =D80*F80 -> 500
A81: =VLOOKUP(B81,Master!$V$7:$W$150,2,FALSE) -> M0017 | B81: Hot Chocolate | G81: =SUM(G82:G85) -> 3923.6842 | H81: 0.15 | I81: =G81+(G81*H81) -> 4512.2368 | J81: TRUE | K81: TRUE
C82: Dark Chocolate | D82: 20 | E82: =VLOOKUP(C82,Master!$B$6:$N$1000,9,FALSE) -> gr | F82: =VLOOKUP(C82,Master!$B$6:$N$1000,10,FALSE) -> 56 | G82: =D82*F82 -> 1120
C83: Air Galon | D83: 50 | E83: =VLOOKUP(C83,Master!$B$6:$N$1000,9,FALSE) -> ml | F83: =VLOOKUP(C83,Master!$B$6:$N$1000,10,FALSE) -> 0.66315789 | G83: =D83*F83 -> 33.157895
C84: Freshmilk | D84: 120 | E84: =VLOOKUP(C84,Master!$B$6:$N$1000,9,FALSE) -> ml | F84: =VLOOKUP(C84,Master!$B$6:$N$1000,10,FALSE) -> 18.421053 | G84: =D84*F84 -> 2210.5263
C85: Packing Cup Hot 8 Oz | D85: 1 | E85: =VLOOKUP(C85,Master!$B$6:$N$1000,9,FALSE) -> pcs | F85: =VLOOKUP(C85,Master!$B$6:$N$1000,10,FALSE) -> 560 | G85: =D85*F85 -> 560
A88: =VLOOKUP(B88,Master!$V$7:$W$150,2,FALSE) -> M0018 | B88: Iced Chocolate | G88: =SUM(G89:G94) -> 4730.1379 | H88: 0.15 | I88: =G88+(G88*H88) -> 5439.6586 | J88: TRUE | K88: TRUE
C89: Dark Chocolate | D89: 20 | E89: =VLOOKUP(C89,Master!$B$6:$N$1000,9,FALSE) -> gr | F89: =VLOOKUP(C89,Master!$B$6:$N$1000,10,FALSE) -> 56 | G89: =D89*F89 -> 1120
C90: Air Galon | D90: 50 | E90: =VLOOKUP(C90,Master!$B$6:$N$243,9,FALSE) -> ml | F90: =VLOOKUP(C90,Master!$B$6:$N$243,10,FALSE) -> 0.66315789 | G90: =D90*F90 -> 33.157895
C91: UHT | D91: 180 | E91: =VLOOKUP(C91,Master!$B$6:$N$243,9,FALSE) -> ml | F91: =VLOOKUP(C91,Master!$B$6:$N$243,10,FALSE) -> 17.094333 | G91: =D91*F91 -> 3076.98
C92: Garnish Kering Mix Fruit | D92: 0 | E92: =VLOOKUP(C92,Master!$B$6:$N$1000,9,FALSE) -> gr | F92: =VLOOKUP(C92,Master!$B$6:$N$1000,10,FALSE) -> 200 | G92: =D92*F92 -> 0
C93: Tusukan Garnish | D93: 0 | E93: =VLOOKUP(C93,Master!$B$6:$N$1000,9,FALSE) -> pcs | F93: =VLOOKUP(C93,Master!$B$6:$N$1000,10,FALSE) -> 320 | G93: =D93*F93 -> 0
C94: Cup Oval 12 Oz Custom Soko | D94: 1 | E94: =VLOOKUP(C94,Master!$B$6:$N$1000,9,FALSE) -> pcs | F94: =VLOOKUP(C94,Master!$B$6:$N$1000,10,FALSE) -> 500 | G94: =D94*F94 -> 500
A95: =VLOOKUP(B95,Master!$V$7:$W$150,2,FALSE) -> M0019 | B95: Choconutt Ice | G95: =SUM(G96:G99) -> 9098.0326 | H95: 0.15 | I95: =G95+(G95*H95) -> 10462.738 | J95: TRUE | K95: TRUE
C96: Arghani Chocolate Mixing | D96: 20 | E96: =VLOOKUP(C96,Master!$B$6:$N$1000,9,FALSE) -> gr | F96: =VLOOKUP(C96,Master!$B$6:$N$1000,10,FALSE) -> 130 | G96: =D96*F96 -> 2600 | K96: CUT
C97: UHT | D97: 180 | E97: =VLOOKUP(C97,Master!$B$6:$N$1000,9,FALSE) -> ml | F97: =VLOOKUP(C97,Master!$B$6:$N$1000,10,FALSE) -> 17.094333 | G97: =D97*F97 -> 3076.98
C98: Drip Hazelnut | D98: 20 | E98: =VLOOKUP(C98,Master!$B$6:$N$1000,9,FALSE) -> ml | F98: =VLOOKUP(C98,Master!$B$6:$N$1000,10,FALSE) -> 146.05263 | G98: =D98*F98 -> 2921.0526 | J98: ganti syrup
C99: Cup Oval 12 Oz Custom Soko | D99: 1 | E99: =VLOOKUP(C99,Master!$B$6:$N$1000,9,FALSE) -> pcs | F99: =VLOOKUP(C99,Master!$B$6:$N$1000,10,FALSE) -> 500 | G99: =D99*F99 -> 500
A100: =VLOOKUP(B100,Master!$V$7:$W$150,2,FALSE) -> M0020 | B100: Naga Black Tea Hot | G100: =SUM(G101:G103) -> 738.73553 | H100: 0.15 | I100: =G100+(G100*H100) -> 849.54586 | J100: TRUE | K100: TRUE
C101: Bar Pro Black Tea | D101: 150 | E101: =VLOOKUP(C101,Master!$B$6:$N$1000,9,FALSE) -> ml | F101: =VLOOKUP(C101,Master!$B$6:$N$1000,10,FALSE) -> 1.1915702 | G101: =D101*F101 -> 178.73553
C102: Air Galon | D102: 0 | E102: =VLOOKUP(C102,Master!$B$6:$N$1000,9,FALSE) -> ml | F102: =VLOOKUP(C102,Master!$B$6:$N$1000,10,FALSE) -> 0.66315789 | G102: =D102*F102 -> 0
C103: Packing Cup Hot 8 Oz | D103: 1 | E103: =VLOOKUP(C103,Master!$B$6:$N$1000,9,FALSE) -> pcs | F103: =VLOOKUP(C103,Master!$B$6:$N$1000,10,FALSE) -> 560 | G103: =D103*F103 -> 560
A104: =VLOOKUP(B104,Master!$V$7:$W$150,2,FALSE) -> M0021 | B104: Naga Black Tea Ice | G104: =SUM(G105:G107) -> 2200.6675 | H104: 0.1 | I104: =G104+(G104*H104) -> 2420.7343 | J104: TRUE | K104: TRUE
...

Sheet Production Bar
A1: Resep Production Bar
A2: The Soko Coffee Tea Chocolate
B4: 1 | C4: 2 | D4: 3 | E4: 4 | F4: 5 | G4: 6 | H4: 7 | I4: 8 | J4: 9 | K4: 10 | L4: 11
A5: No | B5: Menu | C5: Bahan | D5: Recipe QTY | E5: Satuan | F5: Hrg. Satuan | G5: HPP | H5: OH. Cost | I5: HPP Net | J5: Portion | K5: Harga/Porsi | L5: Yield Portion
A6: 1 | B6: Bar Pro Chrysantemum | D6: =SUM(D7:D8) -> 253 | E6: =VLOOKUP(B6,Master!B6:N243,9,FALSE) -> gr/pcs | G6: =SUM(G7:G8) -> 5685.7895 | H6: 0.1 | I6: =G6+(G6*H6) -> 6254.3684 | J6: 200 | K6: =I6/J6 -> 31.271842 | L6: =D6/J6 -> 1.265
C7: Chrysantemum | D7: 3 | E7: =VLOOKUP(C7,Master!$B$6:$N$243,9,FALSE) -> gr | F7: =VLOOKUP(C7,Master!B6:N243,10,FALSE) -> 1840 | G7: =D7*F7 -> 5520
C8: Air Galon | D8: 250 | E8: =VLOOKUP(C8,Master!$B$6:$N$243,9,FALSE) -> ml | F8: =VLOOKUP(C8,Master!B7:N244,10,FALSE) -> 0.66315789 | G8: =D8*F8 -> 165.78947
A9: 2 | B9: Bar Pro Rosella | D9: =SUM(D10:D11) -> 255 | E9: =VLOOKUP(B9,Master!B9:N246,9,FALSE) -> gr/slice | G9: =SUM(G10:G11) -> 3165.7895 | H9: 0.1 | I9: =G9+(G9*H9) -> 3482.3684 | J9: 200 | K9: =I9/J9 -> 17.411842 | L9: =D9/J9 -> 1.275
C10: Rosella Tea | D10: 5 | E10: =VLOOKUP(C10,Master!$B$6:$N$243,9,FALSE) -> gr | F10: =VLOOKUP(C10,Master!B9:N246,10,FALSE) -> 600 | G10: =D10*F10 -> 3000
C11: Air Galon | D11: 250 | E11: =VLOOKUP(C11,Master!$B$6:$N$243,9,FALSE) -> ml | F11: =VLOOKUP(C11,Master!B10:N247,10,FALSE) -> 0.66315789 | G11: =D11*F11 -> 165.78947
A12: 3 | B12: Bar Pro Black Tea | D12: =SUM(D13:D14) -> 1022 | E12: =VLOOKUP(B12,Master!B12:N249,9,FALSE) -> ml | G12: =SUM(G13:G14) -> 2166.4912 | H12: 0.1 | I12: =G12+(G12*H12) -> 2383.1404 | J12: 2000 | K12: =I12/J12 -> 1.1915702 | L12: =D12/J12 -> 0.511
C13: Teh Naga | D13: 22 | E13: =VLOOKUP(C13,Master!$B$6:$N$243,9,FALSE) -> gr | F13: =VLOOKUP(C13,Master!B12:N249,10,FALSE) -> 68.333333 | G13: =D13*F13 -> 1503.3333
C14: Air Galon | D14: 1000 | E14: =VLOOKUP(C14,Master!$B$6:$N$243,9,FALSE) -> ml | F14: =VLOOKUP(C14,Master!B13:N250,10,FALSE) -> 0.66315789 | G14: =D14*F14 -> 663.15789
A15: 4 | B15: Bar Pro Cengkeh | D15: =SUM(D16:D17) -> 230 | E15: =VLOOKUP(B15,Master!B15:N252,9,FALSE) -> gr | G15: =SUM(G16:G17) -> 4339.2632 | H15: 0.1 | I15: =G15+(G15*H15) -> 4773.1895 | J15: 200 | K15: =I15/J15 -> 23.865947 | L15: =D15/J15 -> 1.15
C16: Cengkeh | D16: 20 | E16: =VLOOKUP(C16,Master!$B$6:$N$243,9,FALSE) -> gr | F16: =VLOOKUP(C16,Master!B15:N252,10,FALSE) -> 210 | G16: =D16*F16 -> 4200
C17: Air Galon | D17: 210 | E17: =VLOOKUP(C17,Master!$B$6:$N$243,9,FALSE) -> ml | F17: =VLOOKUP(C17,Master!B16:N253,10,FALSE) -> 0.66315789 | G17: =D17*F17 -> 139.26316
A18: 5 | B18: Bar Pro Mix SKM | D18: =SUM(D19:D20) -> 1220 | E18: =VLOOKUP(B18,Master!B18:N255,9,FALSE) -> ml | G18: =SUM(G19:G20) -> 45473.684 | H18: 0.1 | I18: =G18+(G18*H18) -> 50021.053 | J18: 1220 | K18: =I18/J18 -> 41.000863 | L18: =D18/J18 -> 1
C19: SKM | D19: 740 | E19: =VLOOKUP(C19,Master!$B$6:$N$243,9,FALSE) -> gr | F19: =VLOOKUP(C19,Master!B18:N255,10,FALSE) -> 32.432432 | G19: =D19*F19 -> 24000
C20: Susu Evaporasi | D20: 480 | E20: =VLOOKUP(C20,Master!$B$6:$N$243,9,FALSE) -> ml | F20: =VLOOKUP(C20,Master!B19:N256,10,FALSE) -> 44.736842 | G20: =D20*F20 -> 21473.684
A21: 6 | B21: Bar Pro Lemon Juice | D21: =SUM(D22:D23) -> 660 | E21: =VLOOKUP(B21,Master!B21:N258,9,FALSE) -> ml | G21: =SUM(G22:G23) -> 35218.842 | H21: 0.1 | I21: =G21+(G21*H21) -> 38740.726 | J21: 990 | K21: =I21/J21 -> 39.132047 | L21: =D21/J21 -> 0.66666667
C22: Lemon | D22: 330 | E22: =VLOOKUP(C22,Master!$B$6:$N$243,9,FALSE) -> ml | F22: =VLOOKUP(C22,Master!B21:N258,10,FALSE) -> 106.06061 | G22: =D22*F22 -> 35000
C23: Air Galon | D23: 330 | E23: =VLOOKUP(C23,Master!$B$6:$N$243,9,FALSE) -> ml | F23: =VLOOKUP(C23,Master!B22:N259,10,FALSE) -> 0.66315789 | G23: =D23*F23 -> 218.84211
A24: 7 | B24: Bar Pro Orange Juice | D24: =SUM(D25:D26) -> 660 | E24: =VLOOKUP(B24,Master!B24:N261,9,FALSE) -> ml | G24: =SUM(G25:G26) -> 35218.842 | H24: 0.1 | I24: =G24+(G24*H24) -> 38740.726 | J24: 990 | K24: =I24/J24 -> 39.132047 | L24: =D24/J24 -> 0.66666667
C25: Orange | D25: 330 | E25: =VLOOKUP(C25,Master!$B$6:$N$243,9,FALSE) -> ml | F25: =VLOOKUP(C25,Master!B24:N261,10,FALSE) -> 106.06061 | G25: =D25*F25 -> 35000
C26: Air Galon | D26: 330 | E26: =VLOOKUP(C26,Master!$B$6:$N$243,9,FALSE) -> ml | F26: =VLOOKUP(C26,Master!B25:N262,10,FALSE) -> 0.66315789 | G26: =D26*F26 -> 218.84211
A27: 8 | B27: Bar Pro Simple Syrup | D27: =SUM(D28:D29) -> 2000 | E27: =VLOOKUP(B27,Master!B27:N264,9,FALSE) -> ml | G27: =SUM(G28:G29) -> 18163.158 | H27: 0.1 | I27: =G27+(G27*H27) -> 19979.474 | J27: 1250 | K27: =I27/J27 -> 15.983579 | L27: =D27/J27 -> 1.6
C28: Gula hijau | D28: 1000 | E28: =VLOOKUP(C28,Master!$B$6:$N$243,9,FALSE) -> gr | F28: =VLOOKUP(C28,Master!B27:N264,10,FALSE) -> 17.5 | G28: =D28*F28 -> 17500
C29: Air Galon | D29: 1000 | E29: =VLOOKUP(C29,Master!$B$6:$N$243,9,FALSE) -> ml | F29: =VLOOKUP(C29,Master!B28:N265,10,FALSE) -> 0.66315789 | G29: =D29*F29 -> 663.15789
A30: 9 | B30: Bar Pro Syrup Lemon | D30: =SUM(D31:D32) -> 300 | E30: =VLOOKUP(B30,Master!B30:N267,9,FALSE) -> ml | G30: =SUM(G31:G32) -> 4752.1968 | H30: 0.1 | I30: =G30+(G30*H30) -> 5227.4165 | J30: 40 | K30: =I30/J30 -> 130.68541 | L30: =D30/J30 -> 7.5
C31: Lemon Syrup 460ml | D31: 100 | E31: =VLOOKUP(C31,Master!$B$6:$N$243,9,FALSE) -> ml | F31: =VLOOKUP(C31,Master!B30:N267,10,FALSE) -> 46.195652 | G31: =D31*F31 -> 4619.5652
C32: Air Galon | D32: 200 | E32: =VLOOKUP(C32,Master!$B$6:$N$243,9,FALSE) -> ml | F32: =VLOOKUP(C32,Master!B31:N268,10,FALSE) -> 0.66315789 | G32: =D32*F32 -> 132.63158
A33: 10 | B33: Bar Pro Thai Tea | D33: =SUM(D34:D35) -> 2090 | E33: =VLOOKUP(B33,Master!B33:N270,9,FALSE) -> ml | G33: =SUM(G34:G35) -> 13926.316 | H33: 0.1 | I33: =G33+(G33*H33) -> 15318.947 | J33: 160 | K33: =I33/J33 -> 95.743421 | L33: =D33/J33 -> 13.0625
C34: Thai Black Tea 400 gr | D34: 90 | E34: =VLOOKUP(C34,Master!$B$6:$N$243,9,FALSE) -> gr | F34: =VLOOKUP(C34,Master!B33:N270,10,FALSE) -> 140 | G34: =D34*F34 -> 12600
C35: Air Galon | D35: 2000 | E35: =VLOOKUP(C35,Master!$B$6:$N$243,9,FALSE) -> ml | F35: =VLOOKUP(C35,Master!B34:N271,10,FALSE) -> 0.66315789 | G35: =D35*F35 -> 1326.3158
A36: 11 | B36: Bar Pro espresso | D36: =SUM(D37:D38) -> 2200 | E36: =VLOOKUP(B36,Master!B36:N273,9,FALSE) -> porsi | G36: =SUM(G37:G38) -> 195795.79 | H36: 0.1 | I36: =G36+(G36*H36) -> 215375.37 | J36: 55 | K36: =I36/J36 -> 3915.9158 | L36: =D36/J36 -> 40
C37: Beans | D37: 1000 | E37: =VLOOKUP(C37,Master!$B$6:$N$1000,9,FALSE) -> gr | F37: =VLOOKUP(C37,Master!B36:N1000,10,FALSE) -> 195 | G37: =D37*F37 -> 195000
C38: Air Galon | D38: 1200 | E38: =VLOOKUP(C38,Master!$B$6:$N$1000,9,FALSE) -> ml | F38: =VLOOKUP(C38,Master!B37:N1001,10,FALSE) -> 0.66315789 | G38: =D38*F38 -> 795.78947
A39: 12 | B39: Bar Pro Cold Brew | D39: =SUM(D40:D41) -> 2500 | E39: =VLOOKUP(B39,Master!B39:N276,9,FALSE) -> ml | G39: =SUM(G40:G41) -> 81326.316 | H39: 0.1 | I39: =G39+(G39*H39) -> 89458.947 | J39: 20 | K39: =I39/J39 -> 4472.9474 | L39: =D39/J39 -> 125
C40: Beans Blend 50:50 | D40: 500 | E40: =VLOOKUP(C40,Master!$B$6:$N$1000,9,FALSE) -> gr | F40: =VLOOKUP(C40,Master!B39:N1003,10,FALSE) -> 160 | G40: =D40*F40 -> 80000
C41: Air Galon | D41: 2000 | E41: =VLOOKUP(C41,Master!$B$6:$N$1000,9,FALSE) -> ml | F41: =VLOOKUP(C41,Master!B40:N1004,10,FALSE) -> 0.66315789 | G41: =D41*F41 -> 1326.3158
A42: 13 | B42: Bar Pro Aren Liquid | D42: =SUM(D43:D44) -> 1500 | E42: =VLOOKUP(B42,Master!B42:N279,9,FALSE) -> porsi | G42: =SUM(G43:G44) -> 42331.579 | H42: 0.1 | I42: =G42+(G42*H42) -> 46564.737 | J42: 40 | K42: =I42/J42 -> 1164.1184 | L42: =D42/J42 -> 37.5
C43: Gula Palm | D43: 1000 | E43: =VLOOKUP(C43,Master!$B$6:$N$1000,9,FALSE) -> gr | F43: =VLOOKUP(C43,Master!B42:N1006,10,FALSE) -> 42 | G43: =D43*F43 -> 42000
C44: Air Galon | D44: 500 | E44: =VLOOKUP(C44,Master!$B$6:$N$1000,9,FALSE) -> ml | F44: =VLOOKUP(C44,Master!B43:N1007,10,FALSE) -> 0.66315789 | G44: =D44*F44 -> 331.57895

Sheet List Bahan Burtok
I1: 9 | J1: 10 | K1: PO | M1: PO | O1: PO
A2: List Bahan | B2: Kode | C2: Kategori | D2: Lokasi | E2: Qty | F2: Kemasan | G2: Ukuran | H2: Satuan | I2: Jumlah | J2: Harga per pcs/ml/gr | K2: PO | L2: Sat | M2: PO | N2: Sat | O2: PO | P2: Sat | Q2: Cek
A3: KTC Daging Sop | B3: Z-001 | C3: KTC | D3: Central Kitchen | E3: 1 | F3: gr | H3: gr | J3: 217.8 | L3: pak | N3: pak | P3: pak | Q3: FALSE
A4: KTC Kuah | B4: Z-002 | C4: KTC | D4: Central Kitchen | E4: 1 | F4: ml | H4: ml | J4: 2.2183333 | L4: pak | N4: pak | P4: pak | Q4: FALSE
A5: KTC Perkedel | B5: Z-003 | C5: KTC | D5: Central Kitchen | E5: 1 | F5: pcs | H5: pcs | J5: 1071.0526 | L5: pak | N5: pak | P5: pak | Q5: FALSE
A6: KTC Saikoro | B6: Z-004 | C6: KTC | D6: Central Kitchen | E6: 1 | F6: tusuk | H6: tusuk | J6: 6002.4242 | L6: pak | N6: pak | P6: pak | Q6: FALSE
A7: KTC Garlic Oil | B7: Z-005 | C7: KTC | D7: Central Kitchen | E7: 1 | F7: gr | H7: gr | J7: 120.84749 | L7: pak | N7: pak | P7: pak | Q7: FALSE
A8: KTC Daging Iris | B8: Z-006 | C8: KTC | D8: Central Kitchen | E8: 1 | F8: tusuk | H8: tusuk | J8: 2194.5 | L8: pak | N8: pak | P8: pak | Q8: FALSE
A9: KTC Jukut Goreng | B9: Z-007 | C9: KTC | D9: Central Kitchen | E9: 1 | F9: porsi | H9: porsi | J9: 2438.9444 | L9: pak | N9: pak | P9: pak | Q9: FALSE
A10: KTC Bawang Putih Goreng | B10: Z-008 | C10: KTC | D10: Central Kitchen | E10: 1 | F10: gr | H10: gr | J10: 179.36111 | L10: pak | N10: pak | P10: pak | Q10: FALSE
A11: KTC Bawang Putih Mentah | B11: Z-009 | C11: KTC | D11: Central Kitchen | E11: 1 | F11: gr | H11: gr | J11: 179.36111 | L11: pak | N11: pak | P11: pak | Q11: FALSE
A12: KTC Oil Ijo | B12: Z-010 | C12: KTC | D12: Central Kitchen | E12: 1 | F12: ml | H12: ml | L12: pak | N12: pak | P12: pak | Q12: FALSE
A13: KTC Oil Merah | B13: Z-011 | C13: KTC | D13: Central Kitchen | E13: 1 | F13: ml | H13: ml | L13: pak | N13: pak | P13: pak | Q13: FALSE
A14: KTC Sambal Sop | B14: Z-012 | C14: KTC | D14: Central Kitchen | E14: 1 | F14: gr | H14: gr | L14: pak | N14: pak | P14: pak | Q14: FALSE
A15: Krupuk DDN isi 10 | B15: ZA-004 | C15: Bahan Pokok | D15: Gudang Burtok | E15: 1 | F15: pak | G15: 10 | H15: pcs | I15: 4200 | J15: =I15/G15 -> 420 | L15: pak | N15: pak | P15: pak | Q15: FALSE
A16: Jeruk Nipis 1kg | B16: ZA-005 | C16: Bahan Pokok | D16: Gudang Burtok | E16: 1 | F16: pak | G16: 34 | H16: pcs | I16: 23000 | J16: =I16/G16 -> 676.47059 | L16: pak | N16: pak | P16: pak | Q16: FALSE
A17: Telur Pitan Isi 4 | B17: ZA-006 | C17: Bahan Pokok | D17: Gudang Burtok | E17: 1 | F17: pak | G17: 4 | H17: pcs | I17: 37800 | J17: =I17/G17 -> 9450 | L17: pak | N17: pak | P17: pak | Q17: FALSE
A18: Telur Bebek Asin Isi 6 | B18: ZA-007 | C18: Bahan Pokok | D18: Gudang Burtok | E18: 1 | F18: pak | G18: 6 | H18: pcs | I18: 47950 | J18: =I18/G18 -> 7991.6667 | L18: pak | N18: pak | P18: pak | Q18: FALSE
A19: Telur Bebek Asin Mentah Isi 6 | B19: ZA-008 | C19: Bahan Pokok | D19: Gudang Burtok | E19: 1 | F19: pak | G19: 6 | H19: pcs | I19: 43250 | J19: =I19/G19 -> 7208.3333 | L19: pak | N19: pak | P19: pak | Q19: FALSE
A20: Wansui | B20: ZA-009 | C20: Bahan Pokok | D20: Gudang Burtok | E20: 1 | F20: pak | G20: 1000 | H20: gr | I20: 69000 | J20: =I20/G20 -> 69 | L20: pak | N20: pak | P20: pak | Q20: FALSE
A21: Perkedel | B21: ZA-010 | C21: Bahan Pokok | D21: Gudang Burtok | E21: 1 | F21: pak | G21: 190 | H21: pcs | I21: 185000 | J21: =I21/G21 -> 973.68421 | L21: pak | N21: pak | P21: pak | Q21: FALSE
A22: Selada Air 1 kg | B22: ZA-011 | C22: Bahan Pokok | D22: Gudang Burtok | E22: 1 | F22: kg | G22: 1000 | H22: gr | I22: 34500 | J22: =I22/G22 -> 34.5 | L22: kg | N22: kg | P22: kg | Q22: FALSE
A23: Cabe Rawit Merah | B23: ZA-012 | C23: Bahan Pokok | D23: Gudang Burtok | E23: 1 | F23: Pak | G23: 1000 | H23: gr | I23: 46000 | J23: =I23/G23 -> 46 | L23: Pak | N23: Pak | P23: Pak | Q23: FALSE
A24: Telur Ayam | B24: ZA-013 | C24: Bahan Pokok | D24: Gudang Burtok | E24: 1 | F24: pak | G24: 15 | H24: pcs | I24: 28000 | J24: =I24/G24 -> 1866.6667 | L24: pak | N24: pak | P24: pak | Q24: FALSE
A25: Garam Cap Kapal 250gr | B25: ZA-014 | C25: Bumbu | D25: Gudang Burtok | E25: 1 | F25: pak | G25: 250 | H25: gr | I25: 2500 | J25: =I25/G25 -> 10 | L25: pak | N25: pak | P25: pak | Q25: FALSE
A26: Lada Hitam Bubuk | B26: ZA-015 | C26: Bumbu | D26: Gudang Burtok | E26: 1 | F26: pak | G26: 1000 | H26: gr | I26: 80900 | J26: =I26/G26 -> 80.9 | L26: pak | N26: pak | P26: pak | Q26: FALSE
... A49: Gas 12kg | B49: ZC-004 | C49: Gas | D49: SOKO | E49: 1 | F49: tabung | G49: 60 | H49: Jam | I49: 200000 | J49: =I49/G49 -> 3333.3333 | L49: tabung | N49: tabung | P49: tabung | Q49: FALSE
A50: z | B50: ZZZ | E50: z | F50: z | I50: z | J50: z | K50: z | L50: z | Q50: z

Sheet History Sept 22
A1: History September 2022
A2: The Soko Coffee Tea Chocolate
F5: 44804 | J5: =F5+1 -> 44805
F6: Total PO | H6: =SUM(H8:H59) -> 6246061 | J6: Data Aktual | L6: =SUM(L8:L59) -> #N/A
A7: Remark | B7: Kode | C7: Qty/pack | D7: Unit | E7: toko | F7: PO Pack | G7: Unit Pack | H7: PO Bill | I7: Checker | J7: Bought | K7: Price/Pack | L7: Bill | M7: Keterangan
A8: Pocky Choco Stick | B8: B018 | C8: =VLOOKUP($A8,Master!$B$50:$N$232,8,FALSE) -> 20 | D8: =VLOOKUP($A8,Master!$B$50:$N$232,9,FALSE) -> pcs | E8: =VLOOKUP($A8,Master!$B$50:$N$232,11,FALSE) -> Kurnia Mas | F8: 6 | G8: Pack | H8: 43800 | I8: TRUE | J8: 5 | K8: 7500 | L8: =J8*K8 -> 37500 | M8: KurniaMas
A9: Orange Sunkist Fruit | B9: B029 | C9: =VLOOKUP($A9,Master!$B$50:$N$232,8,FALSE) -> 1000 | D9: =VLOOKUP($A9,Master!$B$50:$N$232,9,FALSE) -> gr | E9: =VLOOKUP($A9,Master!$B$50:$N$232,11,FALSE) -> Borma | F9: 1 | G9: Kilogram | H9: 31900 | I9: TRUE | J9: 1 | K9: 40186 | L9: =J9*K9 -> 40186 | M9: Yogya
A10: Lemon Fruit | B10: B030 | C10: =VLOOKUP($A10,Master!$B$50:$N$232,8,FALSE) -> 1000 | D10: =VLOOKUP($A10,Master!$B$50:$N$232,9,FALSE) -> gr | E10: =VLOOKUP($A10,Master!$B$50:$N$232,11,FALSE) -> Borma | F10: 1 | G10: Kilogram | H10: 16000 | I10: TRUE | J10: 1 | K10: =VLOOKUP($A10,Master!$B$50:$N$232,6,FALSE) -> 18000 | L10: 15000
A11: Leaf Dill | B11: B105 | C11: =VLOOKUP($A11,Master!$B$50:$N$232,8,FALSE) -> #N/A | D11: =VLOOKUP($A11,Master!$B$50:$N$232,9,FALSE) -> #N/A | E11: =VLOOKUP($A11,Master!$B$50:$N$232,11,FALSE) -> #N/A | F11: 1 | G11: Kilogram | H11: 5950 | I11: TRUE | J11: 2 | K11: =VLOOKUP($A11,Master!$B$50:$N$232,6,FALSE) -> #N/A | L11: 10710 | M11: Yogya
A12: Pineapple Juice Jungle Diamond | B12: B119 | C12: =VLOOKUP($A12,Master!$B$50:$N$232,8,FALSE) -> #N/A | D12: =VLOOKUP($A12,Master!$B$50:$N$232,9,FALSE) -> #N/A | E12: =VLOOKUP($A12,Master!$B$50:$N$232,11,FALSE) -> #N/A | F12: 1 | G12: Bottle | H12: 27000 | I12: TRUE | J12: 1 | K12: =VLOOKUP($A12,Master!$B$50:$N$232,6,FALSE) -> #N/A | L12: =J12*K12 -> #N/A | M12: KurniaMas
A13: Pomegranete Juice Jungle Diamond | B13: B120 | C13: =VLOOKUP($A13,Master!$B$50:$N$232,8,FALSE) -> #N/A | D13: =VLOOKUP($A13,Master!$B$50:$N$232,9,FALSE) -> #N/A | E13: =VLOOKUP($A13,Master!$B$50:$N$232,11,FALSE) -> #N/A | F13: 1 | G13: Bottle | H13: 30303 | I13: TRUE | J13: 1 | K13: =VLOOKUP($A13,Master!$B$50:$N$232,6,FALSE) -> #N/A | L13: 27000 | M13: KurniaMas
A14: Tissue Roll | B14: B179 | C14: =VLOOKUP($A14,Master!$B$50:$N$232,8,FALSE) -> #N/A | D14: =VLOOKUP($A14,Master!$B$50:$N$232,9,FALSE) -> #N/A | E14: =VLOOKUP($A14,Master!$B$50:$N$232,11,FALSE) -> #N/A | F14: 2 | G14: Pack | H14: 9600 | I14: TRUE | J14: 1 | K14: 17500 | L14: =J14*K14 -> 17500 | M14: Jolly (isi 10)
A15: Softex Charm | B15: B181 | C15: =VLOOKUP($A15,Master!$B$50:$N$232,8,FALSE) -> #N/A | D15: =VLOOKUP($A15,Master!$B$50:$N$232,9,FALSE) -> #N/A | E15: =VLOOKUP($A15,Master!$B$50:$N$232,11,FALSE) -> #N/A | F15: 2 | G15: Pack | H15: 32200 | I15: TRUE | J15: 2 | K15: =VLOOKUP($A15,Master!$B$50:$N$232,6,FALSE) -> #N/A | L15: 24750 | M15: Yogya
A16: Vit Mineral Water 600ml | B16: B087 | C16: =VLOOKUP($A16,Master!$B$50:$N$232,8,FALSE) -> #N/A | D16: =VLOOKUP($A16,Master!$B$50:$N$232,9,FALSE) -> #N/A | E16: =VLOOKUP($A16,Master!$B$50:$N$232,11,FALSE) -> #N/A | F16: 6 | G16: Dus | H16: 182400 | I16: TRUE | J16: 6 | K16: =VLOOKUP($A16,Master!$B$50:$N$232,6,FALSE) -> #N/A | L16: =J16*K16 -> #N/A
A17: Powder Chocolate Origin Andalas | B17: B016 | C17: =VLOOKUP($A17,Master!$B$50:$N$232,8,FALSE) -> #N/A | D17: =VLOOKUP($A17,Master!$B$50:$N$232,9,FALSE) -> #N/A | E17: =VLOOKUP($A17,Master!$B$50:$N$232,11,FALSE) -> #N/A | F17: 2 | G17: Pack | H17: 440000 | I17: TRUE | J17: 2 | K17: =VLOOKUP($A17,Master!$B$50:$N$232,6,FALSE) -> #N/A | L17: =J17*K17 -> #N/A
A18: Gula Putih Sachet | B18: B184 | C18: =VLOOKUP($A18,Master!$B$50:$N$240,8,FALSE) -> #N/A | D18: =VLOOKUP($A18,Master!$B$50:$N$240,9,FALSE) -> #N/A | E18: Garnish Kering | F18: 2 | G18: Pack | H18: 140000 | I18: TRUE | J18: 2 | K18: =VLOOKUP($A18,Master!$B$50:$N$240,6,FALSE) -> #N/A | L18: 90000 | M18: KurniaMas
A19: Arabika Espresso | B19: B158 | C19: =VLOOKUP($A19,Master!$B$50:$N$232,8,FALSE) -> #N/A | D19: =VLOOKUP($A19,Master!$B$50:$N$232,9,FALSE) -> #N/A | E19: =VLOOKUP($A19,Master!$B$50:$N$232,11,FALSE) -> #N/A | F19: 2 | G19: Kilogram | H19: 350000 | I19: TRUE | J19: 2 | K19: =VLOOKUP($A19,Master!$B$50:$N$232,6,FALSE) -> #N/A | L19: =J19*K19 -> #N/A
A20: Rum Syrup Davinci LMK | B20: B010 | C20: =VLOOKUP($A20,Master!$B$50:$N$232,8,FALSE) -> #N/A | D20: =VLOOKUP($A20,Master!$B$50:$N$232,9,FALSE) -> #N/A | E20: =VLOOKUP($A20,Master!$B$50:$N$232,11,FALSE) -> #N/A | F20: 1 | G20: Bottle | H20: 137000 | I20: TRUE | J20: 1 | K20: =VLOOKUP($A20,Master!$B$50:$N$232,6,FALSE) -> #N/A | L20: 135420
A21: Vanilla Syrup Davinci LMK | B21: B025 | C21: =VLOOKUP($A21,Master!$B$50:$N$232,8,FALSE) -> #N/A | D21: =VLOOKUP($A21,Master!$B$50:$N$232,9,FALSE) -> #N/A | E21: =VLOOKUP($A21,Master!$B$50:$N$232,11,FALSE) -> #N/A | F21: 1 | G21: Bottle | H21: 137000 | I21: TRUE | J21: 1 | K21: =VLOOKUP($A21,Master!$B$50:$N$232,6,FALSE) -> #N/A | L21: 135420
A22: Hazelnut Syrup Davinci LMK | B22: B026 | C22: =VLOOKUP($A22,Master!$B$50:$N$232,8,FALSE) -> #N/A | D22: =VLOOKUP($A22,Master!$B$50:$N$232,9,FALSE) -> #N/A | E22: =VLOOKUP($A22,Master!$B$50:$N$232,11,FALSE) -> #N/A | F22: 1 | G22: Bottle | H22: 137000 | I22: TRUE | J22: 1 | K22: =VLOOKUP($A22,Master!$B$50:$N$232,6,FALSE) -> #N/A | L22: 135420
A23: Caramel Syrup Davinci LMK | B23: B027 | C23: =VLOOKUP($A23,Master!$B$50:$N$232,8,FALSE) -> #N/A | D23: =VLOOKUP($A23,Master!$B$50:$N$232,9,FALSE) -> #N/A | E23: =VLOOKUP($A23,Master!$B$50:$N$232,11,FALSE) -> #N/A | F23: 1 | G23: Bottle | H23: 137000 | I23: TRUE | J23: 1 | K23: =VLOOKUP($A23,Master!$B$50:$N$232,6,FALSE) -> #N/A | L23: 135420
A24: Oyster Sauce Panda | B24: B056 | C24: =VLOOKUP($A24,Master!$B$50:$N$232,8,FALSE) -> 700 | D24: =VLOOKUP($A24,Master!$B$50:$N$232,9,FALSE) -> gr | E24: =VLOOKUP($A24,Master!$B$50:$N$232,11,FALSE) -> Kurnia Mas | F24: 1 | G24: Bottle | H24: 54500 | I24: TRUE | J24: 1 | K24: =VLOOKUP($A24,Master!$B$50:$N$232,6,FALSE) -> 52500 | L24: 48000 | M24: KurniaMas
A25: Gulaku Premium Hijau | B25: B001 | C25: =VLOOKUP($A25,Master!$B$50:$N$232,8,FALSE) -> #N/A | D25: =VLOOKUP($A25,Master!$B$50:$N$232,9,FALSE) -> #N/A | E25: =VLOOKUP($A25,Master!$B$50:$N$232,11,FALSE) -> #N/A | F25: 2 | G25: Kilogram | H25: 28000 | I25: TRUE | J25: 2 | K25: 14250 | L25: =J25*K25 -> 28500
A26: Evaporasi FN | B26: B003 | C26: =VLOOKUP($A26,Master!$B$50:$N$232,8,FALSE) -> #N/A | D26: =VLOOKUP($A26,Master!$B$50:$N$232,9,FALSE) -> #N/A | E26: =VLOOKUP($A26,Master!$B$50:$N$232,11,FALSE) -> #N/A | F26: 5 | G26: Can | H26: 80000 | I26: TRUE | J26: 5 | K26: =VLOOKUP($A26,Master!$B$50:$N$232,6,FALSE) -> #N/A | L26: =J26*K26 -> #N/A
A27: Thai Black Tea Number One 400 gr | B27: B004 | C27: =VLOOKUP($A27,Master!$B$50:$N$232,8,FALSE) -> #N/A | D27: =VLOOKUP($A27,Master!$B$50:$N$232,9,FALSE) -> #N/A | E27: =VLOOKUP($A27,Master!$B$50:$N$232,11,FALSE) -> #N/A | F27: 1 | G27: Pack | H27: 56000 | I27: TRUE | J27: 1 | K27: =VLOOKUP($A27,Master!$B$50:$N$232,6,FALSE) -> #N/A | L27: =J27*K27 -> #N/A
A28: SKM Carnation | B28: B031 | C28: =VLOOKUP($A28,Master!$B$50:$N$232,8,FALSE) -> #N/A | D28: =VLOOKUP($A28,Master!$B$50:$N$232,9,FALSE) -> #N/A | E28: =VLOOKUP($A28,Master!$B$50:$N$232,11,FALSE) -> #N/A | F28: 10 | G28: Can | H28: 110000 | I28: TRUE | J28: 10 | K28: =VLOOKUP($A28,Master!$B$50:$N$232,6,FALSE) -> #N/A | L28: =J28*K28 -> #N/A
A29: Gula Merah / Aren Padat Kiloan | B29: B033 | C29: =VLOOKUP($A29,Master!$B$50:$N$232,8,FALSE) -> 1000 | D29: =VLOOKUP($A29,Master!$B$50:$N$232,9,FALSE) -> gr | E29: =VLOOKUP($A29,Master!$B$50:$N$232,11,FALSE) -> PD Aroma Jaya | F29: 1 | G29: Kilogram | H29: 16000 | I29: TRUE | J29: 1 | K29: =VLOOKUP($A29,Master!$B$50:$N$232,6,FALSE) -> 17000 | L29: =J29*K29 -> 17000
A30: Sunquick Lemon | B30: B042 | C30: =VLOOKUP($A30,Master!$B$50:$N$232,8,FALSE) -> #N/A | D30: =VLOOKUP($A30,Master!$B$50:$N$232,9,FALSE) -> #N/A | E30: =VLOOKUP($A30,Master!$B$50:$N$232,11,FALSE) -> #N/A | F30: 5 | G30: Bottle | H30: 150000 | I30: TRUE | J30: 5 | K30: 31000 | L30: =J30*K30 -> 155000
A31: Sunquick Orange | B31: B043 | C31: =VLOOKUP($A31,Master!$B$50:$N$232,8,FALSE) -> #N/A | D31: =VLOOKUP($A31,Master!$B$50:$N$232,9,FALSE) -> #N/A | E31: =VLOOKUP($A31,Master!$B$50:$N$232,11,FALSE) -> #N/A | F31: 2 | G31: Bottle | H31: 60000 | I31: FALSE | K31: =VLOOKUP($A31,Master!$B$50:$N$232,6,FALSE) -> #N/A | L31: =J31*K31 -> #N/A | M31: Kosong
A32: Tepung Segitiga Biru | B32: B046 | C32: =VLOOKUP($A32,Master!$B$50:$N$232,8,FALSE) -> #N/A | D32: =VLOOKUP($A32,Master!$B$50:$N$232,9,FALSE) -> #N/A | E32: =VLOOKUP($A32,Master!$B$50:$N$232,11,FALSE) -> #N/A | F32: 5 | G32: Pack | H32: 70000 | I32: TRUE | J32: 5 | K32: 14500 | L32: =J32*K32 -> 72500
A33: Mayonaise Maestro | B33: B054 | C33: =VLOOKUP($A33,Master!$B$50:$N$232,8,FALSE) -> #N/A | D33: =VLOOKUP($A33,Master!$B$50:$N$232,9,FALSE) -> #N/A | E33: =VLOOKUP($A33,Master!$B$50:$N$232,11,FALSE) -> #N/A | F33: 1 | G33: Pack | H33: 27500 | I33: TRUE | J33: 1 | K33: =VLOOKUP($A33,Master!$B$50:$N$232,6,FALSE) -> #N/A | L33: =J33*K33 -> #N/A
A34: Pasta Spaghetti Lafonte | B34: B059 | C34: =VLOOKUP($A34,Master!$B$50:$N$232,8,FALSE) -> #N/A | D34: =VLOOKUP($A34,Master!$B$50:$N$232,9,FALSE) -> #N/A | E34: =VLOOKUP($A34,Master!$B$50:$N$232,11,FALSE) -> #N/A | F34: 1 | G34: Pack | H34: 27500 | I34: TRUE | J34: 1 | K34: =VLOOKUP($A34,Master!$B$50:$N$232,6,FALSE) -> #N/A | L34: 27000
A35: Chilli Sauce Delmonte | B35: B064 | C35: =VLOOKUP($A35,Master!$B$50:$N$232,8,FALSE) -> #N/A | D35: =VLOOKUP($A35,Master!$B$50:$N$232,9,FALSE) -> #N/A | E35: =VLOOKUP($A35,Master!$B$50:$N$232,11,FALSE) -> #N/A | F35: 1 | G35: Pack | H35: 19500 | I35: TRUE | J35: 1 | K35: =VLOOKUP($A35,Master!$B$50:$N$232,6,FALSE) -> #N/A | L35: 19250
A36: Delmonte Tomato | B36: B066 | C36: =VLOOKUP($A36,Master!$B$50:$N$232,8,FALSE) -> #N/A | D36: =VLOOKUP($A36,Master!$B$50:$N$232,9,FALSE) -> #N/A | E36: =VLOOKUP($A36,Master!$B$50:$N$232,11,FALSE) -> #N/A | F36: 2 | G36: Pack | H36: 28000 | I36: TRUE | J36: 2 | K36: =VLOOKUP($A36,Master!$B$50:$N$232,6,FALSE) -> #N/A | L36: =J36*K36 -> #N/A
A37: Strawberry Syrup Mardjan | B37: B071 | C37: =VLOOKUP($A37,Master!$B$50:$N$232,8,FALSE) -> #N/A | D37: =VLOOKUP($A37,Master!$B$50:$N$232,9,FALSE) -> #N/A | E37: =VLOOKUP($A37,Master!$B$50:$N$232,11,FALSE) -> #N/A | F37: 1 | G37: Bottle | H37: 20250 | I37: FALSE | K37: =VLOOKUP($A37,Master!$B$50:$N$232,6,FALSE) -> #N/A | L37: =J37*K37 -> #N/A | M37: Kosong
A38: Spaghetti Sauce Delmonte | B38: B114 | C38: =VLOOKUP($A38,Master!$B$50:$N$232,8,FALSE) -> #N/A | D38: =VLOOKUP($A38,Master!$B$50:$N$232,9,FALSE) -> #N/A | E38: =VLOOKUP($A38,Master!$B$50:$N$232,11,FALSE) -> #N/A | F38: 2 | G38: Pack | H38: 15800 | I38: TRUE | J38: 2 | K38: =VLOOKUP($A38,Master!$B$50:$N$232,6,FALSE) -> #N/A | L38: =J38*K38 -> #N/A
A39: Smoke Barbeque Sauce Delmonte | B39: B117 | C39: =VLOOKUP($A39,Master!$B$50:$N$232,8,FALSE) -> #N/A | D39: =VLOOKUP($A39,Master!$B$50:$N$232,9,FALSE) -> #N/A | E39: =VLOOKUP($A39,Master!$B$50:$N$232,11,FALSE) -> #N/A | F39: 1 | G39: Pack | H39: 7900 | I39: TRUE | J39: 1 | K39: =VLOOKUP($A39,Master!$B$50:$N$232,6,FALSE) -> #N/A | L39: =J39*K39 -> #N/A
A40: Trash Bag Tulip 80 x 120 (0,6) | B40: B130 | C40: =VLOOKUP($A40,Master!$B$50:$N$232,8,FALSE) -> 12 | D40: =VLOOKUP($A40,Master!$B$50:$N$232,9,FALSE) -> pcs | E40: =VLOOKUP($A40,Master!$B$50:$N$232,11,FALSE) -> PD Aroma Jaya | F40: 4 | G40: Pack | H40: 88000 | I40: TRUE | J40: 4 | K40: =VLOOKUP($A40,Master!$B$50:$N$232,6,FALSE) -> 18000 | L40: =J40*K40 -> 72000
A41: Plastik Bening Anti Panas 15x30 | B41: B142 | C41: =VLOOKUP($A41,Master!$B$50:$N$232,8,FALSE) -> 50 | D41: =VLOOKUP($A41,Master!$B$50:$N$232,9,FALSE) -> pcs | E41: =VLOOKUP($A41,Master!$B$50:$N$232,11,FALSE) -> PD Aroma Jaya | F41: 2 | G41: Pack | H41: 20000 | I41: TRUE | J41: 2 | K41: =VLOOKUP($A41,Master!$B$50:$N$232,6,FALSE) -> 10000 | L41: 18500
A42: Spons | B42: B143 | C42: =VLOOKUP($A42,Master!$B$50:$N$232,8,FALSE) -> 1 | D42: =VLOOKUP($A42,Master!$B$50:$N$232,9,FALSE) -> pcs | E42: =VLOOKUP($A42,Master!$B$50:$N$232,11,FALSE) -> PD Aroma Jaya | F42: 2 | G42: Pack | H42: 5600 | I42: TRUE | J42: 2 | K42: 3000 | L42: =J42*K42 -> 6000
A43: Plastik Sealer | B43: B183 | C43: =VLOOKUP($A43,Master!$B$50:$N$232,8,FALSE) -> #N/A | D43: =VLOOKUP($A43,Master!$B$50:$N$232,9,FALSE) -> #N/A | E43: =VLOOKUP($A43,Master!$B$50:$N$232,11,FALSE) -> #N/A | F43: 1 | G43: Pack | H43: 65000 | I43: TRUE | J43: 1 | K43: =VLOOKUP($A43,Master!$B$50:$N$232,6,FALSE) -> #N/A | L43: =J43*K43 -> #N/A
A44: Strawberry Puree Health Today | B44: B012 | C44: =VLOOKUP($A44,Master!$B$50:$N$232,8,FALSE) -> #N/A | D44: =VLOOKUP($A44,Master!$B$50:$N$232,9,FALSE) -> #N/A | E44: =VLOOKUP($A44,Master!$B$50:$N$232,11,FALSE) -> #N/A | F44: 1 | G44: Bottle | H44: 216450 | I44: TRUE | J44: 1 | K44: =VLOOKUP($A44,Master!$B$50:$N$232,6,FALSE) -> #N/A | L44: 195000
A45: Taro Powder Health Today | B45: B013 | C45: =VLOOKUP($A45,Master!$B$50:$N$232,8,FALSE) -> #N/A | D45: =VLOOKUP($A45,Master!$B$50:$N$232,9,FALSE) -> #N/A | E45: =VLOOKUP($A45,Master!$B$50:$N$232,11,FALSE) -> #N/A | F45: 1 | G45: Pack | H45: 148500 | I45: TRUE | J45: 1 | K45: =VLOOKUP($A45,Master!$B$50:$N$232,6,FALSE) -> #N/A | L45: 135000
A46: Red Velvet Powder Health Today | B46: B014 | C46: =VLOOKUP($A46,Master!$B$50:$N$232,8,FALSE) -> #N/A | D46: =VLOOKUP($A46,Master!$B$50:$N$232,9,FALSE) -> #N/A | E46: =VLOOKUP($A46,Master!$B$50:$N$232,11,FALSE) -> #N/A | F46: 2 | G46: Pack | H46: 297000 | I46: TRUE | J46: 2 | K46: =VLOOKUP($A46,Master!$B$50:$N$232,6,FALSE) -> #N/A | L46: 270000
A47: Mint Syrup Health Today | B47: B123 | C47: =VLOOKUP($A47,Master!$B$50:$N$232,8,FALSE) -> #N/A | D47: =VLOOKUP($A47,Master!$B$50:$N$232,9,FALSE) -> #N/A | E47: =VLOOKUP($A47,Master!$B$50:$N$232,11,FALSE) -> #N/A | F47: 2 | G47: Bottle | H47: 188700 | I47: TRUE | J47: 2 | K47: =VLOOKUP($A47,Master!$B$50:$N$232,6,FALSE) -> #N/A | L47: 170000
A48: Fanta Soda Botol | B48: B009 | C48: =VLOOKUP($A48,Master!$B$50:$N$232,8,FALSE) -> #N/A | D48: =VLOOKUP($A48,Master!$B$50:$N$232,9,FALSE) -> #N/A | E48: =VLOOKUP($A48,Master!$B$50:$N$232,11,FALSE) -> #N/A | F48: 4 | G48: Crat | H48: 228000 | I48: TRUE | J48: 4 | K48: =VLOOKUP($A48,Master!$B$50:$N$232,6,FALSE) -> #N/A | L48: 121200
A49: UHT Full Cream Diamond Sukanda | B49: B028 | C49: =VLOOKUP($A49,Master!$B$50:$N$232,8,FALSE) -> #N/A | D49: =VLOOKUP($A49,Master!$B$50:$N$232,9,FALSE) -> #N/A | E49: =VLOOKUP($A49,Master!$B$50:$N$232,11,FALSE) -> #N/A | F49: 3 | G49: Dus | H49: 545787 | I49: TRUE | J49: 3 | K49: =571761/3 -> 190587 | L49: =J49*K49 -> 571761
A50: Freshmilk Diamond Sukanda | B50: B048 | C50: =VLOOKUP($A50,Master!$B$50:$N$232,8,FALSE) -> #N/A | D50: =VLOOKUP($A50,Master!$B$50:$N$232,9,FALSE) -> #N/A | E50: =VLOOKUP($A50,Master!$B$50:$N$232,11,FALSE) -> #N/A | F50: 3 | G50: Dus | H50: 608391 | I50: TRUE | J50: 3 | K50: =620100/3 -> 206700 | L50: =J50*K50 -> 620100
A51: Tortilla Corn | B51: B106 | C51: =VLOOKUP($A51,Master!$B$50:$N$232,8,FALSE) -> 10 | D51: =VLOOKUP($A51,Master!$B$50:$N$232,9,FALSE) -> pcs | E51: =VLOOKUP($A51,Master!$B$50:$N$232,11,FALSE) -> Setiabudi Market | F51: 5 | G51: Pack | H51: 84500 | I51: TRUE | J51: 6 | K51: =VLOOKUP($A51,Master!$B$50:$N$232,6,FALSE) -> 16900 | L51: 100386 | M51: Yogya
A52: Strawberry Fruit | B52: B069 | C52: =VLOOKUP($A52,Master!$B$50:$N$232,8,FALSE) -> 500 | D52: =VLOOKUP($A52,Master!$B$50:$N$232,9,FALSE) -> gr | E52: =VLOOKUP($A52,Master!$B$50:$N$232,11,FALSE) -> Toko Lain | F52: 2 | G52: Pack | H52: 50000 | I52: TRUE | J52: 2 | K52: =VLOOKUP($A52,Master!$B$50:$N$232,6,FALSE) -> 25000 | L52: =J52*K52 -> 50000 | M52: Bar+Ktc
A53: Soy Milk Drinho | B53: B007 | C53: =VLOOKUP($A53,Master!$B$50:$N$232,8,FALSE) -> #N/A | D53: =VLOOKUP($A53,Master!$B$50:$N$232,9,FALSE) -> #N/A | E53: =VLOOKUP($A53,Master!$B$50:$N$232,11,FALSE) -> #N/A | F53: 4 | G53: Pack | H53: 102600 | I53: TRUE | J53: 4 | K53: =VLOOKUP($A53,Master!$B$50:$N$232,6,FALSE) -> #N/A | L53: 68742
A54: Spons Kawat | B54: B166 | C54: =VLOOKUP($A54,Master!$B$50:$N$232,8,FALSE) -> #N/A | D54: =VLOOKUP($A54,Master!$B$50:$N$232,9,FALSE) -> #N/A | E54: =VLOOKUP($A54,Master!$B$50:$N$232,11,FALSE) -> #N/A | F54: 2 | G54: Pack | H54: 29800 | I54: TRUE | J54: 2 | K54: =VLOOKUP($A54,Master!$B$50:$N$232,6,FALSE) -> #N/A | L54: 8000 | M54: KurniaMas
A55: Much & More Woodlane Custom | B55: B006 | C55: =VLOOKUP($A55,Master!$B$50:$N$232,8,FALSE) -> 1000 | D55: =VLOOKUP($A55,Master!$B$50:$N$232,9,FALSE) -> gr | E55: =VLOOKUP($A55,Master!$B$50:$N$232,11,FALSE) -> Woodlane | F55: 2 | G55: Kilogram | H55: 340000 | I55: TRUE | J55: 2 | K55: =VLOOKUP($A55,Master!$B$50:$N$232,6,FALSE) -> 170000 | L55: =J55*K55 -> 340000
A56: Single Origin 85k | B56: B021 | C56: =VLOOKUP($A56,Master!$B$50:$N$232,8,FALSE) -> 200 | D56: =VLOOKUP($A56,Master!$B$50:$N$232,9,FALSE) -> gr | E56: =VLOOKUP($A56,Master!$B$50:$N$232,11,FALSE) -> Woodlane | F56: 3 | G56: Pack | H56: 255000 | I56: TRUE | J56: 3 | K56: =VLOOKUP($A56,Master!$B$50:$N$240,6,FALSE) -> 85000 | L56: =J56*K56 -> 255000
A57: Ice Cream Vanilla Diamond Sukanda | B57: B008 | C57: =VLOOKUP($A57,Master!$B$50:$N$232,8,FALSE) -> #N/A | D57: =VLOOKUP($A57,Master!$B$50:$N$232,9,FALSE) -> #N/A | E57: =VLOOKUP($A57,Master!$B$50:$N$232,11,FALSE) -> #N/A | F57: 2 | G57: Pail | H57: 315130 | I57: TRUE | J57: 2 | K57: =VLOOKUP($A57,Master!$B$50:$N$232,6,FALSE) -> #N/A | L57: =J57*K57 -> #N/A
A58: Lafonte Fettucini | C58: 750 | D58: gr | E58: PD Aroma Jaya | F58: 5 | G58: Pack | H58: 23000 | I58: TRUE | J58: 5 | K58: 23000 | L58: =23000*5 -> 115000 | M58: Item Baru
A59: Tepung Tapioka Rose Brand | E59: PD Aroma Jaya | F59: 5 | G59: Pack | H59: 6500 | I59: TRUE | J59: 5 | K59: 6500 | L59: =6500*5 -> 32500 | M59: Item Baru
F61: 44806 | J61: =F61+1 -> 44807
F62: Total PO | H62: =SUM(H64:H73) -> 718500 | J62: Data Aktual | L62: =SUM(L64:L73) -> #N/A
A63: Remark | B63: Kode | C63: Qty/pack | D63: Unit | E63: toko | F63: PO Pack | G63: Unit Pack | H63: PO Bill | I63: Checker | J63: Bought | K63: Price/Pack | L63: Bill | M63: Keterangan
A64: Wortel Grade A | B64: B035 | C64: =VLOOKUP($A64,Master!$B$50:$N$232,8,FALSE) -> 1000 | D64: =VLOOKUP($A64,Master!$B$50:$N$232,9,FALSE) -> gr | E64: =VLOOKUP($A64,Master!$B$50:$N$232,11,FALSE) -> Eden Farm | F64: 1 | G64: Kilogram | H64: 10200 | I64: TRUE | J64: 1 | K64: =VLOOKUP($A64,Master!$B$50:$N$232,6,FALSE) -> 18000 | L64: =J64*K64 -> 18000
A65: Bawang Putih | B65: B050 | C65: =VLOOKUP($A65,Master!$B$50:$N$232,8,FALSE) -> 1000 | D65: =VLOOKUP($A65,Master!$B$50:$N$232,9,FALSE) -> gr | E65: =VLOOKUP($A65,Master!$B$50:$N$232,11,FALSE) -> Eden Farm | F65: 1 | G65: Kilogram | H65: 24200 | I65: TRUE | J65: 1 | K65: =VLOOKUP($A65,Master!$B$50:$N$232,6,FALSE) -> 40000 | L65: 21100
A66: Paprika Green | B66: B058 | C66: =VLOOKUP($A66,Master!$B$50:$N$232,8,FALSE) -> 1000 | D66: =VLOOKUP($A66,Master!$B$50:$N$232,9,FALSE) -> gr | E66: =VLOOKUP($A66,Master!$B$50:$N$232,11,FALSE) -> Eden Farm | F66: 1 | G66: Kilogram | H66: 54500 | I66: TRUE | J66: 1 | K66: 63300 | L66: =J66*K66 -> 63300
A67: Serai | B67: B078 | C67: =VLOOKUP($A67,Master!$B$50:$N$232,8,FALSE) -> 1000 | D67: =VLOOKUP($A67,Master!$B$50:$N$232,9,FALSE) -> gr | E67: =VLOOKUP($A67,Master!$B$50:$N$232,11,FALSE) -> Eden Farm | F67: 0.5 | G67: Kilogram | H67: 11600 | I67: TRUE | J67: 0.5 | K67: 14000 | L67: =J67*K67 -> 7000
A68: Buncis | B68: B144 | C68: =VLOOKUP($A68,Master!$B$50:$N$232,8,FALSE) -> 1000 | D68: =VLOOKUP($A68,Master!$B$50:$N$232,9,FALSE) -> gr | E68: =VLOOKUP($A68,Master!$B$50:$N$232,11,FALSE) -> Eden Farm | F68: 1 | G68: Kilogram | H68: 21800 | I68: TRUE | J68: 1 | K68: =VLOOKUP($A68,Master!$B$50:$N$232,6,FALSE) -> 24000 | L68: 12600
A69: Jagung Manis Kupas | B69: B156 | C69: =VLOOKUP($A69,Master!$B$50:$N$232,8,FALSE) -> #N/A | D69: =VLOOKUP($A69,Master!$B$50:$N$232,9,FALSE) -> #N/A | E69: =VLOOKUP($A69,Master!$B$50:$N$232,11,FALSE) -> #N/A | F69: 0.5 | G69: Kilogram | H69: 9700 | I69: TRUE | J69: 0.5 | K69: =VLOOKUP($A69,Master!$B$50:$N$232,6,FALSE) -> #N/A | L69: 4150
A70: Telur Ayam | B70: B037 | C70: =VLOOKUP($A70,Master!$B$50:$N$232,8,FALSE) -> 15 | D70: =VLOOKUP($A70,Master!$B$50:$N$232,9,FALSE) -> pcs | E70: =VLOOKUP($A70,Master!$B$50:$N$232,11,FALSE) -> Feri Supriadi (Telur , Beras , Minyak ) | F70: 3 | G70: Kilogram | H70: 84000 | I70: TRUE | J70: 3 | K70: 30000 | L70: =J70*K70 -> 90000
A71: Gas 12 Kg | B71: B186 | C71: =VLOOKUP($A71,Master!$B$50:$N$240,8,FALSE) -> #N/A | D71: =VLOOKUP($A71,Master!$B$50:$N$240,9,FALSE) -> #N/A | E71: Limas Raga Inti | F71: 2 | G71: Tabung | H71: 436000 | I71: TRUE | J71: 2 | K71: =VLOOKUP($A71,Master!$B$50:$N$240,6,FALSE) -> #N/A | L71: =J71*K71 -> #N/A
A72: Mayonaise Maestro | B72: B054 | C72: =VLOOKUP($A72,Master!$B$50:$N$232,8,FALSE) -> #N/A | D72: =VLOOKUP($A72,Master!$B$50:$N$232,9,FALSE) -> #N/A | E72: =VLOOKUP($A72,Master!$B$50:$N$232,11,FALSE) -> #N/A | F72: 1 | G72: Pack | H72: 27500 | I72: TRUE | K72: =VLOOKUP($A72,Master!$B$50:$N$232,6,FALSE) -> #N/A | L72: =J72*K72 -> #N/A | M72: Tdk jadi PO
A73: Tahu | B73: B073 | C73: =VLOOKUP($A73,Master!$B$50:$N$232,8,FALSE) -> 10 | D73: =VLOOKUP($A73,Master!$B$50:$N$232,9,FALSE) -> unit | E73: =VLOOKUP($A73,Master!$B$50:$N$232,11,FALSE) -> Toko Lain | F73: 5 | G73: Pack | H73: 39000 | I73: TRUE | J73: 5 | K73: =VLOOKUP($A73,Master!$B$50:$N$232,6,FALSE) -> 8000 | L73: 35000
F75: 44809 | J75: =F75+1 -> 44810
F76: Total PO | H76: =SUM(H78:H132) -> 5907502 | J76: Data Aktual | L76: =SUM(L78:L132) -> #N/A
A77: Remark | B77: Kode | C77: Qty/pack | D77: Unit | E77: toko | F77: PO Pack | G77: Unit Pack | H77: PO Bill | I77: Checker | J77: Bought | K77: Price/Pack | L77: Bill | M77: Keterangan
A78: Sedotan Steril Hitam | B78: B128 | C78: =VLOOKUP($A78,Master!$B$50:$N$232,8,FALSE) -> 300 | D78: =VLOOKUP($A78,Master!$B$50:$N$232,9,FALSE) -> pcs | E78: =VLOOKUP($A78,Master!$B$50:$N$232,11,FALSE) -> Kurnia Mas | F78: 2 | G78: Pack | H78: 60000 | I78: TRUE | J78: 2 | K78: =VLOOKUP($A78,Master!$B$50:$N$232,6,FALSE) -> 30000 | L78: =J78*K78 -> 60000 | M78: KurniaMas
A79: Arghani Chocolate Mixing | B79: B180 | C79: =VLOOKUP($A79,Master!$B$50:$N$232,8,FALSE) -> #N/A | D79: =VLOOKUP($A79,Master!$B$50:$N$232,9,FALSE) -> #N/A | E79: =VLOOKUP($A79,Master!$B$50:$N$232,11,FALSE) -> #N/A | F79: 2 | G79: Kilogram | H79: 260000 | I79: TRUE | J79: 2 | K79: =VLOOKUP($A79,Master!$B$50:$N$232,6,FALSE) -> #N/A | L79: =J79*K79 -> #N/A | M79: Dtg 10/9/22
A80: Beef Topside | B80: B032 | C80: =VLOOKUP($A80,Master!$B$50:$N$232,8,FALSE) -> 1000 | D80: =VLOOKUP($A80,Master!$B$50:$N$232,9,FALSE) -> gr | E80: =VLOOKUP($A80,Master!$B$50:$N$232,11,FALSE) -> BISS (Topside) | F80: 1 | G80: Kilogram | H80: 145000 | I80: TRUE | J80: 1 | K80: =VLOOKUP($A80,Master!$B$50:$N$232,6,FALSE) -> 145000 | L80: 130000 | M80: Prima
A81: Pocky Choco Stick | B81: B018 | C81: =VLOOKUP($A81,Master!$B$50:$N$232,8,FALSE) -> 20 | D81: =VLOOKUP($A81,Master!$B$50:$N$232,9,FALSE) -> pcs | E81: =VLOOKUP($A81,Master!$B$50:$N$232,11,FALSE) -> Kurnia Mas | F81: 4 | G81: Pack | H81: 29200 | I81: TRUE | J81: 4 | K81: =VLOOKUP($A81,Master!$B$50:$N$232,6,FALSE) -> 8500 | L81: =J81*K81 -> 34000 | M81: KurniaMas
A82: Orange Sunkist Fruit | B82: B029 | C82: =VLOOKUP($A82,Master!$B$50:$N$232,8,FALSE) -> 1000 | D82: =VLOOKUP($A82,Master!$B$50:$N$232,9,FALSE) -> gr | E82: =VLOOKUP($A82,Master!$B$50:$N$232,11,FALSE) -> Borma | F82: 1 | G82: Kilogram | H82: 31900 | I82: TRUE | J82: 1 | K82: =VLOOKUP($A82,Master!$B$50:$N$232,6,FALSE) -> 35550 | L82: 31098
A83: Chocolate Mariza Topping | B83: B065 | C83: =VLOOKUP($A83,Master!$B$50:$N$232,8,FALSE) -> #N/A | D83: =VLOOKUP($A83,Master!$B$50:$N$232,9,FALSE) -> #N/A | E83: =VLOOKUP($A83,Master!$B$50:$N$232,11,FALSE) -> #N/A | F83: 1 | G83: Bottle | H83: 27950 | I83: TRUE | J83: 1 | K83: =VLOOKUP($A83,Master!$B$50:$N$232,6,FALSE) -> #N/A | L83: 26000 | M83: KurniaMas
A84: Soda Kue Koepoe | B84: B076 | C84: =VLOOKUP($A84,Master!$B$50:$N$232,8,FALSE) -> #N/A | D84: =VLOOKUP($A84,Master!$B$50:$N$232,9,FALSE) -> #N/A | E84: =VLOOKUP($A84,Master!$B$50:$N$232,11,FALSE) -> #N/A | F84: 1 | G84: Bottle | H84: 5000 | I84: TRUE | J84: 1 | K84: =VLOOKUP($A84,Master!$B$50:$N$232,6,FALSE) -> #N/A | L84: =J84*K84 -> #N/A
A85: Leaf Dill | B85: B105 | C85: =VLOOKUP($A85,Master!$B$50:$N$232,8,FALSE) -> #N/A | D85: =VLOOKUP($A85,Master!$B$50:$N$232,9,FALSE) -> #N/A | E85: =VLOOKUP($A85,Master!$B$50:$N$232,11,FALSE) -> #N/A | F85: 1 | G85: Pack | H85: 5950 | I85: TRUE | J85: 3 | K85: =VLOOKUP($A85,Master!$B$50:$N$232,6,FALSE) -> #N/A | L85: 16065 | M85: Yogya
A86: Pocky Strawberry Stick | B86: B115 | C86: =VLOOKUP($A86,Master!$B$50:$N$232,8,FALSE) -> 20 | D86: =VLOOKUP($A86,Master!$B$50:$N$232,9,FALSE) -> pcs | E86: =VLOOKUP($A86,Master!$B$50:$N$232,11,FALSE) -> Borma | F86: 1 | G86: Pack | H86: 7600 | I86: TRUE | J86: 1 | K86: 7871 | L86: =J86*K86 -> 7871
A87: Pledge Pembersih Kayu | B87: B178 | C87: =VLOOKUP($A87,Master!$B$50:$N$232,8,FALSE) -> #N/A | D87: =VLOOKUP($A87,Master!$B$50:$N$232,9,FALSE) -> #N/A | E87: =VLOOKUP($A87,Master!$B$50:$N$232,11,FALSE) -> #N/A | F87: 1 | G87: Pack | H87: 19650 | I87: TRUE | J87: 1 | K87: =VLOOKUP($A87,Master!$B$50:$N$232,6,FALSE) -> #N/A | L87: 19454
A88: Green Tea Powder Dillco | B88: B015 | C88: =VLOOKUP($A88,Master!$B$50:$N$232,8,FALSE) -> #N/A | D88: =VLOOKUP($A88,Master!$B$50:$N$232,9,FALSE) -> #N/A | E88: =VLOOKUP($A88,Master!$B$50:$N$232,11,FALSE) -> #N/A | F88: 2 | G88: Pack | H88: 340000 | I88: TRUE | J88: 2 | K88: =VLOOKUP($A88,Master!$B$50:$N$232,6,FALSE) -> #N/A | L88: =J88*K88 -> #N/A | M88: Dtg 7/9/22
A89: Powder Chocolate Origin Andalas | B89: B016 | C89: =VLOOKUP($A89,Master!$B$50:$N$232,8,FALSE) -> #N/A | D89: =VLOOKUP($A89,Master!$B$50:$N$232,9,FALSE) -> #N/A | E89: =VLOOKUP($A89,Master!$B$50:$N$232,11,FALSE) -> #N/A | F89: 2 | G89: Pack | H89: 440000 | I89: TRUE | J89: 2 | K89: =VLOOKUP($A89,Master!$B$50:$N$232,6,FALSE) -> #N/A | L89: =J89*K89 -> #N/A | M89: Dtg 7/9/22
A90: Wortel Grade A | B90: B035 | C90: =VLOOKUP($A90,Master!$B$50:$N$232,8,FALSE) -> 1000 | D90: =VLOOKUP($A90,Master!$B$50:$N$232,9,FALSE) -> gr | E90: =VLOOKUP($A90,Master!$B$50:$N$232,11,FALSE) -> Eden Farm | F90: 1 | G90: Kilogram | H90: 10200 | I90: TRUE | J90: 1 | K90: 10400 | L90: =J90*K90 -> 10400
A91: Cabe kering | B91: B039 | C91: =VLOOKUP($A91,Master!$B$50:$N$232,8,FALSE) -> 1000 | D91: =VLOOKUP($A91,Master!$B$50:$N$232,9,FALSE) -> gr | E91: =VLOOKUP($A91,Master!$B$50:$N$232,11,FALSE) -> Eden Farm | F91: 1 | G91: Kilogram | H91: 102600 | I91: TRUE | J91: 1 | K91: 109000 | L91: =J91*K91 -> 109000
A92: Jamur Champignon | B92: B051 | C92: =VLOOKUP($A92,Master!$B$50:$N$232,8,FALSE) -> 1000 | D92: =VLOOKUP($A92,Master!$B$50:$N$232,9,FALSE) -> gr | E92: =VLOOKUP($A92,Master!$B$50:$N$232,11,FALSE) -> Eden Farm | F92: 2 | G92: Kilogram | H92: 41700 | I92: TRUE | J92: 2 | K92: 44000 | L92: =J92*K92 -> 88000
A93: Tomato Cherry | B93: B109 | C93: =VLOOKUP($A93,Master!$B$50:$N$232,8,FALSE) -> 1000 | D93: =VLOOKUP($A93,Master!$B$50:$N$232,9,FALSE) -> gr | E93: =VLOOKUP($A93,Master!$B$50:$N$232,11,FALSE) -> Eden Farm | F93: 1 | G93: Pack | H93: 39900 | I93: TRUE | J93: 1 | K93: =VLOOKUP($A93,Master!$B$50:$N$232,6,FALSE) -> 50000 | L93: 33600
A94: Buncis | B94: B144 | C94: =VLOOKUP($A94,Master!$B$50:$N$232,8,FALSE) -> 1000 | D94: =VLOOKUP($A94,Master!$B$50:$N$232,9,FALSE) -> gr | E94: =VLOOKUP($A94,Master!$B$50:$N$232,11,FALSE) -> Eden Farm | F94: 1 | G94: Kilogram | H94: 21800 | I94: TRUE | J94: 1 | K94: =VLOOKUP($A94,Master!$B$50:$N$232,6,FALSE) -> 24000 | L94: 14600
A95: Jagung Manis Kupas | B95: B156 | C95: =VLOOKUP($A95,Master!$B$50:$N$232,8,FALSE) -> #N/A | D95: =VLOOKUP($A95,Master!$B$50:$N$232,9,FALSE) -> #N/A | E95: =VLOOKUP($A95,Master!$B$50:$N$232,11,FALSE) -> #N/A | F95: 0.5 | G95: Kilogram | H95: 9700 | I95: TRUE | J95: 0.5 | K95: =VLOOKUP($A95,Master!$B$50:$N$232,6,FALSE) -> #N/A | L95: 4550
A96: Bawang Bombay | B96: B055 | C96: =VLOOKUP($A96,Master!$B$50:$N$232,8,FALSE) -> 1000 | D96: =VLOOKUP($A96,Master!$B$50:$N$232,9,FALSE) -> gr | E96: =VLOOKUP($A96,Master!$B$50:$N$232,11,FALSE) -> Eden Farm | F96: 2 | G96: Kilogram | H96: 39800 | I96: TRUE | J96: 2 | K96: 21200 | L96: =J96*K96 -> 42400
A97: Telur Ayam | B97: B037 | C97: =VLOOKUP($A97,Master!$B$50:$N$232,8,FALSE) -> 15 | D97: =VLOOKUP($A97,Master!$B$50:$N$232,9,FALSE) -> pcs | E97: =VLOOKUP($A97,Master!$B$50:$N$232,11,FALSE) -> Feri Supriadi (Telur , Beras , Minyak ) | F97: 3 | G97: Kilogram | H97: 84000 | I97: TRUE | J97: 3 | K97: 29000 | L97: =J97*K97 -> 87000
A98: Arabika Espresso | B98: B158 | C98: =VLOOKUP($A98,Master!$B$50:$N$232,8,FALSE) -> #N/A | D98: =VLOOKUP($A98,Master!$B$50:$N$232,9,FALSE) -> #N/A | E98: =VLOOKUP($A98,Master!$B$50:$N$232,11,FALSE) -> #N/A | F98: 3 | G98: Kilogram | H98: 525000 | I98: TRUE | J98: 3 | K98: =VLOOKUP($A98,Master!$B$50:$N$232,6,FALSE) -> #N/A | L98: =J98*K98 -> #N/A | M98: Dtg 7/9/22
A99: Ayam Sayap | B99: B038 | C99: =VLOOKUP($A99,Master!$B$50:$N$232,8,FALSE) -> 1000 | D99: =VLOOKUP($A99,Master!$B$50:$N$232,9,FALSE) -> gr | E99: =VLOOKUP($A99,Master!$B$50:$N$232,11,FALSE) -> Toko Lain | F99: 3 | G99: Kilogram | H99: 133500 | I99: TRUE | J99: 3 | K99: =VLOOKUP($A99,Master!$B$50:$N$232,6,FALSE) -> 45000 | L99: 105000
A100: Cireng | B100: B041 | C100: =VLOOKUP($A100,Master!$B$50:$N$232,8,FALSE) -> 20 | D100: =VLOOKUP($A100,Master!$B$50:$N$232,9,FALSE) -> unit | E100: =VLOOKUP($A100,Master!$B$50:$N$232,11,FALSE) -> RSB, Dago | F100: 15 | G100: Pack | H100: 90000 | I100: TRUE | J100: 10 | K100: =VLOOKUP($A100,Master!$B$50:$N$232,6,FALSE) -> 13500 | L100: =J100*K100 -> 135000
A101: Ragi Fermipan | B101: B099 | C101: =VLOOKUP($A101,Master!$B$50:$N$232,8,FALSE) -> 10 | D101: =VLOOKUP($A101,Master!$B$50:$N$232,9,FALSE) -> sachet | E101: =VLOOKUP($A101,Master!$B$50:$N$232,11,FALSE) -> Pasar Cihapit | F101: 1 | G101: Pack | H101: 22000 | I101: TRUE | J101: 1 | K101: =VLOOKUP($A101,Master!$B$50:$N$232,6,FALSE) -> 22000 | L101: 18000 | M101: KurniaMas
A102: Gulaku Premium Hijau | B102: B001 | C102: =VLOOKUP($A102,Master!$B$50:$N$232,8,FALSE) -> #N/A | D102: =VLOOKUP($A102,Master!$B$50:$N$232,9,FALSE) -> #N/A | E102: =VLOOKUP($A102,Master!$B$50:$N$232,11,FALSE) -> #N/A | F102: 2 | G102: Kilogram | H102: 28000 | I102: TRUE | J102: 2 | K102: 14250 | L102: =J102*K102 -> 28500
A103: Evaporasi FN | B103: B003 | C103: =VLOOKUP($A103,Master!$B$50:$N$232,8,FALSE) -> #N/A | D103: =VLOOKUP($A103,Master!$B$50:$N$232,9,FALSE) -> #N/A | E103: =VLOOKUP($A103,Master!$B$50:$N$232,11,FALSE) -> #N/A | F103: 4 | G103: Can | H103: 64000 | I103: TRUE | J103: 4 | K103: =VLOOKUP($A103,Master!$B$50:$N$232,6,FALSE) -> #N/A | L103: =J103*K103 -> #N/A
A104: SKM Carnation | B104: B031 | C104: =VLOOKUP($A104,Master!$B$50:$N$232,8,FALSE) -> #N/A | D104: =VLOOKUP($A104,Master!$B$50:$N$232,9,FALSE) -> #N/A | E104: =VLOOKUP($A104,Master!$B$50:$N$232,11,FALSE) -> #N/A | F104: 8 | G104: Can | H104: 88000 | I104: TRUE | J104: 8 | K104: =VLOOKUP($A104,Master!$B$50:$N$232,6,FALSE) -> #N/A | L104: =J104*K104 -> #N/A
...

Sheet History Juli 2022
A1: History Juli 2022
A2: The Soko Coffee Tea Chocolate
F5: 44743 | J5: =F5+1 -> 44744
F6: Total PO | H6: =SUM(H8:H136) -> 915147484 | J6: Data Aktual | L6: =SUM(L8:L136) -> #N/A
A7: Remark | B7: Kode | C7: Qty/pack | D7: Unit | E7: toko | F7: PO Pack | G7: Unit Pack | H7: PO Bill | I7: Checker | J7: Bought | K7: Price/Pack | L7: Bill | M7: Keterangan
A8: Arghani Chocolate Mixing | B8: B180 | C8: =VLOOKUP($A8,Master!$B$50:$N$232,8,FALSE) -> #N/A | D8: =VLOOKUP($A8,Master!$B$50:$N$232,9,FALSE) -> #N/A | E8: =VLOOKUP($A8,Master!$B$50:$N$232,11,FALSE) -> #N/A | F8: 2 | G8: Kilogram | H8: 260000 | I8: TRUE | J8: 2 | K8: =VLOOKUP($A8,Master!$B$50:$N$232,6,FALSE) -> #N/A | L8: =J8*K8 -> #N/A
A9: Gula Merah / Aren Bubuk Saset | B9: B034 | C9: =VLOOKUP($A9,Master!$B$50:$N$232,8,FALSE) -> 250 | D9: =VLOOKUP($A9,Master!$B$50:$N$232,9,FALSE) -> pcs | E9: =VLOOKUP($A9,Master!$B$50:$N$232,11,FALSE) -> Kurnia Mas | F9: 2 | G9: Bag | H9: 85000 | I9: TRUE | J9: 2 | K9: 65000 | L9: =J9*K9 -> 130000
A10: Beef Topside | B10: B032 | C10: =VLOOKUP($A10,Master!$B$50:$N$232,8,FALSE) -> 1000 | D10: =VLOOKUP($A10,Master!$B$50:$N$232,9,FALSE) -> gr | E10: =VLOOKUP($A10,Master!$B$50:$N$232,11,FALSE) -> BISS (Topside) | F10: 1 | G10: Kilogram | H10: 145000 | I10: TRUE | J10: 1 | K10: =VLOOKUP($A10,Master!$B$50:$N$232,6,FALSE) -> 145000 | L10: 130000 | M10: Urgent
A11: Pocky Choco Stick | B11: B018 | C11: =VLOOKUP($A11,Master!$B$50:$N$232,8,FALSE) -> 20 | D11: =VLOOKUP($A11,Master!$B$50:$N$232,9,FALSE) -> pcs | E11: =VLOOKUP($A11,Master!$B$50:$N$232,11,FALSE) -> Kurnia Mas | F11: 3 | G11: Pack | H11: 21900 | I11: TRUE | J11: 3 | K11: =VLOOKUP($A11,Master!$B$50:$N$232,6,FALSE) -> 8500 | L11: 23612
A12: Orange Sunkist Fruit | B12: B029 | C12: =VLOOKUP($A12,Master!$B$50:$N$232,8,FALSE) -> 1000 | D12: =VLOOKUP($A12,Master!$B$50:$N$232,9,FALSE) -> gr | E12: =VLOOKUP($A12,Master!$B$50:$N$232,11,FALSE) -> Borma | F12: 0.5 | G12: Kilogram | H12: 31900 | I12: TRUE | J12: 0.75 | K12: =VLOOKUP($A12,Master!$B$50:$N$232,6,FALSE) -> 35550 | L12: 18761
A13: Lemon Fruit | B13: B030 | C13: =VLOOKUP($A13,Master!$B$50:$N$232,8,FALSE) -> 1000 | D13: =VLOOKUP($A13,Master!$B$50:$N$232,9,FALSE) -> gr | E13: =VLOOKUP($A13,Master!$B$50:$N$232,11,FALSE) -> Borma | F13: 1 | G13: Kilogram | H13: 16000 | I13: TRUE | J13: 1 | K13: =VLOOKUP($A13,Master!$B$50:$N$232,6,FALSE) -> 18000 | L13: 15000
A14: Pocky Strawberry Stick | B14: B115 | C14: =VLOOKUP($A14,Master!$B$50:$N$232,8,FALSE) -> 20 | D14: =VLOOKUP($A14,Master!$B$50:$N$232,9,FALSE) -> pcs | E14: =VLOOKUP($A14,Master!$B$50:$N$232,11,FALSE) -> Borma | F14: 2 | G14: Pack | H14: 15100 | I14: FALSE | K14: =VLOOKUP($A14,Master!$B$50:$N$232,6,FALSE) -> 8500 | L14: =J14*K14 -> 0
A15: Pineapple Juice Jungle Diamond | B15: B119 | C15: =VLOOKUP($A15,Master!$B$50:$N$232,8,FALSE) -> #N/A | D15: =VLOOKUP($A15,Master!$B$50:$N$232,9,FALSE) -> #N/A | E15: =VLOOKUP($A15,Master!$B$50:$N$232,11,FALSE) -> #N/A | F15: 1 | G15: Bottle | H15: 27000 | I15: TRUE | J15: 1 | K15: =VLOOKUP($A15,Master!$B$50:$N$232,6,FALSE) -> #N/A | L15: 23400
A16: Stella Pengharum Ruangan | B16: B153 | C16: =VLOOKUP($A16,Master!$B$50:$N$232,8,FALSE) -> #N/A | D16: =VLOOKUP($A16,Master!$B$50:$N$232,9,FALSE) -> #N/A | E16: =VLOOKUP($A16,Master!$B$50:$N$232,11,FALSE) -> #N/A | F16: 1 | G16: Can | H16: 32200 | I16: TRUE | J16: 1 | K16: =VLOOKUP($A16,Master!$B$50:$N$232,6,FALSE) -> #N/A | L16: 55700
A17: Tissue Roll | B17: B179 | C17: =VLOOKUP($A17,Master!$B$50:$N$232,8,FALSE) -> #N/A | D17: =VLOOKUP($A17,Master!$B$50:$N$232,9,FALSE) -> #N/A | E17: =VLOOKUP($A17,Master!$B$50:$N$232,11,FALSE) -> #N/A | F17: 2 | G17: Pack | H17: 9600 | I17: TRUE | J17: 4 | K17: =VLOOKUP($A17,Master!$B$50:$N$232,6,FALSE) -> #N/A | L17: 36800
A18: Green Tea Powder Dillco | B18: B015 | C18: =VLOOKUP($A18,Master!$B$50:$N$232,8,FALSE) -> #N/A | D18: =VLOOKUP($A18,Master!$B$50:$N$232,9,FALSE) -> #N/A | E18: =VLOOKUP($A18,Master!$B$50:$N$232,11,FALSE) -> #N/A | F18: 2 | G18: Pack | H18: 340000 | I18: FALSE | K18: =VLOOKUP($A18,Master!$B$50:$N$232,6,FALSE) -> #N/A | L18: =J18*K18 -> #N/A
A19: Powder Chocolate Origin Andalas | B19: B016 | C19: =VLOOKUP($A19,Master!$B$50:$N$232,8,FALSE) -> #N/A | D19: =VLOOKUP($A19,Master!$B$50:$N$232,9,FALSE) -> #N/A | E19: =VLOOKUP($A19,Master!$B$50:$N$232,11,FALSE) -> #N/A | F19: 2 | G19: Pack | H19: 440000 | I19: FALSE | K19: =VLOOKUP($A19,Master!$B$50:$N$232,6,FALSE) -> #N/A | L19: =J19*K19 -> #N/A
A20: Wortel Grade A | B20: B035 | C20: =VLOOKUP($A20,Master!$B$50:$N$232,8,FALSE) -> 1000 | D20: =VLOOKUP($A20,Master!$B$50:$N$232,9,FALSE) -> gr | E20: =VLOOKUP($A20,Master!$B$50:$N$232,11,FALSE) -> Eden Farm | F20: 2 | G20: Kilogram | H20: 19400 | I20: TRUE | J20: 2 | K20: =VLOOKUP($A20,Master!$B$50:$N$232,6,FALSE) -> 18000 | L20: 24000 | M20: Urgent
A21: Ayam Boneless Dada | B21: B036 | C21: =VLOOKUP($A21,Master!$B$50:$N$232,8,FALSE) -> 1000 | D21: =VLOOKUP($A21,Master!$B$50:$N$232,9,FALSE) -> gr | E21: =VLOOKUP($A21,Master!$B$50:$N$232,11,FALSE) -> Toko Lain | F21: 3 | G21: Kilogram | H21: 146700 | I21: TRUE | J21: 3.24 | K21: =VLOOKUP($A21,Master!$B$50:$N$232,6,FALSE) -> 50000 | L21: 168739 | M21: Urgent
A22: Bawang Putih | B22: B050 | C22: =VLOOKUP($A22,Master!$B$50:$N$232,8,FALSE) -> 1000 | D22: =VLOOKUP($A22,Master!$B$50:$N$232,9,FALSE) -> gr | E22: =VLOOKUP($A22,Master!$B$50:$N$232,11,FALSE) -> Eden Farm | F22: 3 | G22: Kilogram | H22: 72600 | I22: TRUE | J22: 3 | K22: =VLOOKUP($A22,Master!$B$50:$N$232,6,FALSE) -> 40000 | L22: 90000 | M22: Urgent
A23: Jamur Champignon | B23: B051 | C23: =VLOOKUP($A23,Master!$B$50:$N$232,8,FALSE) -> 1000 | D23: =VLOOKUP($A23,Master!$B$50:$N$232,9,FALSE) -> gr | E23: =VLOOKUP($A23,Master!$B$50:$N$232,11,FALSE) -> Eden Farm | F23: 2 | G23: Kilogram | H23: 83400 | I23: TRUE | J23: 2 | K23: =VLOOKUP($A23,Master!$B$50:$N$232,6,FALSE) -> 45000 | L23: 80000 | M23: Urgent
A24: Bawang Bombay | B24: B055 | C24: =VLOOKUP($A24,Master!$B$50:$N$232,8,FALSE) -> 1000 | D24: =VLOOKUP($A24,Master!$B$50:$N$232,9,FALSE) -> gr | E24: =VLOOKUP($A24,Master!$B$50:$N$232,11,FALSE) -> Eden Farm | F24: 5 | G24: Kilogram | H24: 94500 | I24: TRUE | J24: 5 | K24: =VLOOKUP($A24,Master!$B$50:$N$232,6,FALSE) -> 40000 | L24: 150000 | M24: Urgent
A25: Paprika Green | B25: B058 | C25: =VLOOKUP($A25,Master!$B$50:$N$232,8,FALSE) -> 1000 | D25: =VLOOKUP($A25,Master!$B$50:$N$232,9,FALSE) -> gr | E25: =VLOOKUP($A25,Master!$B$50:$N$232,11,FALSE) -> Eden Farm | F25: 0.5 | G25: Kilogram | H25: 44900 | I25: TRUE | J25: 1 | K25: =VLOOKUP($A25,Master!$B$50:$N$232,6,FALSE) -> 58600 | L25: 39000 | M25: Urgent
A26: Strawberry Fruit | B26: B069 | C26: =VLOOKUP($A26,Master!$B$50:$N$232,8,FALSE) -> 500 | D26: =VLOOKUP($A26,Master!$B$50:$N$232,9,FALSE) -> gr | E26: =VLOOKUP($A26,Master!$B$50:$N$232,11,FALSE) -> Toko Lain | F26: 2 | G26: Pack | H26: 15400 | I26: TRUE | J26: 1 | K26: =VLOOKUP($A26,Master!$B$50:$N$232,6,FALSE) -> 25000 | L26: 50000 | M26: Urgent
A27: Tahu | B27: B073 | C27: =VLOOKUP($A27,Master!$B$50:$N$232,8,FALSE) -> 10 | D27: =VLOOKUP($A27,Master!$B$50:$N$232,9,FALSE) -> unit | E27: =VLOOKUP($A27,Master!$B$50:$N$232,11,FALSE) -> Toko Lain | F27: 15 | G27: Pack | H27: 117000 | I27: TRUE | J27: 15 | K27: =105000/15 -> 7000 | L27: =J27*K27 -> 105000 | M27: Urgent
A28: Tomato Cherry | B28: B109 | C28: =VLOOKUP($A28,Master!$B$50:$N$232,8,FALSE) -> 1000 | D28: =VLOOKUP($A28,Master!$B$50:$N$232,9,FALSE) -> gr | E28: =VLOOKUP($A28,Master!$B$50:$N$232,11,FALSE) -> Eden Farm | F28: 1 | G28: Pack | H28: 39900 | I28: TRUE | J28: 1 | K28: =VLOOKUP($A28,Master!$B$50:$N$232,6,FALSE) -> 50000 | L28: 40000 | M28: Urgent
A29: Kol Ungu | B29: B110 | C29: =VLOOKUP($A29,Master!$B$50:$N$232,8,FALSE) -> 400 | D29: =VLOOKUP($A29,Master!$B$50:$N$232,9,FALSE) -> gr | E29: =VLOOKUP($A29,Master!$B$50:$N$232,11,FALSE) -> Eden Farm | F29: 0.5 | G29: Kilogram | H29: 32100 | I29: TRUE | J29: 1 | K29: =VLOOKUP($A29,Master!$B$50:$N$232,6,FALSE) -> 41400 | L29: 75000 | M29: 3Pcs
A30: Buncis | B30: B144 | C30: =VLOOKUP($A30,Master!$B$50:$N$232,8,FALSE) -> 1000 | D30: =VLOOKUP($A30,Master!$B$50:$N$232,9,FALSE) -> gr | E30: =VLOOKUP($A30,Master!$B$50:$N$232,11,FALSE) -> Eden Farm | F30: 1 | G30: Kilogram | H30: 21800 | I30: TRUE | J30: 1 | K30: =VLOOKUP($A30,Master!$B$50:$N$232,6,FALSE) -> 24000 | L30: 20000 | M30: Urgent
A31: Jagung Manis Kupas | B31: B156 | C31: =VLOOKUP($A31,Master!$B$50:$N$232,8,FALSE) -> #N/A | D31: =VLOOKUP($A31,Master!$B$50:$N$232,9,FALSE) -> #N/A | E31: =VLOOKUP($A31,Master!$B$50:$N$232,11,FALSE) -> #N/A | F31: 1 | G31: Kilogram | H31: 9500 | I31: TRUE | J31: 1 | K31: =VLOOKUP($A31,Master!$B$50:$N$232,6,FALSE) -> #N/A | L31: 12000 | M31: Urgent
A32: Telur Ayam | B32: B037 | C32: =VLOOKUP($A32,Master!$B$50:$N$232,8,FALSE) -> 15 | D32: =VLOOKUP($A32,Master!$B$50:$N$232,9,FALSE) -> pcs | E32: =VLOOKUP($A32,Master!$B$50:$N$232,11,FALSE) -> Feri Supriadi (Telur , Beras , Minyak ) | F32: 5 | G32: Kilogram | H32: 137500 | I32: TRUE | J32: 15 | K32: =VLOOKUP($A32,Master!$B$50:$N$232,6,FALSE) -> 28000 | L32: 409500 | M32: Urgent
A33: Beras Rojo Lele | B33: B062 | C33: =VLOOKUP($A33,Master!$B$50:$N$232,8,FALSE) -> 25000 | D33: =VLOOKUP($A33,Master!$B$50:$N$232,9,FALSE) -> gr | E33: =VLOOKUP($A33,Master!$B$50:$N$232,11,FALSE) -> Feri Supriadi (Telur , Beras , Minyak ) | F33: 25 | G33: Kilogram | H33: 290000 | I33: TRUE | J33: 25 | K33: =VLOOKUP($A33,Master!$B$50:$N$232,6,FALSE) -> 364000 | L33: 288000 | M33: Urgent
A34: Ayam Sayap | B34: B038 | C34: =VLOOKUP($A34,Master!$B$50:$N$232,8,FALSE) -> 1000 | D34: =VLOOKUP($A34,Master!$B$50:$N$232,9,FALSE) -> gr | E34: =VLOOKUP($A34,Master!$B$50:$N$232,11,FALSE) -> Toko Lain | F34: 3 | G34: Kilogram | H34: 133500 | I34: TRUE | J34: 3.84 | K34: =VLOOKUP($A34,Master!$B$50:$N$232,6,FALSE) -> 45000 | L34: 123051
A35: Cireng | B35: B041 | C35: =VLOOKUP($A35,Master!$B$50:$N$232,8,FALSE) -> 20 | D35: =VLOOKUP($A35,Master!$B$50:$N$232,9,FALSE) -> unit | E35: =VLOOKUP($A35,Master!$B$50:$N$232,11,FALSE) -> RSB, Dago | F35: 15 | G35: Pack | H35: 90000 | I35: TRUE | J35: 15 | K35: =VLOOKUP($A35,Master!$B$50:$N$232,6,FALSE) -> 13500 | L35: =J35*K35 -> 202500
A36: Oyster Sauce Panda | B36: B056 | C36: =VLOOKUP($A36,Master!$B$50:$N$232,8,FALSE) -> 700 | D36: =VLOOKUP($A36,Master!$B$50:$N$232,9,FALSE) -> gr | E36: =VLOOKUP($A36,Master!$B$50:$N$232,11,FALSE) -> Kurnia Mas | F36: 1 | G36: Bottle | H36: 46000 | I36: TRUE | J36: 1 | K36: =VLOOKUP($A36,Master!$B$50:$N$232,6,FALSE) -> 52500 | L36: 53955
A37: Ayam Cincang | B37: B095 | C37: =VLOOKUP($A37,Master!$B$50:$N$232,8,FALSE) -> 1000 | D37: =VLOOKUP($A37,Master!$B$50:$N$232,9,FALSE) -> gr | E37: =VLOOKUP($A37,Master!$B$50:$N$232,11,FALSE) -> Pasar Cihapit | F37: 0.3 | G37: Kilogram | H37: 69000 | I37: TRUE | J37: 0.3 | K37: =VLOOKUP($A37,Master!$B$50:$N$232,6,FALSE) -> 69000 | L37: 18701
A38: Daging Cincang | B38: B096 | C38: =VLOOKUP($A38,Master!$B$50:$N$232,8,FALSE) -> 1000 | D38: =VLOOKUP($A38,Master!$B$50:$N$232,9,FALSE) -> gr | E38: =VLOOKUP($A38,Master!$B$50:$N$232,11,FALSE) -> Pasar Cihapit | F38: 0.5 | G38: Kilogram | H38: 148500 | I38: TRUE | J38: 0.514 | K38: =VLOOKUP($A38,Master!$B$50:$N$232,6,FALSE) -> 156222 | L38: 94319
A39: Gulaku Premium Hijau | B39: B001 | C39: =VLOOKUP($A39,Master!$B$50:$N$232,8,FALSE) -> #N/A | D39: =VLOOKUP($A39,Master!$B$50:$N$232,9,FALSE) -> #N/A | E39: =VLOOKUP($A39,Master!$B$50:$N$232,11,FALSE) -> #N/A | F39: 2 | G39: Kilogram | H39: 28000 | I39: TRUE | J39: 2 | K39: =VLOOKUP($A39,Master!$B$50:$N$232,6,FALSE) -> #N/A | L39: =J39*K39 -> #N/A
A40: Evaporasi FN | B40: B003 | C40: =VLOOKUP($A40,Master!$B$50:$N$232,8,FALSE) -> #N/A | D40: =VLOOKUP($A40,Master!$B$50:$N$232,9,FALSE) -> #N/A | E40: =VLOOKUP($A40,Master!$B$50:$N$232,11,FALSE) -> #N/A | F40: 3 | G40: Can | H40: 48000 | I40: TRUE | J40: 3 | K40: =VLOOKUP($A40,Master!$B$50:$N$232,6,FALSE) -> #N/A | L40: =J40*K40 -> #N/A
A41: SKM Carnation | B41: B031 | C41: =VLOOKUP($A41,Master!$B$50:$N$232,8,FALSE) -> #N/A | D41: =VLOOKUP($A41,Master!$B$50:$N$232,9,FALSE) -> #N/A | E41: =VLOOKUP($A41,Master!$B$50:$N$232,11,FALSE) -> #N/A | F41: 6 | G41: Can | H41: 66000 | I41: TRUE | J41: 6 | K41: =VLOOKUP($A41,Master!$B$50:$N$232,6,FALSE) -> #N/A | L41: =J41*K41 -> #N/A
A42: Gula Merah / Aren Padat Kiloan | B42: B033 | C42: =VLOOKUP($A42,Master!$B$50:$N$232,8,FALSE) -> 1000 | D42: =VLOOKUP($A42,Master!$B$50:$N$232,9,FALSE) -> gr | E42: =VLOOKUP($A42,Master!$B$50:$N$232,11,FALSE) -> PD Aroma Jaya | F42: 1 | G42: Kilogram | H42: 16000 | I42: TRUE | J42: 1 | K42: =VLOOKUP($A42,Master!$B$50:$N$232,6,FALSE) -> 17000 | L42: =J42*K42 -> 17000
A43: Sunquick Lemon | B43: B042 | C43: =VLOOKUP($A43,Master!$B$50:$N$232,8,FALSE) -> #N/A | D43: =VLOOKUP($A43,Master!$B$50:$N$232,9,FALSE) -> #N/A | E43: =VLOOKUP($A43,Master!$B$50:$N$232,11,FALSE) -> #N/A | F43: 3 | G43: Bottle | H43: 90000 | I43: TRUE | J43: 3 | K43: =VLOOKUP($A43,Master!$B$50:$N$232,6,FALSE) -> #N/A | L43: =J43*K43 -> #N/A
A44: Cooking Cream Millac Gold | B44: B044 | C44: =VLOOKUP($A44,Master!$B$50:$N$232,8,FALSE) -> #N/A | D44: =VLOOKUP($A44,Master!$B$50:$N$232,9,FALSE) -> #N/A | E44: =VLOOKUP($A44,Master!$B$50:$N$232,11,FALSE) -> #N/A | F44: 4 | G44: Pack | H44: 250000 | I44: TRUE | J44: 4 | K44: =VLOOKUP($A44,Master!$B$50:$N$232,6,FALSE) -> #N/A | L44: 248000
A45: Dark Chocolate Compound Colatta | B45: B045 | C45: =VLOOKUP($A45,Master!$B$50:$N$232,8,FALSE) -> #N/A | D45: =VLOOKUP($A45,Master!$B$50:$N$232,9,FALSE) -> #N/A | E45: =VLOOKUP($A45,Master!$B$50:$N$232,11,FALSE) -> #N/A | F45: 1 | G45: Pack | H45: 53000 | I45: TRUE | J45: 1 | K45: 56000 | L45: =J45*K45 -> 56000
A46: Tepung Segitiga Biru | B46: B046 | C46: =VLOOKUP($A46,Master!$B$50:$N$232,8,FALSE) -> #N/A | D46: =VLOOKUP($A46,Master!$B$50:$N$232,9,FALSE) -> #N/A | E46: =VLOOKUP($A46,Master!$B$50:$N$232,11,FALSE) -> #N/A | F46: 2 | G46: Pack | H46: 28000 | I46: TRUE | J46: 2 | K46: =VLOOKUP($A46,Master!$B$50:$N$232,6,FALSE) -> #N/A | L46: 27500
A47: Minyak Goreng Sania | B47: B049 | C47: =VLOOKUP($A47,Master!$B$50:$N$232,8,FALSE) -> #N/A | D47: =VLOOKUP($A47,Master!$B$50:$N$232,9,FALSE) -> #N/A | E47: =VLOOKUP($A47,Master!$B$50:$N$232,11,FALSE) -> #N/A | F47: 1 | G47: Dus | H47: 365000 | I47: TRUE | J47: 1 | K47: =VLOOKUP($A47,Master!$B$50:$N$232,6,FALSE) -> #N/A | L47: 350000
A48: Leaf Oregano | B48: B052 | C48: =VLOOKUP($A48,Master!$B$50:$N$232,8,FALSE) -> 100 | D48: =VLOOKUP($A48,Master!$B$50:$N$232,9,FALSE) -> gr | E48: =VLOOKUP($A48,Master!$B$50:$N$232,11,FALSE) -> PD Aroma Jaya | F48: 2 | G48: Pack | H48: 56000 | I48: TRUE | J48: 2 | K48: =VLOOKUP($A48,Master!$B$50:$N$232,6,FALSE) -> 28000 | L48: =J48*K48 -> 56000
A49: Powder Chicken Royco | B49: B060 | C49: =VLOOKUP($A49,Master!$B$50:$N$232,8,FALSE) -> #N/A | D49: =VLOOKUP($A49,Master!$B$50:$N$232,9,FALSE) -> #N/A | E49: =VLOOKUP($A49,Master!$B$50:$N$232,11,FALSE) -> #N/A | F49: 1 | G49: Pack | H49: 38000 | I49: TRUE | J49: 1 | K49: =VLOOKUP($A49,Master!$B$50:$N$232,6,FALSE) -> #N/A | L49: =J49*K49 -> #N/A
A50: Chilli Sauce Delmonte | B50: B064 | C50: =VLOOKUP($A50,Master!$B$50:$N$232,8,FALSE) -> #N/A | D50: =VLOOKUP($A50,Master!$B$50:$N$232,9,FALSE) -> #N/A | E50: =VLOOKUP($A50,Master!$B$50:$N$232,11,FALSE) -> #N/A | F50: 2 | G50: Pack | H50: 39000 | I50: TRUE | J50: 2 | K50: =VLOOKUP($A50,Master!$B$50:$N$232,6,FALSE) -> #N/A | L50: =J50*K50 -> #N/A
A51: Delmonte Tomato | B51: B066 | C51: =VLOOKUP($A51,Master!$B$50:$N$232,8,FALSE) -> #N/A | D51: =VLOOKUP($A51,Master!$B$50:$N$232,9,FALSE) -> #N/A | E51: =VLOOKUP($A51,Master!$B$50:$N$232,11,FALSE) -> #N/A | F51: 6 | G51: Pack | H51: 84000 | I51: TRUE | J51: 6 | K51: =VLOOKUP($A51,Master!$B$50:$N$232,6,FALSE) -> #N/A | L51: =J51*K51 -> #N/A
A52: Leaf Bay | B52: B077 | C52: =VLOOKUP($A52,Master!$B$50:$N$232,8,FALSE) -> 100 | D52: =VLOOKUP($A52,Master!$B$50:$N$232,9,FALSE) -> gr | E52: =VLOOKUP($A52,Master!$B$50:$N$232,11,FALSE) -> PD Aroma Jaya | F52: 1 | G52: Pack | H52: 38000 | I52: TRUE | J52: 1 | K52: =VLOOKUP($A52,Master!$B$50:$N$232,6,FALSE) -> 38000 | L52: =J52*K52 -> 38000
A53: Lada Hitam Biji | B53: B098 | C53: =VLOOKUP($A53,Master!$B$50:$N$232,8,FALSE) -> 500 | D53: =VLOOKUP($A53,Master!$B$50:$N$232,9,FALSE) -> gr | E53: =VLOOKUP($A53,Master!$B$50:$N$232,11,FALSE) -> PD Aroma Jaya | F53: 0.5 | G53: Kilogram | H53: 13000 | I53: TRUE | J53: 5 | K53: =VLOOKUP($A53,Master!$B$50:$N$232,6,FALSE) -> 13000 | L53: =J53*K53 -> 65000
A54: Mozzarella Cheese Perfecto | B54: B100 | C54: =VLOOKUP($A54,Master!$B$50:$N$232,8,FALSE) -> #N/A | D54: =VLOOKUP($A54,Master!$B$50:$N$232,9,FALSE) -> #N/A | E54: =VLOOKUP($A54,Master!$B$50:$N$232,11,FALSE) -> #N/A | F54: 2 | G54: Kilogram | H54: 215000 | I54: TRUE | J54: 2 | K54: =VLOOKUP($A54,Master!$B$50:$N$232,6,FALSE) -> #N/A | L54: =J54*K54 -> #N/A
A55: Lemon Syrup Mardjan 460ml | B55: B121 | C55: =VLOOKUP($A55,Master!$B$50:$N$232,8,FALSE) -> #N/A | D55: =VLOOKUP($A55,Master!$B$50:$N$232,9,FALSE) -> #N/A | E55: =VLOOKUP($A55,Master!$B$50:$N$232,11,FALSE) -> #N/A | F55: 1 | G55: Bottle | H55: 20250 | I55: TRUE | J55: 1 | K55: =VLOOKUP($A55,Master!$B$50:$N$232,6,FALSE) -> #N/A | L55: =J55*K55 -> #N/A
A56: Trash Bag Tulip 80 x 120 (0,6) | B56: B130 | C56: =VLOOKUP($A56,Master!$B$50:$N$232,8,FALSE) -> 12 | D56: =VLOOKUP($A56,Master!$B$50:$N$232,9,FALSE) -> pcs | E56: =VLOOKUP($A56,Master!$B$50:$N$232,11,FALSE) -> PD Aroma Jaya | F56: 2 | G56: Pack | H56: 44000 | I56: TRUE | J56: 2 | K56: =VLOOKUP($A56,Master!$B$50:$N$232,6,FALSE) -> 18000 | L56: =J56*K56 -> 36000
A57: Sunlight | B57: B133 | C57: =VLOOKUP($A57,Master!$B$50:$N$232,8,FALSE) -> 5000 | D57: =VLOOKUP($A57,Master!$B$50:$N$232,9,FALSE) -> ml | E57: =VLOOKUP($A57,Master!$B$50:$N$232,11,FALSE) -> Kurnia Mas | F57: 3 | G57: Pack | H57: 58500 | I57: TRUE | J57: 3 | K57: =VLOOKUP($A57,Master!$B$50:$N$232,6,FALSE) -> 54500 | L57: 57000
A58: Spons | B58: B143 | C58: =VLOOKUP($A58,Master!$B$50:$N$232,8,FALSE) -> 1 | D58: =VLOOKUP($A58,Master!$B$50:$N$232,9,FALSE) -> pcs | E58: =VLOOKUP($A58,Master!$B$50:$N$232,11,FALSE) -> PD Aroma Jaya | F58: 3 | G58: Pack | H58: 8400 | I58: TRUE | J58: 3 | K58: =VLOOKUP($A58,Master!$B$50:$N$232,6,FALSE) -> 2800 | L58: =J58*K58 -> 8400
A59: Biji Wijen | B59: B160 | C59: =VLOOKUP($A59,Master!$B$50:$N$232,8,FALSE) -> #N/A | D59: =VLOOKUP($A59,Master!$B$50:$N$232,9,FALSE) -> #N/A | E59: =VLOOKUP($A59,Master!$B$50:$N$232,11,FALSE) -> #N/A | F59: 1 | G59: Pack | H59: 22500 | I59: TRUE | J59: 1 | K59: =VLOOKUP($A59,Master!$B$50:$N$232,6,FALSE) -> #N/A | L59: =J59*K59 -> #N/A
A60: Taro Powder Health Today | B60: B013 | C60: =VLOOKUP($A60,Master!$B$50:$N$232,8,FALSE) -> #N/A | D60: =VLOOKUP($A60,Master!$B$50:$N$232,9,FALSE) -> #N/A | E60: =VLOOKUP($A60,Master!$B$50:$N$232,11,FALSE) -> #N/A | F60: 2 | G60: Pack | H60: 297000 | I60: TRUE | J60: 2 | K60: 135000 | L60: =J60*K60 -> 270000
A61: Red Velvet Powder Health Today | B61: B014 | C61: =VLOOKUP($A61,Master!$B$50:$N$232,8,FALSE) -> #N/A | D61: =VLOOKUP($A61,Master!$B$50:$N$232,9,FALSE) -> #N/A | E61: =VLOOKUP($A61,Master!$B$50:$N$232,11,FALSE) -> #N/A | F61: 2 | G61: Pack | H61: 297000 | I61: TRUE | J61: 2 | K61: 135000 | L61: =J61*K61 -> 270000
A62: Mint Syrup Health Today | B62: B123 | C62: =VLOOKUP($A62,Master!$B$50:$N$232,8,FALSE) -> #N/A | D62: =VLOOKUP($A62,Master!$B$50:$N$232,9,FALSE) -> #N/A | E62: =VLOOKUP($A62,Master!$B$50:$N$232,11,FALSE) -> #N/A | F62: 2 | G62: Bottle | H62: 188700 | I62: TRUE | J62: 2 | K62: =VLOOKUP($A62,Master!$B$50:$N$232,6,FALSE) -> #N/A | L62: 170000
A63: Blackcurrent Puree Health Today | B63: B127 | C63: =VLOOKUP($A63,Master!$B$50:$N$232,8,FALSE) -> #N/A | D63: =VLOOKUP($A63,Master!$B$50:$N$232,9,FALSE) -> #N/A | E63: =VLOOKUP($A63,Master!$B$50:$N$232,11,FALSE) -> #N/A | F63: 1 | G63: Bottle | H63: 216450 | I63: TRUE | J63: 1 | K63: 195000 | L63: =J63*K63 -> 195000
A64: Ice Cream Vanilla Diamond Sukanda | B64: B008 | C64: =VLOOKUP($A64,Master!$B$50:$N$232,8,FALSE) -> #N/A | D64: =VLOOKUP($A64,Master!$B$50:$N$232,9,FALSE) -> #N/A | E64: =VLOOKUP($A64,Master!$B$50:$N$232,11,FALSE) -> #N/A | F64: 2 | G64: Pail | H64: 315130 | I64: TRUE | J64: 2 | K64: =VLOOKUP($A64,Master!$B$50:$N$232,6,FALSE) -> #N/A | L64: =J64*K64 -> #N/A
A65: UHT Full Cream Diamond Sukanda | B65: B028 | C65: =VLOOKUP($A65,Master!$B$50:$N$232,8,FALSE) -> #N/A | D65: =VLOOKUP($A65,Master!$B$50:$N$232,9,FALSE) -> #N/A | E65: =VLOOKUP($A65,Master!$B$50:$N$232,11,FALSE) -> #N/A | F65: 3 | G65: Dus | H65: 545787 | I65: TRUE | J65: 3 | K65: =VLOOKUP($A65,Master!$B$50:$N$232,6,FALSE) -> #N/A | L65: =J65*K65 -> #N/A
A66: Freshmilk Diamond Sukanda | B66: B048 | C66: =VLOOKUP($A66,Master!$B$50:$N$232,8,FALSE) -> #N/A | D66: =VLOOKUP($A66,Master!$B$50:$N$232,9,FALSE) -> #N/A | E66: =VLOOKUP($A66,Master!$B$50:$N$232,11,FALSE) -> #N/A | F66: 3 | G66: Dus | H66: 608391 | I66: TRUE | J66: 3 | K66: =548100/3 -> 182700 | L66: 548100
A67: Tortilla Corn | B67: B106 | C67: =VLOOKUP($A67,Master!$B$50:$N$232,8,FALSE) -> 10 | D67: =VLOOKUP($A67,Master!$B$50:$N$232,9,FALSE) -> pcs | E67: =VLOOKUP($A67,Master!$B$50:$N$232,11,FALSE) -> Setiabudi Market | F67: 2 | G67: Pack | H67: 26000 | I67: TRUE | J67: 4 | K67: =VLOOKUP($A67,Master!$B$50:$N$232,6,FALSE) -> 16900 | L67: 55836
A68: Soy Milk Drinho | B68: B007 | C68: =VLOOKUP($A68,Master!$B$50:$N$232,8,FALSE) -> #N/A | D68: =VLOOKUP($A68,Master!$B$50:$N$232,9,FALSE) -> #N/A | E68: =VLOOKUP($A68,Master!$B$50:$N$232,11,FALSE) -> #N/A | F68: 2 | G68: Pack | H68: 30400 | I68: TRUE | J68: 2 | K68: =VLOOKUP($A68,Master!$B$50:$N$232,6,FALSE) -> #N/A | L68: 32495
A69: Much & More Woodlane Custom | B69: B006 | C69: =VLOOKUP($A69,Master!$B$50:$N$232,8,FALSE) -> 1000 | D69: =VLOOKUP($A69,Master!$B$50:$N$232,9,FALSE) -> gr | E69: =VLOOKUP($A69,Master!$B$50:$N$232,11,FALSE) -> Woodlane | F69: 2 | G69: Kilogram | H69: 340000 | I69: TRUE | J69: 2 | K69: =VLOOKUP($A69,Master!$B$50:$N$232,6,FALSE) -> 170000 | L69: =J69*K69 -> 340000
A70: Single Origin 85k | B70: B021 | C70: =VLOOKUP($A70,Master!$B$50:$N$232,8,FALSE) -> 200 | D70: =VLOOKUP($A70,Master!$B$50:$N$232,9,FALSE) -> gr | E70: =VLOOKUP($A70,Master!$B$50:$N$232,11,FALSE) -> Woodlane | F70: 2 | G70: Pack | H70: 170000 | I70: TRUE | J70: 2 | K70: =VLOOKUP($A70,Master!$B$50:$N$240,6,FALSE) -> 85000 | L70: =J70*K70 -> 170000
F72: 44746 | J72: =F72+1 -> 44747
F73: Total PO | H73: =SUM(H75:H230) -> 900760146 | J73: Data Aktual | L73: =SUM(L75:L230) -> #N/A
A74: Remark | B74: Kode | C74: Qty/pack | D74: Unit | E74: toko | F74: PO Pack | G74: Unit Pack | H74: PO Bill | I74: Checker | J74: Bought | K74: Price/Pack | L74: Bill | M74: Keterangan
A75: Beef Topside | B75: B032 | C75: =VLOOKUP($A75,Master!$B$50:$N$232,8,FALSE) -> 1000 | D75: =VLOOKUP($A75,Master!$B$50:$N$232,9,FALSE) -> gr | E75: =VLOOKUP($A75,Master!$B$50:$N$232,11,FALSE) -> BISS (Topside) | F75: 1 | G75: Kilogram | H75: 145000 | I75: TRUE | J75: 1 | K75: =VLOOKUP($A75,Master!$B$50:$N$232,6,FALSE) -> 145000 | L75: 130000 | M75: Dtg 6/7/22
A76: Pocky Choco Stick | B76: B018 | C76: =VLOOKUP($A76,Master!$B$50:$N$232,8,FALSE) -> 20 | D76: =VLOOKUP($A76,Master!$B$50:$N$232,9,FALSE) -> pcs | E76: =VLOOKUP($A76,Master!$B$50:$N$232,11,FALSE) -> Kurnia Mas | F76: 2 | G76: Pack | H76: 14600 | I76: TRUE | J76: 2 | K76: 7950 | L76: 15741
A77: Orange Sunkist Fruit | B77: B029 | C77: =VLOOKUP($A77,Master!$B$50:$N$232,8,FALSE) -> 1000 | D77: =VLOOKUP($A77,Master!$B$50:$N$232,9,FALSE) -> gr | E77: =VLOOKUP($A77,Master!$B$50:$N$232,11,FALSE) -> Borma | F77: 0.5 | G77: Kilogram | H77: 31900 | I77: TRUE | J77: 0.694 | K77: =VLOOKUP($A77,Master!$B$50:$N$232,6,FALSE) -> 35550 | L77: 18895
A78: Lemon Fruit | B78: B030 | C78: =VLOOKUP($A78,Master!$B$50:$N$232,8,FALSE) -> 1000 | D78: =VLOOKUP($A78,Master!$B$50:$N$232,9,FALSE) -> gr | E78: =VLOOKUP($A78,Master!$B$50:$N$232,11,FALSE) -> Borma | F78: 1 | G78: Kilogram | H78: 16000 | I78: TRUE | J78: 1 | K78: =VLOOKUP($A78,Master!$B$50:$N$232,6,FALSE) -> 18000 | L78: 15000
A79: Chocolate Mariza Topping | B79: B065 | C79: =VLOOKUP($A79,Master!$B$50:$N$232,8,FALSE) -> #N/A | D79: =VLOOKUP($A79,Master!$B$50:$N$232,9,FALSE) -> #N/A | E79: =VLOOKUP($A79,Master!$B$50:$N$232,11,FALSE) -> #N/A | F79: 1 | G79: Bottle | H79: 26350 | I79: TRUE | J79: 1 | K79: 27950 | L79: 27671
A80: Pocky Strawberry Stick | B80: B115 | C80: =VLOOKUP($A80,Master!$B$50:$N$232,8,FALSE) -> 20 | D80: =VLOOKUP($A80,Master!$B$50:$N$232,9,FALSE) -> pcs | E80: =VLOOKUP($A80,Master!$B$50:$N$232,11,FALSE) -> Borma | F80: 2 | G80: Pack | H80: 15100 | I80: FALSE | K80: =VLOOKUP($A80,Master!$B$50:$N$232,6,FALSE) -> 8500 | L80: =J80*K80 -> 0 | M80: Kosong
A81: Detergen Daia | B81: B132 | C81: =VLOOKUP($A81,Master!$B$50:$N$232,8,FALSE) -> 1700 | D81: =VLOOKUP($A81,Master!$B$50:$N$232,9,FALSE) -> gr | E81: =VLOOKUP($A81,Master!$B$50:$N$232,11,FALSE) -> Borma | F81: 1 | G81: Pack | H81: 17900 | I81: TRUE | J81: 1 | K81: =VLOOKUP($A81,Master!$B$50:$N$232,6,FALSE) -> 30938 | L81: 17721
A82: HandSoap Yuri | B82: B150 | C82: =VLOOKUP($A82,Master!$B$50:$N$232,8,FALSE) -> #N/A | D82: =VLOOKUP($A82,Master!$B$50:$N$232,9,FALSE) -> #N/A | E82: =VLOOKUP($A82,Master!$B$50:$N$232,11,FALSE) -> #N/A | F82: 1 | G82: Pack | H82: 22300 | I82: TRUE | J82: 1 | K82: =VLOOKUP($A82,Master!$B$50:$N$232,6,FALSE) -> #N/A | L82: 10841 | M82: Yoa
A83: Pledge Pembersih Kayu | B83: B178 | C83: =VLOOKUP($A83,Master!$B$50:$N$232,8,FALSE) -> #N/A | D83: =VLOOKUP($A83,Master!$B$50:$N$232,9,FALSE) -> #N/A | E83: =VLOOKUP($A83,Master!$B$50:$N$232,11,FALSE) -> #N/A | F83: 1 | G83: Pack | H83: 19650 | I83: TRUE | J83: 1 | K83: =VLOOKUP($A83,Master!$B$50:$N$232,6,FALSE) -> #N/A | L83: 19454
A84: Vit Mineral Water 600ml | B84: B087 | C84: =VLOOKUP($A84,Master!$B$50:$N$232,8,FALSE) -> #N/A | D84: =VLOOKUP($A84,Master!$B$50:$N$232,9,FALSE) -> #N/A | E84: =VLOOKUP($A84,Master!$B$50:$N$232,11,FALSE) -> #N/A | F84: 6 | G84: Dus | H84: 121600 | I84: TRUE | J84: 6 | K84: =VLOOKUP($A84,Master!$B$50:$N$232,6,FALSE) -> #N/A | L84: =J84*K84 -> #N/A | M84: Dtg 8/7/22
A85: Green Tea Powder Dillco | B85: B015 | C85: =VLOOKUP($A85,Master!$B$50:$N$232,8,FALSE) -> #N/A | D85: =VLOOKUP($A85,Master!$B$50:$N$232,9,FALSE) -> #N/A | E85: =VLOOKUP($A85,Master!$B$50:$N$232,11,FALSE) -> #N/A | F85: 1 | G85: Pack | H85: 170000 | I85: TRUE | J85: 1 | K85: =VLOOKUP($A85,Master!$B$50:$N$232,6,FALSE) -> #N/A | L85: =J85*K85 -> #N/A
A86: Powder Chocolate Origin Andalas | B86: B016 | C86: =VLOOKUP($A86,Master!$B$50:$N$232,8,FALSE) -> #N/A | D86: =VLOOKUP($A86,Master!$B$50:$N$232,9,FALSE) -> #N/A | E86: =VLOOKUP($A86,Master!$B$50:$N$232,11,FALSE) -> #N/A | F86: 2 | G86: Pack | H86: 440000 | I86: TRUE | J86: 2 | K86: =VLOOKUP($A86,Master!$B$50:$N$232,6,FALSE) -> #N/A | L86: =J86*K86 -> #N/A
A87: Wortel Grade A | B87: B035 | C87: =VLOOKUP($A87,Master!$B$50:$N$232,8,FALSE) -> 1000 | D87: =VLOOKUP($A87,Master!$B$50:$N$232,9,FALSE) -> gr | E87: =VLOOKUP($A87,Master!$B$50:$N$232,11,FALSE) -> Eden Farm | F87: 1.5 | G87: Kilogram | H87: 19400 | I87: TRUE | J87: 2 | K87: 10200 | L87: =J87*K87 -> 20400
A88: Ayam Boneless Dada | B88: B036 | C88: =VLOOKUP($A88,Master!$B$50:$N$232,8,FALSE) -> 1000 | D88: =VLOOKUP($A88,Master!$B$50:$N$232,9,FALSE) -> gr | E88: =VLOOKUP($A88,Master!$B$50:$N$232,11,FALSE) -> Toko Lain | F88: 3 | G88: Kilogram | H88: 146700 | I88: TRUE | J88: 3 | K88: 50000 | L88: =J88*K88 -> 150000 | M88: A Cecep Ktc
A89: Cabe Rawit | B89: B040 | C89: =VLOOKUP($A89,Master!$B$50:$N$232,8,FALSE) -> 1000 | D89: =VLOOKUP($A89,Master!$B$50:$N$232,9,FALSE) -> gr | E89: =VLOOKUP($A89,Master!$B$50:$N$232,11,FALSE) -> Eden Farm | F89: 1 | G89: Kilogram | H89: 28300 | I89: TRUE | J89: 1 | K89: 110000 | L89: =J89*K89 -> 110000
A90: Bawang Bombay | B90: B055 | C90: =VLOOKUP($A90,Master!$B$50:$N$232,8,FALSE) -> 1000 | D90: =VLOOKUP($A90,Master!$B$50:$N$232,9,FALSE) -> gr | E90: =VLOOKUP($A90,Master!$B$50:$N$232,11,FALSE) -> Eden Farm | F90: 3 | G90: Kilogram | H90: 56700 | I90: TRUE | J90: 3 | K90: =VLOOKUP($A90,Master!$B$50:$N$232,6,FALSE) -> 40000 | L90: 54000
A91: Paprika Green | B91: B058 | C91: =VLOOKUP($A91,Master!$B$50:$N$232,8,FALSE) -> 1000 | D91: =VLOOKUP($A91,Master!$B$50:$N$232,9,FALSE) -> gr | E91: =VLOOKUP($A91,Master!$B$50:$N$232,11,FALSE) -> Eden Farm | F91: 0.5 | G91: Kilogram | H91: 44900 | I91: TRUE | J91: 0.5 | K91: 54500 | L91: =J91*K91 -> 27250
A92: Strawberry Fruit | B92: B069 | C92: =VLOOKUP($A92,Master!$B$50:$N$232,8,FALSE) -> 500 | D92: =VLOOKUP($A92,Master!$B$50:$N$232,9,FALSE) -> gr | E92: =VLOOKUP($A92,Master!$B$50:$N$232,11,FALSE) -> Toko Lain | F92: 3 | G92: Pack | H92: 23100 | I92: TRUE | J92: 1 | K92: =VLOOKUP($A92,Master!$B$50:$N$232,6,FALSE) -> 25000 | L92: 50000 | M92: Direct 1kg
A93: Tomato Cherry | B93: B109 | C93: =VLOOKUP($A93,Master!$B$50:$N$232,8,FALSE) -> 1000 | D93: =VLOOKUP($A93,Master!$B$50:$N$232,9,FALSE) -> gr | E93: =VLOOKUP($A93,Master!$B$50:$N$232,11,FALSE) -> Eden Farm | F93: 1.5 | G93: Kilogram | H93: 79800 | I93: TRUE | J93: 1.5 | K93: =VLOOKUP($A93,Master!$B$50:$N$232,6,FALSE) -> 50000 | L93: 51900
A94: Buncis | B94: B144 | C94: =VLOOKUP($A94,Master!$B$50:$N$232,8,FALSE) -> 1000 | D94: =VLOOKUP($A94,Master!$B$50:$N$232,9,FALSE) -> gr | E94: =VLOOKUP($A94,Master!$B$50:$N$232,11,FALSE) -> Eden Farm | F94: 1 | G94: Kilogram | H94: 21800 | I94: TRUE | J94: 1 | K94: =VLOOKUP($A94,Master!$B$50:$N$232,6,FALSE) -> 24000 | L94: 17500
A95: Jagung Manis Kupas | B95: B156 | C95: =VLOOKUP($A95,Master!$B$50:$N$232,8,FALSE) -> #N/A | D95: =VLOOKUP($A95,Master!$B$50:$N$232,9,FALSE) -> #N/A | E95: =VLOOKUP($A95,Master!$B$50:$N$232,11,FALSE) -> #N/A | F95: 1 | G95: Kilogram | H95: 9500 | I95: TRUE | J95: 1 | K95: 9900 | L95: =J95*K95 -> 9900
A96: Gula Putih Sachet | B96: B184 | C96: =VLOOKUP($A96,Master!$B$50:$N$240,8,FALSE) -> #N/A | D96: =VLOOKUP($A96,Master!$B$50:$N$240,9,FALSE) -> #N/A | E96: B5 | F96: 2 | G96: Pack | H96: 140000 | I96: TRUE | J96: 2 | K96: 45000 | L96: =J96*K96 -> 90000
A97: Gas 12 Kg | B97: B186 | C97: =VLOOKUP($A97,Master!$B$50:$N$240,8,FALSE) -> #N/A | D97: =VLOOKUP($A97,Master!$B$50:$N$240,9,FALSE) -> #N/A | E97: Limas Raga Inti | F97: 2 | G97: Tabung | H97: 387400 | I97: TRUE | J97: 2 | K97: =VLOOKUP($A97,Master!$B$50:$N$240,6,FALSE) -> #N/A | L97: =J97*K97 -> #N/A
A98: Kertas Thermal 80x80 mm | B98: B177 | C98: =VLOOKUP($A98,Master!$B$50:$N$232,8,FALSE) -> #N/A | D98: =VLOOKUP($A98,Master!$B$50:$N$232,9,FALSE) -> #N/A | E98: =VLOOKUP($A98,Master!$B$50:$N$232,11,FALSE) -> #N/A | F98: 10 | G98: Pack | H98: 145000 | I98: TRUE | J98: 10 | K98: 15500 | L98: =J98*K98 -> 155000
A99: Rum Syrup Davinci LMK | B99: B010 | C99: =VLOOKUP($A99,Master!$B$50:$N$232,8,FALSE) -> #N/A | D99: =VLOOKUP($A99,Master!$B$50:$N$232,9,FALSE) -> #N/A | E99: =VLOOKUP($A99,Master!$B$50:$N$232,11,FALSE) -> #N/A | F99: 1 | G99: Bottle | H99: 137000 | I99: TRUE | J99: 1 | K99: =VLOOKUP($A99,Master!$B$50:$N$232,6,FALSE) -> #N/A | L99: 135420
A100: Vanilla Syrup Davinci LMK | B100: B025 | C100: =VLOOKUP($A100,Master!$B$50:$N$232,8,FALSE) -> #N/A | D100: =VLOOKUP($A100,Master!$B$50:$N$232,9,FALSE) -> #N/A | E100: =VLOOKUP($A100,Master!$B$50:$N$232,11,FALSE) -> #N/A | F100: 1 | G100: Bottle | H100: 137000 | I100: TRUE | J100: 1 | K100: =VLOOKUP($A100,Master!$B$50:$N$232,6,FALSE) -> #N/A | L100: 135420
A101: Hazelnut Syrup Davinci LMK | B101: B026 | C101: =VLOOKUP($A101,Master!$B$50:$N$232,8,FALSE) -> #N/A | D101: =VLOOKUP($A101,Master!$B$50:$N$232,9,FALSE) -> #N/A | E101: =VLOOKUP($A101,Master!$B$50:$N$232,11,FALSE) -> #N/A | F101: 1 | G101: Bottle | H101: 137000 | I101: TRUE | J101: 1 | K101: =VLOOKUP($A101,Master!$B$50:$N$232,6,FALSE) -> #N/A | L101: 135420
A102: Caramel Syrup Davinci LMK | B102: B027 | C102: =VLOOKUP($A102,Master!$B$50:$N$232,8,FALSE) -> #N/A | D102: =VLOOKUP($A102,Master!$B$50:$N$232,9,FALSE) -> #N/A | E102: =VLOOKUP($A102,Master!$B$50:$N$232,11,FALSE) -> #N/A | F102: 1 | G102: Bottle | H102: 137000 | I102: TRUE | J102: 1 | K102: =VLOOKUP($A102,Master!$B$50:$N$232,6,FALSE) -> #N/A | L102: 135420
A103: Cireng | B103: B041 | C103: =VLOOKUP($A103,Master!$B$50:$N$232,8,FALSE) -> 20 | D103: =VLOOKUP($A103,Master!$B$50:$N$232,9,FALSE) -> unit | E103: =VLOOKUP($A103,Master!$B$50:$N$232,11,FALSE) -> RSB, Dago | F103: 20 | G103: Pack | H103: 120000 | I103: TRUE | J103: 20 | K103: =VLOOKUP($A103,Master!$B$50:$N$232,6,FALSE) -> 13500 | L103: =J103*K103 -> 270000
...

Sheet History Juni 2022
A1: History Mei 2022 | B1: Juni 2022
A2: The Soko Coffee Tea Chocolate
F5: 44715 | J5: =F5+1 -> 44716
F6: Total PO | H6: =SUM(H8:H149) -> 866991000 | J6: Data Aktual | L6: =SUM(L8:L149) -> #N/A
A7: Remark | B7: Kode | C7: Qty/pack | D7: Unit | E7: toko | F7: PO Pack | G7: Unit Pack | H7: PO Bill | I7: Checker | J7: Bought | K7: Price/Pack | L7: Bill | M7: Keterangan
A8: Stirrer / Straw Strip | B8: =VLOOKUP($A8,Master!$B$50:$N$232,2,FALSE) -> B129 | C8: =VLOOKUP($A8,Master!$B$50:$N$232,8,FALSE) -> 100 | D8: =VLOOKUP($A8,Master!$B$50:$N$232,9,FALSE) -> pcs | E8: =VLOOKUP($A8,Master!$B$50:$N$232,11,FALSE) -> Ade Widya Plastik Cikutra | F8: 1 | G8: Pack | H8: 3600 | I8: TRUE | J8: 1 | K8: 14000 | L8: =J8*K8 -> 14000 | M8: Pasar(sedotan Hitam)
A9: Plastik Wrape | B9: =VLOOKUP($A9,Master!$B$50:$N$232,2,FALSE) -> #N/A | C9: =VLOOKUP($A9,Master!$B$50:$N$232,8,FALSE) -> #N/A | D9: =VLOOKUP($A9,Master!$B$50:$N$232,9,FALSE) -> #N/A | E9: =VLOOKUP($A9,Master!$B$50:$N$232,11,FALSE) -> #N/A | F9: 1 | G9: Pack | H9: 18000 | I9: TRUE | J9: 1 | K9: 24000 | L9: =J9*K9 -> 24000
A10: Tissue Roll | B10: =VLOOKUP($A10,Master!$B$50:$N$232,2,FALSE) -> #N/A | C10: =VLOOKUP($A10,Master!$B$50:$N$232,8,FALSE) -> #N/A | D10: =VLOOKUP($A10,Master!$B$50:$N$232,9,FALSE) -> #N/A | E10: =VLOOKUP($A10,Master!$B$50:$N$232,11,FALSE) -> #N/A | F10: 2 | G10: Pack | H10: 9400 | I10: TRUE | J10: 2 | K10: 9200 | L10: =J10*K10 -> 18400
